Workbook
Name SegmentaçãodeDados_CLIENTE1: #N/A
Name SegmentaçãodeDados_ID_SITE1: #N/A

Sheet PLANEJAMENTO
A1: ID SITE | B1: IDEX CONTEL | C1: CLIENTE | D1: CIDADE | E1: ESTADO | F1: LOCALIZAÇÃO | G1: SIENGE | H1: OS TOWER SYSTEM | I1: ANALISTA CONTEL | J1: VALOR EMPREITA | K1: MATERIAL | L1: FRETE/DEMAIS ITENS | M1: ETAPA | N1: STATUS | O1: ORÇAMENTO (RECEITA) (R$) | P1: CUSTOS TOTAIS (R$) | Q1: LUCRO (R$) | R1: M.C% | S1: STATUS VIABILIDADE | T1: STATUS PRAZO
A2: BR88410-A | B2: =IF(A2<>"","contel-"&TEXT(COUNTA($A$2:A2),"00"),"") -> contel-01 | C2: SBA | D2: CUJIBIM | E2: RO | F2: https://maps.app.goo.gl/Bpy8uL8ayiBD3Kdj7 | G2: 1457 | H2: 15869 | I2: PEDRO | J2: =SUM(EQUIPE!C2,EQUIPE!E2,EQUIPE!G2,EQUIPE!I2,EQUIPE!K2,EQUIPE!M2,EQUIPE!O2) -> 11006 | K2: 5615.61 | L2: 1600 | M2: =IFERROR(LEFT( IF(INDEX('ETAPA OBRA'!C:C,MATCH($B2,'ETAPA OBRA'!$B:$B,0))="x",'ETAPA OBRA'!C$1&", ","")& IF(INDEX('ETAPA OBRA'!D:D,MATCH($B2,'ETAPA OBRA'!$B:$B,0))="x",'ETAPA OBRA'!D$1&", ","")& IF(INDEX('ETAPA OBRA'!F:F,MATCH($B2,'ETAPA OBRA'!$B:$B,0))="x",'ETAPA OBRA'!F$1&", ","")& IF(INDEX('ETAPA OBRA'!G:G,MATCH($B2,'ETAPA OBRA'!$B:$B,0))="x",'ETAPA OBRA'!G$1&", ","")& IF(INDEX('ETAPA OBRA'!H:H,MATCH($B2,'ETAPA OBRA'!$B:$B,0))="x",'ETAPA OBRA'!H$1&", ","")& IF(INDEX('ETAPA OBRA'!I:I,MATCH($B2,'ETAPA OBRA'!$B:$B,0))="x",'ETAPA OBRA'!I$1&", ","")& IF(INDEX('ETAPA OBRA'!J:J,MATCH($B2,'ETAPA OBRA'!$B:$B,0))="x",'ETAPA OBRA'!J$1&", ","")& IF(INDEX('ETAPA OBRA'!K:K,MATCH($B2,'ETAPA OBRA'!$B:$B,0))="x",'ETAPA OBRA'!K$1&", ","")& IF(INDEX('ETAPA OBRA'!L:L,MATCH($B2,'ETAPA OBRA'!$B:$B,0))="x",'ETAPA OBRA'!L$1&", ","")& IF(INDEX('ETAPA OBRA'!M:M,MATCH($B2,'ETAPA OBRA'!$B:$B,0))="x",'ETAPA OBRA'!M$1&", ","")& IF(INDEX('ETAPA OBRA'!N:N,MATCH($B2,'ETAPA OBRA'!$B:$B,0))="x",'ETAPA OBRA'!N$1&", ","")& IF(INDEX('ETAPA OBRA'!O:O,MATCH($B2,'ETAPA OBRA'!$B:$B,0))="x",'ETAPA OBRA'!O$1&", ","")& IF(INDEX('ETAPA OBRA'!P:P,MATCH($B2,'ETAPA OBRA'!$B:$B,0))="x",'ETAPA OBRA'!P$1&", ","")& IF(INDEX('ETAPA OBRA'!Q:Q,MATCH($B2,'ETAPA OBRA'!$B:$B,0))="x",'ETAPA OBRA'!Q$1&", ","")& IF(INDEX('ETAPA OBRA'!R:R,MATCH($B2,'ETAPA OBRA'!$B:$B,0))="x",'ETAPA OBRA'!R$1&", ","")& IF(INDEX('ETAPA OBRA'!S:S,MATCH($B2,'ETAPA OBRA'!$B:$B,0))="x",'ETAPA OBRA'!S$1&", ","")& IF(INDEX('ETAPA OBRA'!T:T,MATCH($B2,'ETAPA OBRA'!$B:$B,0))="x",'ETAPA OBRA'!T$1&", ","")& IF(INDEX('ETAPA OBRA'!U:U,MATCH($B2,'ETAPA OBRA'!$B:$B,0))="x",'ETAPA OBRA'!U$1&", ",""),LEN( IF(INDEX('ETAPA OBRA'!C:C,MATCH($B2,'ETAPA OBRA'!$B:$B,0))="x",'ETAPA OBRA'!C$1&", ","")& IF(INDEX('ETAPA OBRA'!D:D,MATCH($B2,'ETAPA OBRA'!$B:$B,0))="x",'ETAPA OBRA'!D$1&", ","")& IF(INDEX('ETAPA OBRA'!F:F,MATCH($B2,'ETAPA OBRA'!$B:$B,0))="x",'ETAPA OBRA'!F$1&", ","")& IF(INDEX('ETAPA OBRA'!G:G,MATCH($B2,'ETAPA OBRA'!$B:$B,0))="x",'ETAPA OBRA'!G$1&", ","")& IF(INDEX('ETAPA OBRA'!H:H,MATCH($B2,'ETAPA OBRA'!$B:$B,0))="x",'ETAPA OBRA'!H$1&", ","")& IF(INDEX('ETAPA OBRA'!I:I,MATCH($B2,'ETAPA OBRA'!$B:$B,0))="x",'ETAPA OBRA'!I$1&", ","")& IF(INDEX('ETAPA OBRA'!J:J,MATCH($B2,'ETAPA OBRA'!$B:$B,0))="x",'ETAPA OBRA'!J$1&", ","")& IF(INDEX('ETAPA OBRA'!K:K,MATCH($B2,'ETAPA OBRA'!$B:$B,0))="x",'ETAPA OBRA'!K$1&", ","")& IF(INDEX('ETAPA OBRA'!L:L,MATCH($B2,'ETAPA OBRA'!$B:$B,0))="x",'ETAPA OBRA'!L$1&", ","")& IF(INDEX('ETAPA OBRA'!M:M,MATCH($B2,'ETAPA OBRA'!$B:$B,0))="x",'ETAPA OBRA'!M$1&", ","")& IF(INDEX('ETAPA OBRA'!N:N,MATCH($B2,'ETAPA OBRA'!$B:$B,0))="x",'ETAPA OBRA'!N$1&", ","")& IF(INDEX('ETAPA OBRA'!O:O,MATCH($B2,'ETAPA OBRA'!$B:$B,0))="x",'ETAPA OBRA'!O$1&", ","")& IF(INDEX('ETAPA OBRA'!P:P,MATCH($B2,'ETAPA OBRA'!$B:$B,0))="x",'ETAPA OBRA'!P$1&", ","")& IF(INDEX('ETAPA OBRA'!Q:Q,MATCH($B2,'ETAPA OBRA'!$B:$B,0))="x",'ETAPA OBRA'!Q$1&", ","")& IF(INDEX('ETAPA OBRA'!R:R,MATCH($B2,'ETAPA OBRA'!$B:$B,0))="x",'ETAPA OBRA'!R$1&", ","")& IF(INDEX('ETAPA OBRA'!S:S,MATCH($B2,'ETAPA OBRA'!$B:$B,0))="x",'ETAPA OBRA'!S$1&", ","")& IF(INDEX('ETAPA OBRA'!T:T,MATCH($B2,'ETAPA OBRA'!$B:$B,0))="x",'ETAPA OBRA'!T$1&", ","")& IF(INDEX('ETAPA OBRA'!U:U,MATCH($B2,'ETAPA OBRA'!$B:$B,0))="x",'ETAPA OBRA'!U$1&", ","") )-2),"") -> Finalizado | N2: =IF(M2="","Não iniciada", IF(ISNUMBER(FIND("Cancelada",M2)),"Cancelada", IF(ISNUMBER(FIND("Paralisada",M2)),"Paralisada", IF(ISNUMBER(FIND("Finalizado",M2)),"Finalizado", "Em andamento")))) -> Finalizado | O2: 38900.7 | P2: =SUM($J2:$L2) -> 18221.61 | Q2: =O2-P2 -> 20679.09 | R2: =IF(O2=0,0,Q2/O2) -> 0.53158658 | S2: =IF(R2>=0.2,"✅ OK - Fechar Parceiro","⚠️ Ajustar Custos (<20%)") -> ✅ OK - Fechar Parceiro | T2: =Cronograma[[#This Row],[STATUS]] -> ✅ CONCLUÍDO
A3: BR87873-R | B3: =IF(A3<>"","contel-"&TEXT(COUNTA($A$2:A3),"00"),"") -> contel-02 | C3: SBA | D3: GOIÂNIA | E3: GO | F3: https://maps.app.goo.gl/TnE3sh9j2FyxrzrFA | G3: 1527 | H3: 16078 | I3: PEDRO | J3: =SUM(EQUIPE!C3,EQUIPE!E3,EQUIPE!G3,EQUIPE!I3,EQUIPE!K3,EQUIPE!M3,EQUIPE!O3) -> 800 | K3: 1087.53 | L3: 804.64 | M3: =IFERROR(LEFT( IF(INDEX('ETAPA OBRA'!C:C,MATCH($B3,'ETAPA OBRA'!$B:$B,0))="x",'ETAPA OBRA'!C$1&", ","")& IF(INDEX('ETAPA OBRA'!D:D,MATCH($B3,'ETAPA OBRA'!$B:$B,0))="x",'ETAPA OBRA'!D$1&", ","")& IF(INDEX('ETAPA OBRA'!F:F,MATCH($B3,'ETAPA OBRA'!$B:$B,0))="x",'ETAPA OBRA'!F$1&", ","")& IF(INDEX('ETAPA OBRA'!G:G,MATCH($B3,'ETAPA OBRA'!$B:$B,0))="x",'ETAPA OBRA'!G$1&", ","")& IF(INDEX('ETAPA OBRA'!H:H,MATCH($B3,'ETAPA OBRA'!$B:$B,0))="x",'ETAPA OBRA'!H$1&", ","")& IF(INDEX('ETAPA OBRA'!I:I,MATCH($B3,'ETAPA OBRA'!$B:$B,0))="x",'ETAPA OBRA'!I$1&", ","")& IF(INDEX('ETAPA OBRA'!J:J,MATCH($B3,'ETAPA OBRA'!$B:$B,0))="x",'ETAPA OBRA'!J$1&", ","")& IF(INDEX('ETAPA OBRA'!K:K,MATCH($B3,'ETAPA OBRA'!$B:$B,0))="x",'ETAPA OBRA'!K$1&", ","")& IF(INDEX('ETAPA OBRA'!L:L,MATCH($B3,'ETAPA OBRA'!$B:$B,0))="x",'ETAPA OBRA'!L$1&", ","")& IF(INDEX('ETAPA OBRA'!M:M,MATCH($B3,'ETAPA OBRA'!$B:$B,0))="x",'ETAPA OBRA'!M$1&", ","")& IF(INDEX('ETAPA OBRA'!N:N,MATCH($B3,'ETAPA OBRA'!$B:$B,0))="x",'ETAPA OBRA'!N$1&", ","")& IF(INDEX('ETAPA OBRA'!O:O,MATCH($B3,'ETAPA OBRA'!$B:$B,0))="x",'ETAPA OBRA'!O$1&", ","")& IF(INDEX('ETAPA OBRA'!P:P,MATCH($B3,'ETAPA OBRA'!$B:$B,0))="x",'ETAPA OBRA'!P$1&", ","")& IF(INDEX('ETAPA OBRA'!Q:Q,MATCH($B3,'ETAPA OBRA'!$B:$B,0))="x",'ETAPA OBRA'!Q$1&", ","")& IF(INDEX('ETAPA OBRA'!R:R,MATCH($B3,'ETAPA OBRA'!$B:$B,0))="x",'ETAPA OBRA'!R$1&", ","")& IF(INDEX('ETAPA OBRA'!S:S,MATCH($B3,'ETAPA OBRA'!$B:$B,0))="x",'ETAPA OBRA'!S$1&", ","")& IF(INDEX('ETAPA OBRA'!T:T,MATCH($B3,'ETAPA OBRA'!$B:$B,0))="x",'ETAPA OBRA'!T$1&", ","")& IF(INDEX('ETAPA OBRA'!U:U,MATCH($B3,'ETAPA OBRA'!$B:$B,0))="x",'ETAPA OBRA'!U$1&", ",""),LEN( IF(INDEX('ETAPA OBRA'!C:C,MATCH($B3,'ETAPA OBRA'!$B:$B,0))="x",'ETAPA OBRA'!C$1&", ","")& IF(INDEX('ETAPA OBRA'!D:D,MATCH($B3,'ETAPA OBRA'!$B:$B,0))="x",'ETAPA OBRA'!D$1&", ","")& IF(INDEX('ETAPA OBRA'!F:F,MATCH($B3,'ETAPA OBRA'!$B:$B,0))="x",'ETAPA OBRA'!F$1&", ","")& IF(INDEX('ETAPA OBRA'!G:G,MATCH($B3,'ETAPA OBRA'!$B:$B,0))="x",'ETAPA OBRA'!G$1&", ","")& IF(INDEX('ETAPA OBRA'!H:H,MATCH($B3,'ETAPA OBRA'!$B:$B,0))="x",'ETAPA OBRA'!H$1&", ","")& IF(INDEX('ETAPA OBRA'!I:I,MATCH($B3,'ETAPA OBRA'!$B:$B,0))="x",'ETAPA OBRA'!I$1&", ","")& IF(INDEX('ETAPA OBRA'!J:J,MATCH($B3,'ETAPA OBRA'!$B:$B,0))="x",'ETAPA OBRA'!J$1&", ","")& IF(INDEX('ETAPA OBRA'!K:K,MATCH($B3,'ETAPA OBRA'!$B:$B,0))="x",'ETAPA OBRA'!K$1&", ","")& IF(INDEX('ETAPA OBRA'!L:L,MATCH($B3,'ETAPA OBRA'!$B:$B,0))="x",'ETAPA OBRA'!L$1&", ","")& IF(INDEX('ETAPA OBRA'!M:M,MATCH($B3,'ETAPA OBRA'!$B:$B,0))="x",'ETAPA OBRA'!M$1&", ","")& IF(INDEX('ETAPA OBRA'!N:N,MATCH($B3,'ETAPA OBRA'!$B:$B,0))="x",'ETAPA OBRA'!N$1&", ","")& IF(INDEX('ETAPA OBRA'!O:O,MATCH($B3,'ETAPA OBRA'!$B:$B,0))="x",'ETAPA OBRA'!O$1&", ","")& IF(INDEX('ETAPA OBRA'!P:P,MATCH($B3,'ETAPA OBRA'!$B:$B,0))="x",'ETAPA OBRA'!P$1&", ","")& IF(INDEX('ETAPA OBRA'!Q:Q,MATCH($B3,'ETAPA OBRA'!$B:$B,0))="x",'ETAPA OBRA'!Q$1&", ","")& IF(INDEX('ETAPA OBRA'!R:R,MATCH($B3,'ETAPA OBRA'!$B:$B,0))="x",'ETAPA OBRA'!R$1&", ","")& IF(INDEX('ETAPA OBRA'!S:S,MATCH($B3,'ETAPA OBRA'!$B:$B,0))="x",'ETAPA OBRA'!S$1&", ","")& IF(INDEX('ETAPA OBRA'!T:T,MATCH($B3,'ETAPA OBRA'!$B:$B,0))="x",'ETAPA OBRA'!T$1&", ","")& IF(INDEX('ETAPA OBRA'!U:U,MATCH($B3,'ETAPA OBRA'!$B:$B,0))="x",'ETAPA OBRA'!U$1&", ","") )-2),"") -> Finalizado | N3: =IF(M3="","Não iniciada", IF(ISNUMBER(FIND("Cancelada",M3)),"Cancelada", IF(ISNUMBER(FIND("Paralisada",M3)),"Paralisada", IF(ISNUMBER(FIND("Finalizado",M3)),"Finalizado", "Em andamento")))) -> Finalizado | O3: 5055.68 | P3: =SUM($J3:$L3) -> 2692.17 | Q3: =O3-P3 -> 2363.51 | R3: =IF(O3=0,0,Q3/O3) -> 0.46749596 | S3: =IF(R3>=0.2,"✅ OK - Fechar Parceiro","⚠️ Ajustar Custos (<20%)") -> ✅ OK - Fechar Parceiro | T3: =Cronograma[[#This Row],[STATUS]] -> ✅ CONCLUÍDO
A4: BR72396-A | B4: =IF(A4<>"","contel-"&TEXT(COUNTA($A$2:A4),"00"),"") -> contel-03 | C4: SBA | D4: PONTE NOVA | E4: MG | F4: https://maps.app.goo.gl/5FumfAyzjMHGaKJY8 | G4: 1582 | H4: 15870 | I4: DANIEL | J4: =SUM(EQUIPE!C4,EQUIPE!E4,EQUIPE!G4,EQUIPE!I4,EQUIPE!K4,EQUIPE!M4,EQUIPE!O4) -> 1300 | K4: 650 | L4: 285.3 | M4: =IFERROR(LEFT( IF(INDEX('ETAPA OBRA'!C:C,MATCH($B4,'ETAPA OBRA'!$B:$B,0))="x",'ETAPA OBRA'!C$1&", ","")& IF(INDEX('ETAPA OBRA'!D:D,MATCH($B4,'ETAPA OBRA'!$B:$B,0))="x",'ETAPA OBRA'!D$1&", ","")& IF(INDEX('ETAPA OBRA'!F:F,MATCH($B4,'ETAPA OBRA'!$B:$B,0))="x",'ETAPA OBRA'!F$1&", ","")& IF(INDEX('ETAPA OBRA'!G:G,MATCH($B4,'ETAPA OBRA'!$B:$B,0))="x",'ETAPA OBRA'!G$1&", ","")& IF(INDEX('ETAPA OBRA'!H:H,MATCH($B4,'ETAPA OBRA'!$B:$B,0))="x",'ETAPA OBRA'!H$1&", ","")& IF(INDEX('ETAPA OBRA'!I:I,MATCH($B4,'ETAPA OBRA'!$B:$B,0))="x",'ETAPA OBRA'!I$1&", ","")& IF(INDEX('ETAPA OBRA'!J:J,MATCH($B4,'ETAPA OBRA'!$B:$B,0))="x",'ETAPA OBRA'!J$1&", ","")& IF(INDEX('ETAPA OBRA'!K:K,MATCH($B4,'ETAPA OBRA'!$B:$B,0))="x",'ETAPA OBRA'!K$1&", ","")& IF(INDEX('ETAPA OBRA'!L:L,MATCH($B4,'ETAPA OBRA'!$B:$B,0))="x",'ETAPA OBRA'!L$1&", ","")& IF(INDEX('ETAPA OBRA'!M:M,MATCH($B4,'ETAPA OBRA'!$B:$B,0))="x",'ETAPA OBRA'!M$1&", ","")& IF(INDEX('ETAPA OBRA'!N:N,MATCH($B4,'ETAPA OBRA'!$B:$B,0))="x",'ETAPA OBRA'!N$1&", ","")& IF(INDEX('ETAPA OBRA'!O:O,MATCH($B4,'ETAPA OBRA'!$B:$B,0))="x",'ETAPA OBRA'!O$1&", ","")& IF(INDEX('ETAPA OBRA'!P:P,MATCH($B4,'ETAPA OBRA'!$B:$B,0))="x",'ETAPA OBRA'!P$1&", ","")& IF(INDEX('ETAPA OBRA'!Q:Q,MATCH($B4,'ETAPA OBRA'!$B:$B,0))="x",'ETAPA OBRA'!Q$1&", ","")& IF(INDEX('ETAPA OBRA'!R:R,MATCH($B4,'ETAPA OBRA'!$B:$B,0))="x",'ETAPA OBRA'!R$1&", ","")& IF(INDEX('ETAPA OBRA'!S:S,MATCH($B4,'ETAPA OBRA'!$B:$B,0))="x",'ETAPA OBRA'!S$1&", ","")& IF(INDEX('ETAPA OBRA'!T:T,MATCH($B4,'ETAPA OBRA'!$B:$B,0))="x",'ETAPA OBRA'!T$1&", ","")& IF(INDEX('ETAPA OBRA'!U:U,MATCH($B4,'ETAPA OBRA'!$B:$B,0))="x",'ETAPA OBRA'!U$1&", ",""),LEN( IF(INDEX('ETAPA OBRA'!C:C,MATCH($B4,'ETAPA OBRA'!$B:$B,0))="x",'ETAPA OBRA'!C$1&", ","")& IF(INDEX('ETAPA OBRA'!D:D,MATCH($B4,'ETAPA OBRA'!$B:$B,0))="x",'ETAPA OBRA'!D$1&", ","")& IF(INDEX('ETAPA OBRA'!F:F,MATCH($B4,'ETAPA OBRA'!$B:$B,0))="x",'ETAPA OBRA'!F$1&", ","")& IF(INDEX('ETAPA OBRA'!G:G,MATCH($B4,'ETAPA OBRA'!$B:$B,0))="x",'ETAPA OBRA'!G$1&", ","")& IF(INDEX('ETAPA OBRA'!H:H,MATCH($B4,'ETAPA OBRA'!$B:$B,0))="x",'ETAPA OBRA'!H$1&", ","")& IF(INDEX('ETAPA OBRA'!I:I,MATCH($B4,'ETAPA OBRA'!$B:$B,0))="x",'ETAPA OBRA'!I$1&", ","")& IF(INDEX('ETAPA OBRA'!J:J,MATCH($B4,'ETAPA OBRA'!$B:$B,0))="x",'ETAPA OBRA'!J$1&", ","")& IF(INDEX('ETAPA OBRA'!K:K,MATCH($B4,'ETAPA OBRA'!$B:$B,0))="x",'ETAPA OBRA'!K$1&", ","")& IF(INDEX('ETAPA OBRA'!L:L,MATCH($B4,'ETAPA OBRA'!$B:$B,0))="x",'ETAPA OBRA'!L$1&", ","")& IF(INDEX('ETAPA OBRA'!M:M,MATCH($B4,'ETAPA OBRA'!$B:$B,0))="x",'ETAPA OBRA'!M$1&", ","")& IF(INDEX('ETAPA OBRA'!N:N,MATCH($B4,'ETAPA OBRA'!$B:$B,0))="x",'ETAPA OBRA'!N$1&", ","")& IF(INDEX('ETAPA OBRA'!O:O,MATCH($B4,'ETAPA OBRA'!$B:$B,0))="x",'ETAPA OBRA'!O$1&", ","")& IF(INDEX('ETAPA OBRA'!P:P,MATCH($B4,'ETAPA OBRA'!$B:$B,0))="x",'ETAPA OBRA'!P$1&", ","")& IF(INDEX('ETAPA OBRA'!Q:Q,MATCH($B4,'ETAPA OBRA'!$B:$B,0))="x",'ETAPA OBRA'!Q$1&", ","")& IF(INDEX('ETAPA OBRA'!R:R,MATCH($B4,'ETAPA OBRA'!$B:$B,0))="x",'ETAPA OBRA'!R$1&", ","")& IF(INDEX('ETAPA OBRA'!S:S,MATCH($B4,'ETAPA OBRA'!$B:$B,0))="x",'ETAPA OBRA'!S$1&", ","")& IF(INDEX('ETAPA OBRA'!T:T,MATCH($B4,'ETAPA OBRA'!$B:$B,0))="x",'ETAPA OBRA'!T$1&", ","")& IF(INDEX('ETAPA OBRA'!U:U,MATCH($B4,'ETAPA OBRA'!$B:$B,0))="x",'ETAPA OBRA'!U$1&", ","") )-2),"") -> Finalizado | N4: =IF(M4="","Não iniciada", IF(ISNUMBER(FIND("Cancelada",M4)),"Cancelada", IF(ISNUMBER(FIND("Paralisada",M4)),"Paralisada", IF(ISNUMBER(FIND("Finalizado",M4)),"Finalizado", "Em andamento")))) -> Finalizado | O4: 9830.09 | P4: =SUM($J4:$L4) -> 2235.3 | Q4: =O4-P4 -> 7594.79 | R4: =IF(O4=0,0,Q4/O4) -> 0.77260635 | S4: =IF(R4>=0.2,"✅ OK - Fechar Parceiro","⚠️ Ajustar Custos (<20%)") -> ✅ OK - Fechar Parceiro | T4: =Cronograma[[#This Row],[STATUS]] -> ✅ CONCLUÍDO
A5: 47080009 | B5: =IF(A5<>"","contel-"&TEXT(COUNTA($A$2:A5),"00"),"") -> contel-04 | C5: IHS | D5: TIMBÓ | E5: SC | F5: https://maps.app.goo.gl/GEmH9t4Wq3nsX1C89 | G5: 1665 | H5: 4014 | I5: PEDRO | J5: =SUM(EQUIPE!C5,EQUIPE!E5,EQUIPE!G5,EQUIPE!I5,EQUIPE!K5,EQUIPE!M5,EQUIPE!O5) -> 10000 | K5: 10267.7 | L5: 853.78 | M5: =IFERROR(LEFT( IF(INDEX('ETAPA OBRA'!C:C,MATCH($B5,'ETAPA OBRA'!$B:$B,0))="x",'ETAPA OBRA'!C$1&", ","")& IF(INDEX('ETAPA OBRA'!D:D,MATCH($B5,'ETAPA OBRA'!$B:$B,0))="x",'ETAPA OBRA'!D$1&", ","")& IF(INDEX('ETAPA OBRA'!F:F,MATCH($B5,'ETAPA OBRA'!$B:$B,0))="x",'ETAPA OBRA'!F$1&", ","")& IF(INDEX('ETAPA OBRA'!G:G,MATCH($B5,'ETAPA OBRA'!$B:$B,0))="x",'ETAPA OBRA'!G$1&", ","")& IF(INDEX('ETAPA OBRA'!H:H,MATCH($B5,'ETAPA OBRA'!$B:$B,0))="x",'ETAPA OBRA'!H$1&", ","")& IF(INDEX('ETAPA OBRA'!I:I,MATCH($B5,'ETAPA OBRA'!$B:$B,0))="x",'ETAPA OBRA'!I$1&", ","")& IF(INDEX('ETAPA OBRA'!J:J,MATCH($B5,'ETAPA OBRA'!$B:$B,0))="x",'ETAPA OBRA'!J$1&", ","")& IF(INDEX('ETAPA OBRA'!K:K,MATCH($B5,'ETAPA OBRA'!$B:$B,0))="x",'ETAPA OBRA'!K$1&", ","")& IF(INDEX('ETAPA OBRA'!L:L,MATCH($B5,'ETAPA OBRA'!$B:$B,0))="x",'ETAPA OBRA'!L$1&", ","")& IF(INDEX('ETAPA OBRA'!M:M,MATCH($B5,'ETAPA OBRA'!$B:$B,0))="x",'ETAPA OBRA'!M$1&", ","")& IF(INDEX('ETAPA OBRA'!N:N,MATCH($B5,'ETAPA OBRA'!$B:$B,0))="x",'ETAPA OBRA'!N$1&", ","")& IF(INDEX('ETAPA OBRA'!O:O,MATCH($B5,'ETAPA OBRA'!$B:$B,0))="x",'ETAPA OBRA'!O$1&", ","")& IF(INDEX('ETAPA OBRA'!P:P,MATCH($B5,'ETAPA OBRA'!$B:$B,0))="x",'ETAPA OBRA'!P$1&", ","")& IF(INDEX('ETAPA OBRA'!Q:Q,MATCH($B5,'ETAPA OBRA'!$B:$B,0))="x",'ETAPA OBRA'!Q$1&", ","")& IF(INDEX('ETAPA OBRA'!R:R,MATCH($B5,'ETAPA OBRA'!$B:$B,0))="x",'ETAPA OBRA'!R$1&", ","")& IF(INDEX('ETAPA OBRA'!S:S,MATCH($B5,'ETAPA OBRA'!$B:$B,0))="x",'ETAPA OBRA'!S$1&", ","")& IF(INDEX('ETAPA OBRA'!T:T,MATCH($B5,'ETAPA OBRA'!$B:$B,0))="x",'ETAPA OBRA'!T$1&", ","")& IF(INDEX('ETAPA OBRA'!U:U,MATCH($B5,'ETAPA OBRA'!$B:$B,0))="x",'ETAPA OBRA'!U$1&", ",""),LEN( IF(INDEX('ETAPA OBRA'!C:C,MATCH($B5,'ETAPA OBRA'!$B:$B,0))="x",'ETAPA OBRA'!C$1&", ","")& IF(INDEX('ETAPA OBRA'!D:D,MATCH($B5,'ETAPA OBRA'!$B:$B,0))="x",'ETAPA OBRA'!D$1&", ","")& IF(INDEX('ETAPA OBRA'!F:F,MATCH($B5,'ETAPA OBRA'!$B:$B,0))="x",'ETAPA OBRA'!F$1&", ","")& IF(INDEX('ETAPA OBRA'!G:G,MATCH($B5,'ETAPA OBRA'!$B:$B,0))="x",'ETAPA OBRA'!G$1&", ","")& IF(INDEX('ETAPA OBRA'!H:H,MATCH($B5,'ETAPA OBRA'!$B:$B,0))="x",'ETAPA OBRA'!H$1&", ","")& IF(INDEX('ETAPA OBRA'!I:I,MATCH($B5,'ETAPA OBRA'!$B:$B,0))="x",'ETAPA OBRA'!I$1&", ","")& IF(INDEX('ETAPA OBRA'!J:J,MATCH($B5,'ETAPA OBRA'!$B:$B,0))="x",'ETAPA OBRA'!J$1&", ","")& IF(INDEX('ETAPA OBRA'!K:K,MATCH($B5,'ETAPA OBRA'!$B:$B,0))="x",'ETAPA OBRA'!K$1&", ","")& IF(INDEX('ETAPA OBRA'!L:L,MATCH($B5,'ETAPA OBRA'!$B:$B,0))="x",'ETAPA OBRA'!L$1&", ","")& IF(INDEX('ETAPA OBRA'!M:M,MATCH($B5,'ETAPA OBRA'!$B:$B,0))="x",'ETAPA OBRA'!M$1&", ","")& IF(INDEX('ETAPA OBRA'!N:N,MATCH($B5,'ETAPA OBRA'!$B:$B,0))="x",'ETAPA OBRA'!N$1&", ","")& IF(INDEX('ETAPA OBRA'!O:O,MATCH($B5,'ETAPA OBRA'!$B:$B,0))="x",'ETAPA OBRA'!O$1&", ","")& IF(INDEX('ETAPA OBRA'!P:P,MATCH($B5,'ETAPA OBRA'!$B:$B,0))="x",'ETAPA OBRA'!P$1&", ","")& IF(INDEX('ETAPA OBRA'!Q:Q,MATCH($B5,'ETAPA OBRA'!$B:$B,0))="x",'ETAPA OBRA'!Q$1&", ","")& IF(INDEX('ETAPA OBRA'!R:R,MATCH($B5,'ETAPA OBRA'!$B:$B,0))="x",'ETAPA OBRA'!R$1&", ","")& IF(INDEX('ETAPA OBRA'!S:S,MATCH($B5,'ETAPA OBRA'!$B:$B,0))="x",'ETAPA OBRA'!S$1&", ","")& IF(INDEX('ETAPA OBRA'!T:T,MATCH($B5,'ETAPA OBRA'!$B:$B,0))="x",'ETAPA OBRA'!T$1&", ","")& IF(INDEX('ETAPA OBRA'!U:U,MATCH($B5,'ETAPA OBRA'!$B:$B,0))="x",'ETAPA OBRA'!U$1&", ","") )-2),"") -> Finalizado | N5: =IF(M5="","Não iniciada", IF(ISNUMBER(FIND("Cancelada",M5)),"Cancelada", IF(ISNUMBER(FIND("Paralisada",M5)),"Paralisada", IF(ISNUMBER(FIND("Finalizado",M5)),"Finalizado", "Em andamento")))) -> Finalizado | O5: 119837.4 | P5: =SUM($J5:$L5) -> 21121.48 | Q5: =O5-P5 -> 98715.92 | R5: =IF(O5=0,0,Q5/O5) -> 0.82374885 | S5: =IF(R5>=0.2,"✅ OK - Fechar Parceiro","⚠️ Ajustar Custos (<20%)") -> ✅ OK - Fechar Parceiro | T5: =Cronograma[[#This Row],[STATUS]] -> ✅ CONCLUÍDO
A6: 38050011 | B6: =IF(A6<>"","contel-"&TEXT(COUNTA($A$2:A6),"00"),"") -> contel-05 | C6: IHS | D6: TRÊS MARIAS | E6: MG | F6: https://maps.app.goo.gl/NzQT4s3F2LTnY1nW9 | G6: 1678 | H6: 12763 | I6: PEDRO | J6: =SUM(EQUIPE!C6,EQUIPE!E6,EQUIPE!G6,EQUIPE!I6,EQUIPE!K6,EQUIPE!M6,EQUIPE!O6) -> 0 | K6: 24882.24 | L6: 0 | M6: =IFERROR(LEFT( IF(INDEX('ETAPA OBRA'!C:C,MATCH($B6,'ETAPA OBRA'!$B:$B,0))="x",'ETAPA OBRA'!C$1&", ","")& IF(INDEX('ETAPA OBRA'!D:D,MATCH($B6,'ETAPA OBRA'!$B:$B,0))="x",'ETAPA OBRA'!D$1&", ","")& IF(INDEX('ETAPA OBRA'!F:F,MATCH($B6,'ETAPA OBRA'!$B:$B,0))="x",'ETAPA OBRA'!F$1&", ","")& IF(INDEX('ETAPA OBRA'!G:G,MATCH($B6,'ETAPA OBRA'!$B:$B,0))="x",'ETAPA OBRA'!G$1&", ","")& IF(INDEX('ETAPA OBRA'!H:H,MATCH($B6,'ETAPA OBRA'!$B:$B,0))="x",'ETAPA OBRA'!H$1&", ","")& IF(INDEX('ETAPA OBRA'!I:I,MATCH($B6,'ETAPA OBRA'!$B:$B,0))="x",'ETAPA OBRA'!I$1&", ","")& IF(INDEX('ETAPA OBRA'!J:J,MATCH($B6,'ETAPA OBRA'!$B:$B,0))="x",'ETAPA OBRA'!J$1&", ","")& IF(INDEX('ETAPA OBRA'!K:K,MATCH($B6,'ETAPA OBRA'!$B:$B,0))="x",'ETAPA OBRA'!K$1&", ","")& IF(INDEX('ETAPA OBRA'!L:L,MATCH($B6,'ETAPA OBRA'!$B:$B,0))="x",'ETAPA OBRA'!L$1&", ","")& IF(INDEX('ETAPA OBRA'!M:M,MATCH($B6,'ETAPA OBRA'!$B:$B,0))="x",'ETAPA OBRA'!M$1&", ","")& IF(INDEX('ETAPA OBRA'!N:N,MATCH($B6,'ETAPA OBRA'!$B:$B,0))="x",'ETAPA OBRA'!N$1&", ","")& IF(INDEX('ETAPA OBRA'!O:O,MATCH($B6,'ETAPA OBRA'!$B:$B,0))="x",'ETAPA OBRA'!O$1&", ","")& IF(INDEX('ETAPA OBRA'!P:P,MATCH($B6,'ETAPA OBRA'!$B:$B,0))="x",'ETAPA OBRA'!P$1&", ","")& IF(INDEX('ETAPA OBRA'!Q:Q,MATCH($B6,'ETAPA OBRA'!$B:$B,0))="x",'ETAPA OBRA'!Q$1&", ","")& IF(INDEX('ETAPA OBRA'!R:R,MATCH($B6,'ETAPA OBRA'!$B:$B,0))="x",'ETAPA OBRA'!R$1&", ","")& IF(INDEX('ETAPA OBRA'!S:S,MATCH($B6,'ETAPA OBRA'!$B:$B,0))="x",'ETAPA OBRA'!S$1&", ","")& IF(INDEX('ETAPA OBRA'!T:T,MATCH($B6,'ETAPA OBRA'!$B:$B,0))="x",'ETAPA OBRA'!T$1&", ","")& IF(INDEX('ETAPA OBRA'!U:U,MATCH($B6,'ETAPA OBRA'!$B:$B,0))="x",'ETAPA OBRA'!U$1&", ",""),LEN( IF(INDEX('ETAPA OBRA'!C:C,MATCH($B6,'ETAPA OBRA'!$B:$B,0))="x",'ETAPA OBRA'!C$1&", ","")& IF(INDEX('ETAPA OBRA'!D:D,MATCH($B6,'ETAPA OBRA'!$B:$B,0))="x",'ETAPA OBRA'!D$1&", ","")& IF(INDEX('ETAPA OBRA'!F:F,MATCH($B6,'ETAPA OBRA'!$B:$B,0))="x",'ETAPA OBRA'!F$1&", ","")& IF(INDEX('ETAPA OBRA'!G:G,MATCH($B6,'ETAPA OBRA'!$B:$B,0))="x",'ETAPA OBRA'!G$1&", ","")& IF(INDEX('ETAPA OBRA'!H:H,MATCH($B6,'ETAPA OBRA'!$B:$B,0))="x",'ETAPA OBRA'!H$1&", ","")& IF(INDEX('ETAPA OBRA'!I:I,MATCH($B6,'ETAPA OBRA'!$B:$B,0))="x",'ETAPA OBRA'!I$1&", ","")& IF(INDEX('ETAPA OBRA'!J:J,MATCH($B6,'ETAPA OBRA'!$B:$B,0))="x",'ETAPA OBRA'!J$1&", ","")& IF(INDEX('ETAPA OBRA'!K:K,MATCH($B6,'ETAPA OBRA'!$B:$B,0))="x",'ETAPA OBRA'!K$1&", ","")& IF(INDEX('ETAPA OBRA'!L:L,MATCH($B6,'ETAPA OBRA'!$B:$B,0))="x",'ETAPA OBRA'!L$1&", ","")& IF(INDEX('ETAPA OBRA'!M:M,MATCH($B6,'ETAPA OBRA'!$B:$B,0))="x",'ETAPA OBRA'!M$1&", ","")& IF(INDEX('ETAPA OBRA'!N:N,MATCH($B6,'ETAPA OBRA'!$B:$B,0))="x",'ETAPA OBRA'!N$1&", ","")& IF(INDEX('ETAPA OBRA'!O:O,MATCH($B6,'ETAPA OBRA'!$B:$B,0))="x",'ETAPA OBRA'!O$1&", ","")& IF(INDEX('ETAPA OBRA'!P:P,MATCH($B6,'ETAPA OBRA'!$B:$B,0))="x",'ETAPA OBRA'!P$1&", ","")& IF(INDEX('ETAPA OBRA'!Q:Q,MATCH($B6,'ETAPA OBRA'!$B:$B,0))="x",'ETAPA OBRA'!Q$1&", ","")& IF(INDEX('ETAPA OBRA'!R:R,MATCH($B6,'ETAPA OBRA'!$B:$B,0))="x",'ETAPA OBRA'!R$1&", ","")& IF(INDEX('ETAPA OBRA'!S:S,MATCH($B6,'ETAPA OBRA'!$B:$B,0))="x",'ETAPA OBRA'!S$1&", ","")& IF(INDEX('ETAPA OBRA'!T:T,MATCH($B6,'ETAPA OBRA'!$B:$B,0))="x",'ETAPA OBRA'!T$1&", ","")& IF(INDEX('ETAPA OBRA'!U:U,MATCH($B6,'ETAPA OBRA'!$B:$B,0))="x",'ETAPA OBRA'!U$1&", ","") )-2),"") -> Laudo de verticalidade, Envio RFI | N6: =IF(M6="","Não iniciada", IF(ISNUMBER(FIND("Cancelada",M6)),"Cancelada", IF(ISNUMBER(FIND("Paralisada",M6)),"Paralisada", IF(ISNUMBER(FIND("Finalizado",M6)),"Finalizado", "Em andamento")))) -> Em andamento | O6: 89264 | P6: =SUM($J6:$L6) -> 24882.24 | Q6: =O6-P6 -> 64381.76 | R6: =IF(O6=0,0,Q6/O6) -> 0.72125112 | S6: =IF(R6>=0.2,"✅ OK - Fechar Parceiro","⚠️ Ajustar Custos (<20%)") -> ✅ OK - Fechar Parceiro | T6: =Cronograma[[#This Row],[STATUS]] -> ⏰ ATRASADO
A7: 38050012 | B7: =IF(A7<>"","contel-"&TEXT(COUNTA($A$2:A7),"00"),"") -> contel-06 | C7: IHS | D7: TRÊS MARIAS | E7: MG | F7: https://maps.app.goo.gl/FhvvJXRy7LcsaaeZ7 | G7: 1679 | H7: 12764 | I7: PEDRO | J7: =SUM(EQUIPE!C7,EQUIPE!E7,EQUIPE!G7,EQUIPE!I7,EQUIPE!K7,EQUIPE!M7,EQUIPE!O7) -> 0 | K7: 16990.4 | L7: 11517.19 | M7: =IFERROR(LEFT( IF(INDEX('ETAPA OBRA'!C:C,MATCH($B7,'ETAPA OBRA'!$B:$B,0))="x",'ETAPA OBRA'!C$1&", ","")& IF(INDEX('ETAPA OBRA'!D:D,MATCH($B7,'ETAPA OBRA'!$B:$B,0))="x",'ETAPA OBRA'!D$1&", ","")& IF(INDEX('ETAPA OBRA'!F:F,MATCH($B7,'ETAPA OBRA'!$B:$B,0))="x",'ETAPA OBRA'!F$1&", ","")& IF(INDEX('ETAPA OBRA'!G:G,MATCH($B7,'ETAPA OBRA'!$B:$B,0))="x",'ETAPA OBRA'!G$1&", ","")& IF(INDEX('ETAPA OBRA'!H:H,MATCH($B7,'ETAPA OBRA'!$B:$B,0))="x",'ETAPA OBRA'!H$1&", ","")& IF(INDEX('ETAPA OBRA'!I:I,MATCH($B7,'ETAPA OBRA'!$B:$B,0))="x",'ETAPA OBRA'!I$1&", ","")& IF(INDEX('ETAPA OBRA'!J:J,MATCH($B7,'ETAPA OBRA'!$B:$B,0))="x",'ETAPA OBRA'!J$1&", ","")& IF(INDEX('ETAPA OBRA'!K:K,MATCH($B7,'ETAPA OBRA'!$B:$B,0))="x",'ETAPA OBRA'!K$1&", ","")& IF(INDEX('ETAPA OBRA'!L:L,MATCH($B7,'ETAPA OBRA'!$B:$B,0))="x",'ETAPA OBRA'!L$1&", ","")& IF(INDEX('ETAPA OBRA'!M:M,MATCH($B7,'ETAPA OBRA'!$B:$B,0))="x",'ETAPA OBRA'!M$1&", ","")& IF(INDEX('ETAPA OBRA'!N:N,MATCH($B7,'ETAPA OBRA'!$B:$B,0))="x",'ETAPA OBRA'!N$1&", ","")& IF(INDEX('ETAPA OBRA'!O:O,MATCH($B7,'ETAPA OBRA'!$B:$B,0))="x",'ETAPA OBRA'!O$1&", ","")& IF(INDEX('ETAPA OBRA'!P:P,MATCH($B7,'ETAPA OBRA'!$B:$B,0))="x",'ETAPA OBRA'!P$1&", ","")& IF(INDEX('ETAPA OBRA'!Q:Q,MATCH($B7,'ETAPA OBRA'!$B:$B,0))="x",'ETAPA OBRA'!Q$1&", ","")& IF(INDEX('ETAPA OBRA'!R:R,MATCH($B7,'ETAPA OBRA'!$B:$B,0))="x",'ETAPA OBRA'!R$1&", ","")& IF(INDEX('ETAPA OBRA'!S:S,MATCH($B7,'ETAPA OBRA'!$B:$B,0))="x",'ETAPA OBRA'!S$1&", ","")& IF(INDEX('ETAPA OBRA'!T:T,MATCH($B7,'ETAPA OBRA'!$B:$B,0))="x",'ETAPA OBRA'!T$1&", ","")& IF(INDEX('ETAPA OBRA'!U:U,MATCH($B7,'ETAPA OBRA'!$B:$B,0))="x",'ETAPA OBRA'!U$1&", ",""),LEN( IF(INDEX('ETAPA OBRA'!C:C,MATCH($B7,'ETAPA OBRA'!$B:$B,0))="x",'ETAPA OBRA'!C$1&", ","")& IF(INDEX('ETAPA OBRA'!D:D,MATCH($B7,'ETAPA OBRA'!$B:$B,0))="x",'ETAPA OBRA'!D$1&", ","")& IF(INDEX('ETAPA OBRA'!F:F,MATCH($B7,'ETAPA OBRA'!$B:$B,0))="x",'ETAPA OBRA'!F$1&", ","")& IF(INDEX('ETAPA OBRA'!G:G,MATCH($B7,'ETAPA OBRA'!$B:$B,0))="x",'ETAPA OBRA'!G$1&", ","")& IF(INDEX('ETAPA OBRA'!H:H,MATCH($B7,'ETAPA OBRA'!$B:$B,0))="x",'ETAPA OBRA'!H$1&", ","")& IF(INDEX('ETAPA OBRA'!I:I,MATCH($B7,'ETAPA OBRA'!$B:$B,0))="x",'ETAPA OBRA'!I$1&", ","")& IF(INDEX('ETAPA OBRA'!J:J,MATCH($B7,'ETAPA OBRA'!$B:$B,0))="x",'ETAPA OBRA'!J$1&", ","")& IF(INDEX('ETAPA OBRA'!K:K,MATCH($B7,'ETAPA OBRA'!$B:$B,0))="x",'ETAPA OBRA'!K$1&", ","")& IF(INDEX('ETAPA OBRA'!L:L,MATCH($B7,'ETAPA OBRA'!$B:$B,0))="x",'ETAPA OBRA'!L$1&", ","")& IF(INDEX('ETAPA OBRA'!M:M,MATCH($B7,'ETAPA OBRA'!$B:$B,0))="x",'ETAPA OBRA'!M$1&", ","")& IF(INDEX('ETAPA OBRA'!N:N,MATCH($B7,'ETAPA OBRA'!$B:$B,0))="x",'ETAPA OBRA'!N$1&", ","")& IF(INDEX('ETAPA OBRA'!O:O,MATCH($B7,'ETAPA OBRA'!$B:$B,0))="x",'ETAPA OBRA'!O$1&", ","")& IF(INDEX('ETAPA OBRA'!P:P,MATCH($B7,'ETAPA OBRA'!$B:$B,0))="x",'ETAPA OBRA'!P$1&", ","")& IF(INDEX('ETAPA OBRA'!Q:Q,MATCH($B7,'ETAPA OBRA'!$B:$B,0))="x",'ETAPA OBRA'!Q$1&", ","")& IF(INDEX('ETAPA OBRA'!R:R,MATCH($B7,'ETAPA OBRA'!$B:$B,0))="x",'ETAPA OBRA'!R$1&", ","")& IF(INDEX('ETAPA OBRA'!S:S,MATCH($B7,'ETAPA OBRA'!$B:$B,0))="x",'ETAPA OBRA'!S$1&", ","")& IF(INDEX('ETAPA OBRA'!T:T,MATCH($B7,'ETAPA OBRA'!$B:$B,0))="x",'ETAPA OBRA'!T$1&", ","")& IF(INDEX('ETAPA OBRA'!U:U,MATCH($B7,'ETAPA OBRA'!$B:$B,0))="x",'ETAPA OBRA'!U$1&", ","") )-2),"") -> Laudo de verticalidade, Envio RFI | N7: =IF(M7="","Não iniciada", IF(ISNUMBER(FIND("Cancelada",M7)),"Cancelada", IF(ISNUMBER(FIND("Paralisada",M7)),"Paralisada", IF(ISNUMBER(FIND("Finalizado",M7)),"Finalizado", "Em andamento")))) -> Em andamento | O7: 89264 | P7: =SUM($J7:$L7) -> 28507.59 | Q7: =O7-P7 -> 60756.41 | R7: =IF(O7=0,0,Q7/O7) -> 0.68063732 | S7: =IF(R7>=0.2,"✅ OK - Fechar Parceiro","⚠️ Ajustar Custos (<20%)") -> ✅ OK - Fechar Parceiro | T7: =Cronograma[[#This Row],[STATUS]] -> ⏰ ATRASADO
A8: 33050064 | B8: =IF(A8<>"","contel-"&TEXT(COUNTA($A$2:A8),"00"),"") -> contel-07 | C8: IHS | D8: POCRANE | E8: MG | F8: https://maps.app.goo.gl/3RSxxC8eTf2D8Cmh8 | G8: 1680 | H8: 12765 | I8: PEDRO | J8: =SUM(EQUIPE!C8,EQUIPE!E8,EQUIPE!G8,EQUIPE!I8,EQUIPE!K8,EQUIPE!M8,EQUIPE!O8) -> 26000 | K8: 15959.77 | L8: 13697.3 | M8: =IFERROR(LEFT( IF(INDEX('ETAPA OBRA'!C:C,MATCH($B8,'ETAPA OBRA'!$B:$B,0))="x",'ETAPA OBRA'!C$1&", ","")& IF(INDEX('ETAPA OBRA'!D:D,MATCH($B8,'ETAPA OBRA'!$B:$B,0))="x",'ETAPA OBRA'!D$1&", ","")& IF(INDEX('ETAPA OBRA'!F:F,MATCH($B8,'ETAPA OBRA'!$B:$B,0))="x",'ETAPA OBRA'!F$1&", ","")& IF(INDEX('ETAPA OBRA'!G:G,MATCH($B8,'ETAPA OBRA'!$B:$B,0))="x",'ETAPA OBRA'!G$1&", ","")& IF(INDEX('ETAPA OBRA'!H:H,MATCH($B8,'ETAPA OBRA'!$B:$B,0))="x",'ETAPA OBRA'!H$1&", ","")& IF(INDEX('ETAPA OBRA'!I:I,MATCH($B8,'ETAPA OBRA'!$B:$B,0))="x",'ETAPA OBRA'!I$1&", ","")& IF(INDEX('ETAPA OBRA'!J:J,MATCH($B8,'ETAPA OBRA'!$B:$B,0))="x",'ETAPA OBRA'!J$1&", ","")& IF(INDEX('ETAPA OBRA'!K:K,MATCH($B8,'ETAPA OBRA'!$B:$B,0))="x",'ETAPA OBRA'!K$1&", ","")& IF(INDEX('ETAPA OBRA'!L:L,MATCH($B8,'ETAPA OBRA'!$B:$B,0))="x",'ETAPA OBRA'!L$1&", ","")& IF(INDEX('ETAPA OBRA'!M:M,MATCH($B8,'ETAPA OBRA'!$B:$B,0))="x",'ETAPA OBRA'!M$1&", ","")& IF(INDEX('ETAPA OBRA'!N:N,MATCH($B8,'ETAPA OBRA'!$B:$B,0))="x",'ETAPA OBRA'!N$1&", ","")& IF(INDEX('ETAPA OBRA'!O:O,MATCH($B8,'ETAPA OBRA'!$B:$B,0))="x",'ETAPA OBRA'!O$1&", ","")& IF(INDEX('ETAPA OBRA'!P:P,MATCH($B8,'ETAPA OBRA'!$B:$B,0))="x",'ETAPA OBRA'!P$1&", ","")& IF(INDEX('ETAPA OBRA'!Q:Q,MATCH($B8,'ETAPA OBRA'!$B:$B,0))="x",'ETAPA OBRA'!Q$1&", ","")& IF(INDEX('ETAPA OBRA'!R:R,MATCH($B8,'ETAPA OBRA'!$B:$B,0))="x",'ETAPA OBRA'!R$1&", ","")& IF(INDEX('ETAPA OBRA'!S:S,MATCH($B8,'ETAPA OBRA'!$B:$B,0))="x",'ETAPA OBRA'!S$1&", ","")& IF(INDEX('ETAPA OBRA'!T:T,MATCH($B8,'ETAPA OBRA'!$B:$B,0))="x",'ETAPA OBRA'!T$1&", ","")& IF(INDEX('ETAPA OBRA'!U:U,MATCH($B8,'ETAPA OBRA'!$B:$B,0))="x",'ETAPA OBRA'!U$1&", ",""),LEN( IF(INDEX('ETAPA OBRA'!C:C,MATCH($B8,'ETAPA OBRA'!$B:$B,0))="x",'ETAPA OBRA'!C$1&", ","")& IF(INDEX('ETAPA OBRA'!D:D,MATCH($B8,'ETAPA OBRA'!$B:$B,0))="x",'ETAPA OBRA'!D$1&", ","")& IF(INDEX('ETAPA OBRA'!F:F,MATCH($B8,'ETAPA OBRA'!$B:$B,0))="x",'ETAPA OBRA'!F$1&", ","")& IF(INDEX('ETAPA OBRA'!G:G,MATCH($B8,'ETAPA OBRA'!$B:$B,0))="x",'ETAPA OBRA'!G$1&", ","")& IF(INDEX('ETAPA OBRA'!H:H,MATCH($B8,'ETAPA OBRA'!$B:$B,0))="x",'ETAPA OBRA'!H$1&", ","")& IF(INDEX('ETAPA OBRA'!I:I,MATCH($B8,'ETAPA OBRA'!$B:$B,0))="x",'ETAPA OBRA'!I$1&", ","")& IF(INDEX('ETAPA OBRA'!J:J,MATCH($B8,'ETAPA OBRA'!$B:$B,0))="x",'ETAPA OBRA'!J$1&", ","")& IF(INDEX('ETAPA OBRA'!K:K,MATCH($B8,'ETAPA OBRA'!$B:$B,0))="x",'ETAPA OBRA'!K$1&", ","")& IF(INDEX('ETAPA OBRA'!L:L,MATCH($B8,'ETAPA OBRA'!$B:$B,0))="x",'ETAPA OBRA'!L$1&", ","")& IF(INDEX('ETAPA OBRA'!M:M,MATCH($B8,'ETAPA OBRA'!$B:$B,0))="x",'ETAPA OBRA'!M$1&", ","")& IF(INDEX('ETAPA OBRA'!N:N,MATCH($B8,'ETAPA OBRA'!$B:$B,0))="x",'ETAPA OBRA'!N$1&", ","")& IF(INDEX('ETAPA OBRA'!O:O,MATCH($B8,'ETAPA OBRA'!$B:$B,0))="x",'ETAPA OBRA'!O$1&", ","")& IF(INDEX('ETAPA OBRA'!P:P,MATCH($B8,'ETAPA OBRA'!$B:$B,0))="x",'ETAPA OBRA'!P$1&", ","")& IF(INDEX('ETAPA OBRA'!Q:Q,MATCH($B8,'ETAPA OBRA'!$B:$B,0))="x",'ETAPA OBRA'!Q$1&", ","")& IF(INDEX('ETAPA OBRA'!R:R,MATCH($B8,'ETAPA OBRA'!$B:$B,0))="x",'ETAPA OBRA'!R$1&", ","")& IF(INDEX('ETAPA OBRA'!S:S,MATCH($B8,'ETAPA OBRA'!$B:$B,0))="x",'ETAPA OBRA'!S$1&", ","")& IF(INDEX('ETAPA OBRA'!T:T,MATCH($B8,'ETAPA OBRA'!$B:$B,0))="x",'ETAPA OBRA'!T$1&", ","")& IF(INDEX('ETAPA OBRA'!U:U,MATCH($B8,'ETAPA OBRA'!$B:$B,0))="x",'ETAPA OBRA'!U$1&", ","") )-2),"") -> Laudo de verticalidade, Envio RFI | N8: =IF(M8="","Não iniciada", IF(ISNUMBER(FIND("Cancelada",M8)),"Cancelada", IF(ISNUMBER(FIND("Paralisada",M8)),"Paralisada", IF(ISNUMBER(FIND("Finalizado",M8)),"Finalizado", "Em andamento")))) -> Em andamento | O8: 89264 | P8: =SUM($J8:$L8) -> 55657.07 | Q8: =O8-P8 -> 33606.93 | R8: =IF(O8=0,0,Q8/O8) -> 0.37648918 | S8: =IF(R8>=0.2,"✅ OK - Fechar Parceiro","⚠️ Ajustar Custos (<20%)") -> ✅ OK - Fechar Parceiro | T8: =Cronograma[[#This Row],[STATUS]] -> ⏰ ATRASADO
A9: 38050013 | B9: =IF(A9<>"","contel-"&TEXT(COUNTA($A$2:A9),"00"),"") -> contel-08 | C9: IHS | D9: SÃO GONÇALO DO ABAETÉ | E9: MG | F9: https://maps.app.goo.gl/mHsLofcw4vKxRipE6 | G9: 1681 | H9: 12766 | I9: PEDRO | J9: =SUM(EQUIPE!C9,EQUIPE!E9,EQUIPE!G9,EQUIPE!I9,EQUIPE!K9,EQUIPE!M9,EQUIPE!O9) -> 27500 | K9: 27453.33 | L9: 1490 | M9: =IFERROR(LEFT( IF(INDEX('ETAPA OBRA'!C:C,MATCH($B9,'ETAPA OBRA'!$B:$B,0))="x",'ETAPA OBRA'!C$1&", ","")& IF(INDEX('ETAPA OBRA'!D:D,MATCH($B9,'ETAPA OBRA'!$B:$B,0))="x",'ETAPA OBRA'!D$1&", ","")& IF(INDEX('ETAPA OBRA'!F:F,MATCH($B9,'ETAPA OBRA'!$B:$B,0))="x",'ETAPA OBRA'!F$1&", ","")& IF(INDEX('ETAPA OBRA'!G:G,MATCH($B9,'ETAPA OBRA'!$B:$B,0))="x",'ETAPA OBRA'!G$1&", ","")& IF(INDEX('ETAPA OBRA'!H:H,MATCH($B9,'ETAPA OBRA'!$B:$B,0))="x",'ETAPA OBRA'!H$1&", ","")& IF(INDEX('ETAPA OBRA'!I:I,MATCH($B9,'ETAPA OBRA'!$B:$B,0))="x",'ETAPA OBRA'!I$1&", ","")& IF(INDEX('ETAPA OBRA'!J:J,MATCH($B9,'ETAPA OBRA'!$B:$B,0))="x",'ETAPA OBRA'!J$1&", ","")& IF(INDEX('ETAPA OBRA'!K:K,MATCH($B9,'ETAPA OBRA'!$B:$B,0))="x",'ETAPA OBRA'!K$1&", ","")& IF(INDEX('ETAPA OBRA'!L:L,MATCH($B9,'ETAPA OBRA'!$B:$B,0))="x",'ETAPA OBRA'!L$1&", ","")& IF(INDEX('ETAPA OBRA'!M:M,MATCH($B9,'ETAPA OBRA'!$B:$B,0))="x",'ETAPA OBRA'!M$1&", ","")& IF(INDEX('ETAPA OBRA'!N:N,MATCH($B9,'ETAPA OBRA'!$B:$B,0))="x",'ETAPA OBRA'!N$1&", ","")& IF(INDEX('ETAPA OBRA'!O:O,MATCH($B9,'ETAPA OBRA'!$B:$B,0))="x",'ETAPA OBRA'!O$1&", ","")& IF(INDEX('ETAPA OBRA'!P:P,MATCH($B9,'ETAPA OBRA'!$B:$B,0))="x",'ETAPA OBRA'!P$1&", ","")& IF(INDEX('ETAPA OBRA'!Q:Q,MATCH($B9,'ETAPA OBRA'!$B:$B,0))="x",'ETAPA OBRA'!Q$1&", ","")& IF(INDEX('ETAPA OBRA'!R:R,MATCH($B9,'ETAPA OBRA'!$B:$B,0))="x",'ETAPA OBRA'!R$1&", ","")& IF(INDEX('ETAPA OBRA'!S:S,MATCH($B9,'ETAPA OBRA'!$B:$B,0))="x",'ETAPA OBRA'!S$1&", ","")& IF(INDEX('ETAPA OBRA'!T:T,MATCH($B9,'ETAPA OBRA'!$B:$B,0))="x",'ETAPA OBRA'!T$1&", ","")& IF(INDEX('ETAPA OBRA'!U:U,MATCH($B9,'ETAPA OBRA'!$B:$B,0))="x",'ETAPA OBRA'!U$1&", ",""),LEN( IF(INDEX('ETAPA OBRA'!C:C,MATCH($B9,'ETAPA OBRA'!$B:$B,0))="x",'ETAPA OBRA'!C$1&", ","")& IF(INDEX('ETAPA OBRA'!D:D,MATCH($B9,'ETAPA OBRA'!$B:$B,0))="x",'ETAPA OBRA'!D$1&", ","")& IF(INDEX('ETAPA OBRA'!F:F,MATCH($B9,'ETAPA OBRA'!$B:$B,0))="x",'ETAPA OBRA'!F$1&", ","")& IF(INDEX('ETAPA OBRA'!G:G,MATCH($B9,'ETAPA OBRA'!$B:$B,0))="x",'ETAPA OBRA'!G$1&", ","")& IF(INDEX('ETAPA OBRA'!H:H,MATCH($B9,'ETAPA OBRA'!$B:$B,0))="x",'ETAPA OBRA'!H$1&", ","")& IF(INDEX('ETAPA OBRA'!I:I,MATCH($B9,'ETAPA OBRA'!$B:$B,0))="x",'ETAPA OBRA'!I$1&", ","")& IF(INDEX('ETAPA OBRA'!J:J,MATCH($B9,'ETAPA OBRA'!$B:$B,0))="x",'ETAPA OBRA'!J$1&", ","")& IF(INDEX('ETAPA OBRA'!K:K,MATCH($B9,'ETAPA OBRA'!$B:$B,0))="x",'ETAPA OBRA'!K$1&", ","")& IF(INDEX('ETAPA OBRA'!L:L,MATCH($B9,'ETAPA OBRA'!$B:$B,0))="x",'ETAPA OBRA'!L$1&", ","")& IF(INDEX('ETAPA OBRA'!M:M,MATCH($B9,'ETAPA OBRA'!$B:$B,0))="x",'ETAPA OBRA'!M$1&", ","")& IF(INDEX('ETAPA OBRA'!N:N,MATCH($B9,'ETAPA OBRA'!$B:$B,0))="x",'ETAPA OBRA'!N$1&", ","")& IF(INDEX('ETAPA OBRA'!O:O,MATCH($B9,'ETAPA OBRA'!$B:$B,0))="x",'ETAPA OBRA'!O$1&", ","")& IF(INDEX('ETAPA OBRA'!P:P,MATCH($B9,'ETAPA OBRA'!$B:$B,0))="x",'ETAPA OBRA'!P$1&", ","")& IF(INDEX('ETAPA OBRA'!Q:Q,MATCH($B9,'ETAPA OBRA'!$B:$B,0))="x",'ETAPA OBRA'!Q$1&", ","")& IF(INDEX('ETAPA OBRA'!R:R,MATCH($B9,'ETAPA OBRA'!$B:$B,0))="x",'ETAPA OBRA'!R$1&", ","")& IF(INDEX('ETAPA OBRA'!S:S,MATCH($B9,'ETAPA OBRA'!$B:$B,0))="x",'ETAPA OBRA'!S$1&", ","")& IF(INDEX('ETAPA OBRA'!T:T,MATCH($B9,'ETAPA OBRA'!$B:$B,0))="x",'ETAPA OBRA'!T$1&", ","")& IF(INDEX('ETAPA OBRA'!U:U,MATCH($B9,'ETAPA OBRA'!$B:$B,0))="x",'ETAPA OBRA'!U$1&", ","") )-2),"") -> Laudo de verticalidade, Envio RFI | N9: =IF(M9="","Não iniciada", IF(ISNUMBER(FIND("Cancelada",M9)),"Cancelada", IF(ISNUMBER(FIND("Paralisada",M9)),"Paralisada", IF(ISNUMBER(FIND("Finalizado",M9)),"Finalizado", "Em andamento")))) -> Em andamento | O9: 89264 | P9: =SUM($J9:$L9) -> 56443.33 | Q9: =O9-P9 -> 32820.67 | R9: =IF(O9=0,0,Q9/O9) -> 0.36768092 | S9: =IF(R9>=0.2,"✅ OK - Fechar Parceiro","⚠️ Ajustar Custos (<20%)") -> ✅ OK - Fechar Parceiro | T9: =Cronograma[[#This Row],[STATUS]] -> 🕓 EM ANDAMENTO
A10: 38050008 | B10: =IF(A10<>"","contel-"&TEXT(COUNTA($A$2:A10),"00"),"") -> contel-09 | C10: IHS | D10: FORMOSO | E10: MG | F10: https://maps.app.goo.gl/JBh7GfA722cC6J6y7 | G10: 1682 | H10: 12767 | I10: PEDRO | J10: =SUM(EQUIPE!C10,EQUIPE!E10,EQUIPE!G10,EQUIPE!I10,EQUIPE!K10,EQUIPE!M10,EQUIPE!O10) -> 27000 | K10: 20963.08 | L10: 0 | M10: =IFERROR(LEFT( IF(INDEX('ETAPA OBRA'!C:C,MATCH($B10,'ETAPA OBRA'!$B:$B,0))="x",'ETAPA OBRA'!C$1&", ","")& IF(INDEX('ETAPA OBRA'!D:D,MATCH($B10,'ETAPA OBRA'!$B:$B,0))="x",'ETAPA OBRA'!D$1&", ","")& IF(INDEX('ETAPA OBRA'!F:F,MATCH($B10,'ETAPA OBRA'!$B:$B,0))="x",'ETAPA OBRA'!F$1&", ","")& IF(INDEX('ETAPA OBRA'!G:G,MATCH($B10,'ETAPA OBRA'!$B:$B,0))="x",'ETAPA OBRA'!G$1&", ","")& IF(INDEX('ETAPA OBRA'!H:H,MATCH($B10,'ETAPA OBRA'!$B:$B,0))="x",'ETAPA OBRA'!H$1&", ","")& IF(INDEX('ETAPA OBRA'!I:I,MATCH($B10,'ETAPA OBRA'!$B:$B,0))="x",'ETAPA OBRA'!I$1&", ","")& IF(INDEX('ETAPA OBRA'!J:J,MATCH($B10,'ETAPA OBRA'!$B:$B,0))="x",'ETAPA OBRA'!J$1&", ","")& IF(INDEX('ETAPA OBRA'!K:K,MATCH($B10,'ETAPA OBRA'!$B:$B,0))="x",'ETAPA OBRA'!K$1&", ","")& IF(INDEX('ETAPA OBRA'!L:L,MATCH($B10,'ETAPA OBRA'!$B:$B,0))="x",'ETAPA OBRA'!L$1&", ","")& IF(INDEX('ETAPA OBRA'!M:M,MATCH($B10,'ETAPA OBRA'!$B:$B,0))="x",'ETAPA OBRA'!M$1&", ","")& IF(INDEX('ETAPA OBRA'!N:N,MATCH($B10,'ETAPA OBRA'!$B:$B,0))="x",'ETAPA OBRA'!N$1&", ","")& IF(INDEX('ETAPA OBRA'!O:O,MATCH($B10,'ETAPA OBRA'!$B:$B,0))="x",'ETAPA OBRA'!O$1&", ","")& IF(INDEX('ETAPA OBRA'!P:P,MATCH($B10,'ETAPA OBRA'!$B:$B,0))="x",'ETAPA OBRA'!P$1&", ","")& IF(INDEX('ETAPA OBRA'!Q:Q,MATCH($B10,'ETAPA OBRA'!$B:$B,0))="x",'ETAPA OBRA'!Q$1&", ","")& IF(INDEX('ETAPA OBRA'!R:R,MATCH($B10,'ETAPA OBRA'!$B:$B,0))="x",'ETAPA OBRA'!R$1&", ","")& IF(INDEX('ETAPA OBRA'!S:S,MATCH($B10,'ETAPA OBRA'!$B:$B,0))="x",'ETAPA OBRA'!S$1&", ","")& IF(INDEX('ETAPA OBRA'!T:T,MATCH($B10,'ETAPA OBRA'!$B:$B,0))="x",'ETAPA OBRA'!T$1&", ","")& IF(INDEX('ETAPA OBRA'!U:U,MATCH($B10,'ETAPA OBRA'!$B:$B,0))="x",'ETAPA OBRA'!U$1&", ",""),LEN( IF(INDEX('ETAPA OBRA'!C:C,MATCH($B10,'ETAPA OBRA'!$B:$B,0))="x",'ETAPA OBRA'!C$1&", ","")& IF(INDEX('ETAPA OBRA'!D:D,MATCH($B10,'ETAPA OBRA'!$B:$B,0))="x",'ETAPA OBRA'!D$1&", ","")& IF(INDEX('ETAPA OBRA'!F:F,MATCH($B10,'ETAPA OBRA'!$B:$B,0))="x",'ETAPA OBRA'!F$1&", ","")& IF(INDEX('ETAPA OBRA'!G:G,MATCH($B10,'ETAPA OBRA'!$B:$B,0))="x",'ETAPA OBRA'!G$1&", ","")& IF(INDEX('ETAPA OBRA'!H:H,MATCH($B10,'ETAPA OBRA'!$B:$B,0))="x",'ETAPA OBRA'!H$1&", ","")& IF(INDEX('ETAPA OBRA'!I:I,MATCH($B10,'ETAPA OBRA'!$B:$B,0))="x",'ETAPA OBRA'!I$1&", ","")& IF(INDEX('ETAPA OBRA'!J:J,MATCH($B10,'ETAPA OBRA'!$B:$B,0))="x",'ETAPA OBRA'!J$1&", ","")& IF(INDEX('ETAPA OBRA'!K:K,MATCH($B10,'ETAPA OBRA'!$B:$B,0))="x",'ETAPA OBRA'!K$1&", ","")& IF(INDEX('ETAPA OBRA'!L:L,MATCH($B10,'ETAPA OBRA'!$B:$B,0))="x",'ETAPA OBRA'!L$1&", ","")& IF(INDEX('ETAPA OBRA'!M:M,MATCH($B10,'ETAPA OBRA'!$B:$B,0))="x",'ETAPA OBRA'!M$1&", ","")& IF(INDEX('ETAPA OBRA'!N:N,MATCH($B10,'ETAPA OBRA'!$B:$B,0))="x",'ETAPA OBRA'!N$1&", ","")& IF(INDEX('ETAPA OBRA'!O:O,MATCH($B10,'ETAPA OBRA'!$B:$B,0))="x",'ETAPA OBRA'!O$1&", ","")& IF(INDEX('ETAPA OBRA'!P:P,MATCH($B10,'ETAPA OBRA'!$B:$B,0))="x",'ETAPA OBRA'!P$1&", ","")& IF(INDEX('ETAPA OBRA'!Q:Q,MATCH($B10,'ETAPA OBRA'!$B:$B,0))="x",'ETAPA OBRA'!Q$1&", ","")& IF(INDEX('ETAPA OBRA'!R:R,MATCH($B10,'ETAPA OBRA'!$B:$B,0))="x",'ETAPA OBRA'!R$1&", ","")& IF(INDEX('ETAPA OBRA'!S:S,MATCH($B10,'ETAPA OBRA'!$B:$B,0))="x",'ETAPA OBRA'!S$1&", ","")& IF(INDEX('ETAPA OBRA'!T:T,MATCH($B10,'ETAPA OBRA'!$B:$B,0))="x",'ETAPA OBRA'!T$1&", ","")& IF(INDEX('ETAPA OBRA'!U:U,MATCH($B10,'ETAPA OBRA'!$B:$B,0))="x",'ETAPA OBRA'!U$1&", ","") )-2),"") -> Laudo de verticalidade, Envio RFI | N10: =IF(M10="","Não iniciada", IF(ISNUMBER(FIND("Cancelada",M10)),"Cancelada", IF(ISNUMBER(FIND("Paralisada",M10)),"Paralisada", IF(ISNUMBER(FIND("Finalizado",M10)),"Finalizado", "Em andamento")))) -> Em andamento | O10: 89264 | P10: =SUM($J10:$L10) -> 47963.08 | Q10: =O10-P10 -> 41300.92 | R10: =IF(O10=0,0,Q10/O10) -> 0.46268283 | S10: =IF(R10>=0.2,"✅ OK - Fechar Parceiro","⚠️ Ajustar Custos (<20%)") -> ✅ OK - Fechar Parceiro | T10: =Cronograma[[#This Row],[STATUS]] -> ⏰ ATRASADO
A11: 88050062 | B11: =IF(A11<>"","contel-"&TEXT(COUNTA($A$2:A11),"00"),"") -> contel-10 | C11: IHS | D11: QUIXADÁ | E11: CE | F11: https://maps.app.goo.gl/QdG7puZ7e7jJzaxS9 | G11: 1683 | H11: 12768 | I11: PEDRO | J11: =SUM(EQUIPE!C11,EQUIPE!E11,EQUIPE!G11,EQUIPE!I11,EQUIPE!K11,EQUIPE!M11,EQUIPE!O11) -> 24500 | K11: 18952.57 | L11: 0 | M11: =IFERROR(LEFT( IF(INDEX('ETAPA OBRA'!C:C,MATCH($B11,'ETAPA OBRA'!$B:$B,0))="x",'ETAPA OBRA'!C$1&", ","")& IF(INDEX('ETAPA OBRA'!D:D,MATCH($B11,'ETAPA OBRA'!$B:$B,0))="x",'ETAPA OBRA'!D$1&", ","")& IF(INDEX('ETAPA OBRA'!F:F,MATCH($B11,'ETAPA OBRA'!$B:$B,0))="x",'ETAPA OBRA'!F$1&", ","")& IF(INDEX('ETAPA OBRA'!G:G,MATCH($B11,'ETAPA OBRA'!$B:$B,0))="x",'ETAPA OBRA'!G$1&", ","")& IF(INDEX('ETAPA OBRA'!H:H,MATCH($B11,'ETAPA OBRA'!$B:$B,0))="x",'ETAPA OBRA'!H$1&", ","")& IF(INDEX('ETAPA OBRA'!I:I,MATCH($B11,'ETAPA OBRA'!$B:$B,0))="x",'ETAPA OBRA'!I$1&", ","")& IF(INDEX('ETAPA OBRA'!J:J,MATCH($B11,'ETAPA OBRA'!$B:$B,0))="x",'ETAPA OBRA'!J$1&", ","")& IF(INDEX('ETAPA OBRA'!K:K,MATCH($B11,'ETAPA OBRA'!$B:$B,0))="x",'ETAPA OBRA'!K$1&", ","")& IF(INDEX('ETAPA OBRA'!L:L,MATCH($B11,'ETAPA OBRA'!$B:$B,0))="x",'ETAPA OBRA'!L$1&", ","")& IF(INDEX('ETAPA OBRA'!M:M,MATCH($B11,'ETAPA OBRA'!$B:$B,0))="x",'ETAPA OBRA'!M$1&", ","")& IF(INDEX('ETAPA OBRA'!N:N,MATCH($B11,'ETAPA OBRA'!$B:$B,0))="x",'ETAPA OBRA'!N$1&", ","")& IF(INDEX('ETAPA OBRA'!O:O,MATCH($B11,'ETAPA OBRA'!$B:$B,0))="x",'ETAPA OBRA'!O$1&", ","")& IF(INDEX('ETAPA OBRA'!P:P,MATCH($B11,'ETAPA OBRA'!$B:$B,0))="x",'ETAPA OBRA'!P$1&", ","")& IF(INDEX('ETAPA OBRA'!Q:Q,MATCH($B11,'ETAPA OBRA'!$B:$B,0))="x",'ETAPA OBRA'!Q$1&", ","")& IF(INDEX('ETAPA OBRA'!R:R,MATCH($B11,'ETAPA OBRA'!$B:$B,0))="x",'ETAPA OBRA'!R$1&", ","")& IF(INDEX('ETAPA OBRA'!S:S,MATCH($B11,'ETAPA OBRA'!$B:$B,0))="x",'ETAPA OBRA'!S$1&", ","")& IF(INDEX('ETAPA OBRA'!T:T,MATCH($B11,'ETAPA OBRA'!$B:$B,0))="x",'ETAPA OBRA'!T$1&", ","")& IF(INDEX('ETAPA OBRA'!U:U,MATCH($B11,'ETAPA OBRA'!$B:$B,0))="x",'ETAPA OBRA'!U$1&", ",""),LEN( IF(INDEX('ETAPA OBRA'!C:C,MATCH($B11,'ETAPA OBRA'!$B:$B,0))="x",'ETAPA OBRA'!C$1&", ","")& IF(INDEX('ETAPA OBRA'!D:D,MATCH($B11,'ETAPA OBRA'!$B:$B,0))="x",'ETAPA OBRA'!D$1&", ","")& IF(INDEX('ETAPA OBRA'!F:F,MATCH($B11,'ETAPA OBRA'!$B:$B,0))="x",'ETAPA OBRA'!F$1&", ","")& IF(INDEX('ETAPA OBRA'!G:G,MATCH($B11,'ETAPA OBRA'!$B:$B,0))="x",'ETAPA OBRA'!G$1&", ","")& IF(INDEX('ETAPA OBRA'!H:H,MATCH($B11,'ETAPA OBRA'!$B:$B,0))="x",'ETAPA OBRA'!H$1&", ","")& IF(INDEX('ETAPA OBRA'!I:I,MATCH($B11,'ETAPA OBRA'!$B:$B,0))="x",'ETAPA OBRA'!I$1&", ","")& IF(INDEX('ETAPA OBRA'!J:J,MATCH($B11,'ETAPA OBRA'!$B:$B,0))="x",'ETAPA OBRA'!J$1&", ","")& IF(INDEX('ETAPA OBRA'!K:K,MATCH($B11,'ETAPA OBRA'!$B:$B,0))="x",'ETAPA OBRA'!K$1&", ","")& IF(INDEX('ETAPA OBRA'!L:L,MATCH($B11,'ETAPA OBRA'!$B:$B,0))="x",'ETAPA OBRA'!L$1&", ","")& IF(INDEX('ETAPA OBRA'!M:M,MATCH($B11,'ETAPA OBRA'!$B:$B,0))="x",'ETAPA OBRA'!M$1&", ","")& IF(INDEX('ETAPA OBRA'!N:N,MATCH($B11,'ETAPA OBRA'!$B:$B,0))="x",'ETAPA OBRA'!N$1&", ","")& IF(INDEX('ETAPA OBRA'!O:O,MATCH($B11,'ETAPA OBRA'!$B:$B,0))="x",'ETAPA OBRA'!O$1&", ","")& IF(INDEX('ETAPA OBRA'!P:P,MATCH($B11,'ETAPA OBRA'!$B:$B,0))="x",'ETAPA OBRA'!P$1&", ","")& IF(INDEX('ETAPA OBRA'!Q:Q,MATCH($B11,'ETAPA OBRA'!$B:$B,0))="x",'ETAPA OBRA'!Q$1&", ","")& IF(INDEX('ETAPA OBRA'!R:R,MATCH($B11,'ETAPA OBRA'!$B:$B,0))="x",'ETAPA OBRA'!R$1&", ","")& IF(INDEX('ETAPA OBRA'!S:S,MATCH($B11,'ETAPA OBRA'!$B:$B,0))="x",'ETAPA OBRA'!S$1&", ","")& IF(INDEX('ETAPA OBRA'!T:T,MATCH($B11,'ETAPA OBRA'!$B:$B,0))="x",'ETAPA OBRA'!T$1&", ","")& IF(INDEX('ETAPA OBRA'!U:U,MATCH($B11,'ETAPA OBRA'!$B:$B,0))="x",'ETAPA OBRA'!U$1&", ","") )-2),"") -> Finalizado | N11: =IF(M11="","Não iniciada", IF(ISNUMBER(FIND("Cancelada",M11)),"Cancelada", IF(ISNUMBER(FIND("Paralisada",M11)),"Paralisada", IF(ISNUMBER(FIND("Finalizado",M11)),"Finalizado", "Em andamento")))) -> Finalizado | O11: 89264 | P11: =SUM($J11:$L11) -> 43452.57 | Q11: =O11-P11 -> 45811.43 | R11: =IF(O11=0,0,Q11/O11) -> 0.51321283 | S11: =IF(R11>=0.2,"✅ OK - Fechar Parceiro","⚠️ Ajustar Custos (<20%)") -> ✅ OK - Fechar Parceiro | T11: =Cronograma[[#This Row],[STATUS]] -> ✅ CONCLUÍDO
A12: 88050069 | B12: =IF(A12<>"","contel-"&TEXT(COUNTA($A$2:A12),"00"),"") -> contel-11 | C12: IHS | D12: MALHADA | E12: CE | F12: https://maps.app.goo.gl/7anpJtZhoq92gEPg7 | G12: 1684 | H12: 12769 | I12: PEDRO | J12: =SUM(EQUIPE!C12,EQUIPE!E12,EQUIPE!G12,EQUIPE!I12,EQUIPE!K12,EQUIPE!M12,EQUIPE!O12) -> 0 | K12: 13872.51 | L12: 0 | M12: =IFERROR(LEFT( IF(INDEX('ETAPA OBRA'!C:C,MATCH($B12,'ETAPA OBRA'!$B:$B,0))="x",'ETAPA OBRA'!C$1&", ","")& IF(INDEX('ETAPA OBRA'!D:D,MATCH($B12,'ETAPA OBRA'!$B:$B,0))="x",'ETAPA OBRA'!D$1&", ","")& IF(INDEX('ETAPA OBRA'!F:F,MATCH($B12,'ETAPA OBRA'!$B:$B,0))="x",'ETAPA OBRA'!F$1&", ","")& IF(INDEX('ETAPA OBRA'!G:G,MATCH($B12,'ETAPA OBRA'!$B:$B,0))="x",'ETAPA OBRA'!G$1&", ","")& IF(INDEX('ETAPA OBRA'!H:H,MATCH($B12,'ETAPA OBRA'!$B:$B,0))="x",'ETAPA OBRA'!H$1&", ","")& IF(INDEX('ETAPA OBRA'!I:I,MATCH($B12,'ETAPA OBRA'!$B:$B,0))="x",'ETAPA OBRA'!I$1&", ","")& IF(INDEX('ETAPA OBRA'!J:J,MATCH($B12,'ETAPA OBRA'!$B:$B,0))="x",'ETAPA OBRA'!J$1&", ","")& IF(INDEX('ETAPA OBRA'!K:K,MATCH($B12,'ETAPA OBRA'!$B:$B,0))="x",'ETAPA OBRA'!K$1&", ","")& IF(INDEX('ETAPA OBRA'!L:L,MATCH($B12,'ETAPA OBRA'!$B:$B,0))="x",'ETAPA OBRA'!L$1&", ","")& IF(INDEX('ETAPA OBRA'!M:M,MATCH($B12,'ETAPA OBRA'!$B:$B,0))="x",'ETAPA OBRA'!M$1&", ","")& IF(INDEX('ETAPA OBRA'!N:N,MATCH($B12,'ETAPA OBRA'!$B:$B,0))="x",'ETAPA OBRA'!N$1&", ","")& IF(INDEX('ETAPA OBRA'!O:O,MATCH($B12,'ETAPA OBRA'!$B:$B,0))="x",'ETAPA OBRA'!O$1&", ","")& IF(INDEX('ETAPA OBRA'!P:P,MATCH($B12,'ETAPA OBRA'!$B:$B,0))="x",'ETAPA OBRA'!P$1&", ","")& IF(INDEX('ETAPA OBRA'!Q:Q,MATCH($B12,'ETAPA OBRA'!$B:$B,0))="x",'ETAPA OBRA'!Q$1&", ","")& IF(INDEX('ETAPA OBRA'!R:R,MATCH($B12,'ETAPA OBRA'!$B:$B,0))="x",'ETAPA OBRA'!R$1&", ","")& IF(INDEX('ETAPA OBRA'!S:S,MATCH($B12,'ETAPA OBRA'!$B:$B,0))="x",'ETAPA OBRA'!S$1&", ","")& IF(INDEX('ETAPA OBRA'!T:T,MATCH($B12,'ETAPA OBRA'!$B:$B,0))="x",'ETAPA OBRA'!T$1&", ","")& IF(INDEX('ETAPA OBRA'!U:U,MATCH($B12,'ETAPA OBRA'!$B:$B,0))="x",'ETAPA OBRA'!U$1&", ",""),LEN( IF(INDEX('ETAPA OBRA'!C:C,MATCH($B12,'ETAPA OBRA'!$B:$B,0))="x",'ETAPA OBRA'!C$1&", ","")& IF(INDEX('ETAPA OBRA'!D:D,MATCH($B12,'ETAPA OBRA'!$B:$B,0))="x",'ETAPA OBRA'!D$1&", ","")& IF(INDEX('ETAPA OBRA'!F:F,MATCH($B12,'ETAPA OBRA'!$B:$B,0))="x",'ETAPA OBRA'!F$1&", ","")& IF(INDEX('ETAPA OBRA'!G:G,MATCH($B12,'ETAPA OBRA'!$B:$B,0))="x",'ETAPA OBRA'!G$1&", ","")& IF(INDEX('ETAPA OBRA'!H:H,MATCH($B12,'ETAPA OBRA'!$B:$B,0))="x",'ETAPA OBRA'!H$1&", ","")& IF(INDEX('ETAPA OBRA'!I:I,MATCH($B12,'ETAPA OBRA'!$B:$B,0))="x",'ETAPA OBRA'!I$1&", ","")& IF(INDEX('ETAPA OBRA'!J:J,MATCH($B12,'ETAPA OBRA'!$B:$B,0))="x",'ETAPA OBRA'!J$1&", ","")& IF(INDEX('ETAPA OBRA'!K:K,MATCH($B12,'ETAPA OBRA'!$B:$B,0))="x",'ETAPA OBRA'!K$1&", ","")& IF(INDEX('ETAPA OBRA'!L:L,MATCH($B12,'ETAPA OBRA'!$B:$B,0))="x",'ETAPA OBRA'!L$1&", ","")& IF(INDEX('ETAPA OBRA'!M:M,MATCH($B12,'ETAPA OBRA'!$B:$B,0))="x",'ETAPA OBRA'!M$1&", ","")& IF(INDEX('ETAPA OBRA'!N:N,MATCH($B12,'ETAPA OBRA'!$B:$B,0))="x",'ETAPA OBRA'!N$1&", ","")& IF(INDEX('ETAPA OBRA'!O:O,MATCH($B12,'ETAPA OBRA'!$B:$B,0))="x",'ETAPA OBRA'!O$1&", ","")& IF(INDEX('ETAPA OBRA'!P:P,MATCH($B12,'ETAPA OBRA'!$B:$B,0))="x",'ETAPA OBRA'!P$1&", ","")& IF(INDEX('ETAPA OBRA'!Q:Q,MATCH($B12,'ETAPA OBRA'!$B:$B,0))="x",'ETAPA OBRA'!Q$1&", ","")& IF(INDEX('ETAPA OBRA'!R:R,MATCH($B12,'ETAPA OBRA'!$B:$B,0))="x",'ETAPA OBRA'!R$1&", ","")& IF(INDEX('ETAPA OBRA'!S:S,MATCH($B12,'ETAPA OBRA'!$B:$B,0))="x",'ETAPA OBRA'!S$1&", ","")& IF(INDEX('ETAPA OBRA'!T:T,MATCH($B12,'ETAPA OBRA'!$B:$B,0))="x",'ETAPA OBRA'!T$1&", ","")& IF(INDEX('ETAPA OBRA'!U:U,MATCH($B12,'ETAPA OBRA'!$B:$B,0))="x",'ETAPA OBRA'!U$1&", ","") )-2),"") -> Finalizado | N12: =IF(M12="","Não iniciada", IF(ISNUMBER(FIND("Cancelada",M12)),"Cancelada", IF(ISNUMBER(FIND("Paralisada",M12)),"Paralisada", IF(ISNUMBER(FIND("Finalizado",M12)),"Finalizado", "Em andamento")))) -> Finalizado | O12: 89264 | P12: =SUM($J12:$L12) -> 13872.51 | Q12: =O12-P12 -> 75391.49 | R12: =IF(O12=0,0,Q12/O12) -> 0.84459009 | S12: =IF(R12>=0.2,"✅ OK - Fechar Parceiro","⚠️ Ajustar Custos (<20%)") -> ✅ OK - Fechar Parceiro | T12: =Cronograma[[#This Row],[STATUS]] -> ✅ CONCLUÍDO
A13: 83010085 | B13: =IF(A13<>"","contel-"&TEXT(COUNTA($A$2:A13),"00"),"") -> contel-12 | C13: IHS | D13: BERNARDINO BATISTA | E13: PB | F13: https://maps.app.goo.gl/rkUwhhpPfBuKEvyx7 | G13: 1685 | H13: 12770 | I13: PEDRO | J13: =SUM(EQUIPE!C13,EQUIPE!E13,EQUIPE!G13,EQUIPE!I13,EQUIPE!K13,EQUIPE!M13,EQUIPE!O13) -> 0 | K13: 25453.15 | L13: 0 | M13: =IFERROR(LEFT( IF(INDEX('ETAPA OBRA'!C:C,MATCH($B13,'ETAPA OBRA'!$B:$B,0))="x",'ETAPA OBRA'!C$1&", ","")& IF(INDEX('ETAPA OBRA'!D:D,MATCH($B13,'ETAPA OBRA'!$B:$B,0))="x",'ETAPA OBRA'!D$1&", ","")& IF(INDEX('ETAPA OBRA'!F:F,MATCH($B13,'ETAPA OBRA'!$B:$B,0))="x",'ETAPA OBRA'!F$1&", ","")& IF(INDEX('ETAPA OBRA'!G:G,MATCH($B13,'ETAPA OBRA'!$B:$B,0))="x",'ETAPA OBRA'!G$1&", ","")& IF(INDEX('ETAPA OBRA'!H:H,MATCH($B13,'ETAPA OBRA'!$B:$B,0))="x",'ETAPA OBRA'!H$1&", ","")& IF(INDEX('ETAPA OBRA'!I:I,MATCH($B13,'ETAPA OBRA'!$B:$B,0))="x",'ETAPA OBRA'!I$1&", ","")& IF(INDEX('ETAPA OBRA'!J:J,MATCH($B13,'ETAPA OBRA'!$B:$B,0))="x",'ETAPA OBRA'!J$1&", ","")& IF(INDEX('ETAPA OBRA'!K:K,MATCH($B13,'ETAPA OBRA'!$B:$B,0))="x",'ETAPA OBRA'!K$1&", ","")& IF(INDEX('ETAPA OBRA'!L:L,MATCH($B13,'ETAPA OBRA'!$B:$B,0))="x",'ETAPA OBRA'!L$1&", ","")& IF(INDEX('ETAPA OBRA'!M:M,MATCH($B13,'ETAPA OBRA'!$B:$B,0))="x",'ETAPA OBRA'!M$1&", ","")& IF(INDEX('ETAPA OBRA'!N:N,MATCH($B13,'ETAPA OBRA'!$B:$B,0))="x",'ETAPA OBRA'!N$1&", ","")& IF(INDEX('ETAPA OBRA'!O:O,MATCH($B13,'ETAPA OBRA'!$B:$B,0))="x",'ETAPA OBRA'!O$1&", ","")& IF(INDEX('ETAPA OBRA'!P:P,MATCH($B13,'ETAPA OBRA'!$B:$B,0))="x",'ETAPA OBRA'!P$1&", ","")& IF(INDEX('ETAPA OBRA'!Q:Q,MATCH($B13,'ETAPA OBRA'!$B:$B,0))="x",'ETAPA OBRA'!Q$1&", ","")& IF(INDEX('ETAPA OBRA'!R:R,MATCH($B13,'ETAPA OBRA'!$B:$B,0))="x",'ETAPA OBRA'!R$1&", ","")& IF(INDEX('ETAPA OBRA'!S:S,MATCH($B13,'ETAPA OBRA'!$B:$B,0))="x",'ETAPA OBRA'!S$1&", ","")& IF(INDEX('ETAPA OBRA'!T:T,MATCH($B13,'ETAPA OBRA'!$B:$B,0))="x",'ETAPA OBRA'!T$1&", ","")& IF(INDEX('ETAPA OBRA'!U:U,MATCH($B13,'ETAPA OBRA'!$B:$B,0))="x",'ETAPA OBRA'!U$1&", ",""),LEN( IF(INDEX('ETAPA OBRA'!C:C,MATCH($B13,'ETAPA OBRA'!$B:$B,0))="x",'ETAPA OBRA'!C$1&", ","")& IF(INDEX('ETAPA OBRA'!D:D,MATCH($B13,'ETAPA OBRA'!$B:$B,0))="x",'ETAPA OBRA'!D$1&", ","")& IF(INDEX('ETAPA OBRA'!F:F,MATCH($B13,'ETAPA OBRA'!$B:$B,0))="x",'ETAPA OBRA'!F$1&", ","")& IF(INDEX('ETAPA OBRA'!G:G,MATCH($B13,'ETAPA OBRA'!$B:$B,0))="x",'ETAPA OBRA'!G$1&", ","")& IF(INDEX('ETAPA OBRA'!H:H,MATCH($B13,'ETAPA OBRA'!$B:$B,0))="x",'ETAPA OBRA'!H$1&", ","")& IF(INDEX('ETAPA OBRA'!I:I,MATCH($B13,'ETAPA OBRA'!$B:$B,0))="x",'ETAPA OBRA'!I$1&", ","")& IF(INDEX('ETAPA OBRA'!J:J,MATCH($B13,'ETAPA OBRA'!$B:$B,0))="x",'ETAPA OBRA'!J$1&", ","")& IF(INDEX('ETAPA OBRA'!K:K,MATCH($B13,'ETAPA OBRA'!$B:$B,0))="x",'ETAPA OBRA'!K$1&", ","")& IF(INDEX('ETAPA OBRA'!L:L,MATCH($B13,'ETAPA OBRA'!$B:$B,0))="x",'ETAPA OBRA'!L$1&", ","")& IF(INDEX('ETAPA OBRA'!M:M,MATCH($B13,'ETAPA OBRA'!$B:$B,0))="x",'ETAPA OBRA'!M$1&", ","")& IF(INDEX('ETAPA OBRA'!N:N,MATCH($B13,'ETAPA OBRA'!$B:$B,0))="x",'ETAPA OBRA'!N$1&", ","")& IF(INDEX('ETAPA OBRA'!O:O,MATCH($B13,'ETAPA OBRA'!$B:$B,0))="x",'ETAPA OBRA'!O$1&", ","")& IF(INDEX('ETAPA OBRA'!P:P,MATCH($B13,'ETAPA OBRA'!$B:$B,0))="x",'ETAPA OBRA'!P$1&", ","")& IF(INDEX('ETAPA OBRA'!Q:Q,MATCH($B13,'ETAPA OBRA'!$B:$B,0))="x",'ETAPA OBRA'!Q$1&", ","")& IF(INDEX('ETAPA OBRA'!R:R,MATCH($B13,'ETAPA OBRA'!$B:$B,0))="x",'ETAPA OBRA'!R$1&", ","")& IF(INDEX('ETAPA OBRA'!S:S,MATCH($B13,'ETAPA OBRA'!$B:$B,0))="x",'ETAPA OBRA'!S$1&", ","")& IF(INDEX('ETAPA OBRA'!T:T,MATCH($B13,'ETAPA OBRA'!$B:$B,0))="x",'ETAPA OBRA'!T$1&", ","")& IF(INDEX('ETAPA OBRA'!U:U,MATCH($B13,'ETAPA OBRA'!$B:$B,0))="x",'ETAPA OBRA'!U$1&", ","") )-2),"") -> Fabricação / Galvanização | N13: =IF(M13="","Não iniciada", IF(ISNUMBER(FIND("Cancelada",M13)),"Cancelada", IF(ISNUMBER(FIND("Paralisada",M13)),"Paralisada", IF(ISNUMBER(FIND("Finalizado",M13)),"Finalizado", "Em andamento")))) -> Em andamento | O13: 89264 | P13: =SUM($J13:$L13) -> 25453.15 | Q13: =O13-P13 -> 63810.85 | R13: =IF(O13=0,0,Q13/O13) -> 0.71485537 | S13: =IF(R13>=0.2,"✅ OK - Fechar Parceiro","⚠️ Ajustar Custos (<20%)") -> ✅ OK - Fechar Parceiro | T13: =Cronograma[[#This Row],[STATUS]] -> ⏰ ATRASADO
A14: 89050013 | B14: =IF(A14<>"","contel-"&TEXT(COUNTA($A$2:A14),"00"),"") -> contel-13 | C14: IHS | D14: LAGOA DO SITIO | E14: PI | F14: https://maps.app.goo.gl/1h4ggSVzz3kafxQu8 | G14: 1686 | H14: 12771 | I14: PEDRO | J14: =SUM(EQUIPE!C14,EQUIPE!E14,EQUIPE!G14,EQUIPE!I14,EQUIPE!K14,EQUIPE!M14,EQUIPE!O14) -> 0 | K14: 20703.67 | L14: 0 | M14: =IFERROR(LEFT( IF(INDEX('ETAPA OBRA'!C:C,MATCH($B14,'ETAPA OBRA'!$B:$B,0))="x",'ETAPA OBRA'!C$1&", ","")& IF(INDEX('ETAPA OBRA'!D:D,MATCH($B14,'ETAPA OBRA'!$B:$B,0))="x",'ETAPA OBRA'!D$1&", ","")& IF(INDEX('ETAPA OBRA'!F:F,MATCH($B14,'ETAPA OBRA'!$B:$B,0))="x",'ETAPA OBRA'!F$1&", ","")& IF(INDEX('ETAPA OBRA'!G:G,MATCH($B14,'ETAPA OBRA'!$B:$B,0))="x",'ETAPA OBRA'!G$1&", ","")& IF(INDEX('ETAPA OBRA'!H:H,MATCH($B14,'ETAPA OBRA'!$B:$B,0))="x",'ETAPA OBRA'!H$1&", ","")& IF(INDEX('ETAPA OBRA'!I:I,MATCH($B14,'ETAPA OBRA'!$B:$B,0))="x",'ETAPA OBRA'!I$1&", ","")& IF(INDEX('ETAPA OBRA'!J:J,MATCH($B14,'ETAPA OBRA'!$B:$B,0))="x",'ETAPA OBRA'!J$1&", ","")& IF(INDEX('ETAPA OBRA'!K:K,MATCH($B14,'ETAPA OBRA'!$B:$B,0))="x",'ETAPA OBRA'!K$1&", ","")& IF(INDEX('ETAPA OBRA'!L:L,MATCH($B14,'ETAPA OBRA'!$B:$B,0))="x",'ETAPA OBRA'!L$1&", ","")& IF(INDEX('ETAPA OBRA'!M:M,MATCH($B14,'ETAPA OBRA'!$B:$B,0))="x",'ETAPA OBRA'!M$1&", ","")& IF(INDEX('ETAPA OBRA'!N:N,MATCH($B14,'ETAPA OBRA'!$B:$B,0))="x",'ETAPA OBRA'!N$1&", ","")& IF(INDEX('ETAPA OBRA'!O:O,MATCH($B14,'ETAPA OBRA'!$B:$B,0))="x",'ETAPA OBRA'!O$1&", ","")& IF(INDEX('ETAPA OBRA'!P:P,MATCH($B14,'ETAPA OBRA'!$B:$B,0))="x",'ETAPA OBRA'!P$1&", ","")& IF(INDEX('ETAPA OBRA'!Q:Q,MATCH($B14,'ETAPA OBRA'!$B:$B,0))="x",'ETAPA OBRA'!Q$1&", ","")& IF(INDEX('ETAPA OBRA'!R:R,MATCH($B14,'ETAPA OBRA'!$B:$B,0))="x",'ETAPA OBRA'!R$1&", ","")& IF(INDEX('ETAPA OBRA'!S:S,MATCH($B14,'ETAPA OBRA'!$B:$B,0))="x",'ETAPA OBRA'!S$1&", ","")& IF(INDEX('ETAPA OBRA'!T:T,MATCH($B14,'ETAPA OBRA'!$B:$B,0))="x",'ETAPA OBRA'!T$1&", ","")& IF(INDEX('ETAPA OBRA'!U:U,MATCH($B14,'ETAPA OBRA'!$B:$B,0))="x",'ETAPA OBRA'!U$1&", ",""),LEN( IF(INDEX('ETAPA OBRA'!C:C,MATCH($B14,'ETAPA OBRA'!$B:$B,0))="x",'ETAPA OBRA'!C$1&", ","")& IF(INDEX('ETAPA OBRA'!D:D,MATCH($B14,'ETAPA OBRA'!$B:$B,0))="x",'ETAPA OBRA'!D$1&", ","")& IF(INDEX('ETAPA OBRA'!F:F,MATCH($B14,'ETAPA OBRA'!$B:$B,0))="x",'ETAPA OBRA'!F$1&", ","")& IF(INDEX('ETAPA OBRA'!G:G,MATCH($B14,'ETAPA OBRA'!$B:$B,0))="x",'ETAPA OBRA'!G$1&", ","")& IF(INDEX('ETAPA OBRA'!H:H,MATCH($B14,'ETAPA OBRA'!$B:$B,0))="x",'ETAPA OBRA'!H$1&", ","")& IF(INDEX('ETAPA OBRA'!I:I,MATCH($B14,'ETAPA OBRA'!$B:$B,0))="x",'ETAPA OBRA'!I$1&", ","")& IF(INDEX('ETAPA OBRA'!J:J,MATCH($B14,'ETAPA OBRA'!$B:$B,0))="x",'ETAPA OBRA'!J$1&", ","")& IF(INDEX('ETAPA OBRA'!K:K,MATCH($B14,'ETAPA OBRA'!$B:$B,0))="x",'ETAPA OBRA'!K$1&", ","")& IF(INDEX('ETAPA OBRA'!L:L,MATCH($B14,'ETAPA OBRA'!$B:$B,0))="x",'ETAPA OBRA'!L$1&", ","")& IF(INDEX('ETAPA OBRA'!M:M,MATCH($B14,'ETAPA OBRA'!$B:$B,0))="x",'ETAPA OBRA'!M$1&", ","")& IF(INDEX('ETAPA OBRA'!N:N,MATCH($B14,'ETAPA OBRA'!$B:$B,0))="x",'ETAPA OBRA'!N$1&", ","")& IF(INDEX('ETAPA OBRA'!O:O,MATCH($B14,'ETAPA OBRA'!$B:$B,0))="x",'ETAPA OBRA'!O$1&", ","")& IF(INDEX('ETAPA OBRA'!P:P,MATCH($B14,'ETAPA OBRA'!$B:$B,0))="x",'ETAPA OBRA'!P$1&", ","")& IF(INDEX('ETAPA OBRA'!Q:Q,MATCH($B14,'ETAPA OBRA'!$B:$B,0))="x",'ETAPA OBRA'!Q$1&", ","")& IF(INDEX('ETAPA OBRA'!R:R,MATCH($B14,'ETAPA OBRA'!$B:$B,0))="x",'ETAPA OBRA'!R$1&", ","")& IF(INDEX('ETAPA OBRA'!S:S,MATCH($B14,'ETAPA OBRA'!$B:$B,0))="x",'ETAPA OBRA'!S$1&", ","")& IF(INDEX('ETAPA OBRA'!T:T,MATCH($B14,'ETAPA OBRA'!$B:$B,0))="x",'ETAPA OBRA'!T$1&", ","")& IF(INDEX('ETAPA OBRA'!U:U,MATCH($B14,'ETAPA OBRA'!$B:$B,0))="x",'ETAPA OBRA'!U$1&", ","") )-2),"") -> Fabricação / Galvanização | N14: =IF(M14="","Não iniciada", IF(ISNUMBER(FIND("Cancelada",M14)),"Cancelada", IF(ISNUMBER(FIND("Paralisada",M14)),"Paralisada", IF(ISNUMBER(FIND("Finalizado",M14)),"Finalizado", "Em andamento")))) -> Em andamento | O14: 89264 | P14: =SUM($J14:$L14) -> 20703.67 | Q14: =O14-P14 -> 68560.33 | R14: =IF(O14=0,0,Q14/O14) -> 0.76806249 | S14: =IF(R14>=0.2,"✅ OK - Fechar Parceiro","⚠️ Ajustar Custos (<20%)") -> ✅ OK - Fechar Parceiro | T14: =Cronograma[[#This Row],[STATUS]] -> 🕓 EM ANDAMENTO
A15: BR55017-A | B15: =IF(A15<>"","contel-"&TEXT(COUNTA($A$2:A15),"00"),"") -> contel-14 | C15: SBA | D15: MARQUES DE SOUSA | E15: RS | F15: https://maps.app.goo.gl/NXVPhzLsuvYKgB5N9 | G15: 1688 | H15: 12707 | I15: DANILO | J15: =SUM(EQUIPE!C15,EQUIPE!E15,EQUIPE!G15,EQUIPE!I15,EQUIPE!K15,EQUIPE!M15,EQUIPE!O15) -> 7800 | K15: 0 | L15: 4071.47 | M15: =IFERROR(LEFT( IF(INDEX('ETAPA OBRA'!C:C,MATCH($B15,'ETAPA OBRA'!$B:$B,0))="x",'ETAPA OBRA'!C$1&", ","")& IF(INDEX('ETAPA OBRA'!D:D,MATCH($B15,'ETAPA OBRA'!$B:$B,0))="x",'ETAPA OBRA'!D$1&", ","")& IF(INDEX('ETAPA OBRA'!F:F,MATCH($B15,'ETAPA OBRA'!$B:$B,0))="x",'ETAPA OBRA'!F$1&", ","")& IF(INDEX('ETAPA OBRA'!G:G,MATCH($B15,'ETAPA OBRA'!$B:$B,0))="x",'ETAPA OBRA'!G$1&", ","")& IF(INDEX('ETAPA OBRA'!H:H,MATCH($B15,'ETAPA OBRA'!$B:$B,0))="x",'ETAPA OBRA'!H$1&", ","")& IF(INDEX('ETAPA OBRA'!I:I,MATCH($B15,'ETAPA OBRA'!$B:$B,0))="x",'ETAPA OBRA'!I$1&", ","")& IF(INDEX('ETAPA OBRA'!J:J,MATCH($B15,'ETAPA OBRA'!$B:$B,0))="x",'ETAPA OBRA'!J$1&", ","")& IF(INDEX('ETAPA OBRA'!K:K,MATCH($B15,'ETAPA OBRA'!$B:$B,0))="x",'ETAPA OBRA'!K$1&", ","")& IF(INDEX('ETAPA OBRA'!L:L,MATCH($B15,'ETAPA OBRA'!$B:$B,0))="x",'ETAPA OBRA'!L$1&", ","")& IF(INDEX('ETAPA OBRA'!M:M,MATCH($B15,'ETAPA OBRA'!$B:$B,0))="x",'ETAPA OBRA'!M$1&", ","")& IF(INDEX('ETAPA OBRA'!N:N,MATCH($B15,'ETAPA OBRA'!$B:$B,0))="x",'ETAPA OBRA'!N$1&", ","")& IF(INDEX('ETAPA OBRA'!O:O,MATCH($B15,'ETAPA OBRA'!$B:$B,0))="x",'ETAPA OBRA'!O$1&", ","")& IF(INDEX('ETAPA OBRA'!P:P,MATCH($B15,'ETAPA OBRA'!$B:$B,0))="x",'ETAPA OBRA'!P$1&", ","")& IF(INDEX('ETAPA OBRA'!Q:Q,MATCH($B15,'ETAPA OBRA'!$B:$B,0))="x",'ETAPA OBRA'!Q$1&", ","")& IF(INDEX('ETAPA OBRA'!R:R,MATCH($B15,'ETAPA OBRA'!$B:$B,0))="x",'ETAPA OBRA'!R$1&", ","")& IF(INDEX('ETAPA OBRA'!S:S,MATCH($B15,'ETAPA OBRA'!$B:$B,0))="x",'ETAPA OBRA'!S$1&", ","")& IF(INDEX('ETAPA OBRA'!T:T,MATCH($B15,'ETAPA OBRA'!$B:$B,0))="x",'ETAPA OBRA'!T$1&", ","")& IF(INDEX('ETAPA OBRA'!U:U,MATCH($B15,'ETAPA OBRA'!$B:$B,0))="x",'ETAPA OBRA'!U$1&", ",""),LEN( IF(INDEX('ETAPA OBRA'!C:C,MATCH($B15,'ETAPA OBRA'!$B:$B,0))="x",'ETAPA OBRA'!C$1&", ","")& IF(INDEX('ETAPA OBRA'!D:D,MATCH($B15,'ETAPA OBRA'!$B:$B,0))="x",'ETAPA OBRA'!D$1&", ","")& IF(INDEX('ETAPA OBRA'!F:F,MATCH($B15,'ETAPA OBRA'!$B:$B,0))="x",'ETAPA OBRA'!F$1&", ","")& IF(INDEX('ETAPA OBRA'!G:G,MATCH($B15,'ETAPA OBRA'!$B:$B,0))="x",'ETAPA OBRA'!G$1&", ","")& IF(INDEX('ETAPA OBRA'!H:H,MATCH($B15,'ETAPA OBRA'!$B:$B,0))="x",'ETAPA OBRA'!H$1&", ","")& IF(INDEX('ETAPA OBRA'!I:I,MATCH($B15,'ETAPA OBRA'!$B:$B,0))="x",'ETAPA OBRA'!I$1&", ","")& IF(INDEX('ETAPA OBRA'!J:J,MATCH($B15,'ETAPA OBRA'!$B:$B,0))="x",'ETAPA OBRA'!J$1&", ","")& IF(INDEX('ETAPA OBRA'!K:K,MATCH($B15,'ETAPA OBRA'!$B:$B,0))="x",'ETAPA OBRA'!K$1&", ","")& IF(INDEX('ETAPA OBRA'!L:L,MATCH($B15,'ETAPA OBRA'!$B:$B,0))="x",'ETAPA OBRA'!L$1&", ","")& IF(INDEX('ETAPA OBRA'!M:M,MATCH($B15,'ETAPA OBRA'!$B:$B,0))="x",'ETAPA OBRA'!M$1&", ","")& IF(INDEX('ETAPA OBRA'!N:N,MATCH($B15,'ETAPA OBRA'!$B:$B,0))="x",'ETAPA OBRA'!N$1&", ","")& IF(INDEX('ETAPA OBRA'!O:O,MATCH($B15,'ETAPA OBRA'!$B:$B,0))="x",'ETAPA OBRA'!O$1&", ","")& IF(INDEX('ETAPA OBRA'!P:P,MATCH($B15,'ETAPA OBRA'!$B:$B,0))="x",'ETAPA OBRA'!P$1&", ","")& IF(INDEX('ETAPA OBRA'!Q:Q,MATCH($B15,'ETAPA OBRA'!$B:$B,0))="x",'ETAPA OBRA'!Q$1&", ","")& IF(INDEX('ETAPA OBRA'!R:R,MATCH($B15,'ETAPA OBRA'!$B:$B,0))="x",'ETAPA OBRA'!R$1&", ","")& IF(INDEX('ETAPA OBRA'!S:S,MATCH($B15,'ETAPA OBRA'!$B:$B,0))="x",'ETAPA OBRA'!S$1&", ","")& IF(INDEX('ETAPA OBRA'!T:T,MATCH($B15,'ETAPA OBRA'!$B:$B,0))="x",'ETAPA OBRA'!T$1&", ","")& IF(INDEX('ETAPA OBRA'!U:U,MATCH($B15,'ETAPA OBRA'!$B:$B,0))="x",'ETAPA OBRA'!U$1&", ","") )-2),"") -> Finalizado | N15: =IF(M15="","Não iniciada", IF(ISNUMBER(FIND("Cancelada",M15)),"Cancelada", IF(ISNUMBER(FIND("Paralisada",M15)),"Paralisada", IF(ISNUMBER(FIND("Finalizado",M15)),"Finalizado", "Em andamento")))) -> Finalizado | O15: 26432.8 | P15: =SUM($J15:$L15) -> 11871.47 | Q15: =O15-P15 -> 14561.33 | R15: =IF(O15=0,0,Q15/O15) -> 0.5508811 | S15: =IF(R15>=0.2,"✅ OK - Fechar Parceiro","⚠️ Ajustar Custos (<20%)") -> ✅ OK - Fechar Parceiro | T15: =Cronograma[[#This Row],[STATUS]] -> ✅ CONCLUÍDO
A16: BR56393-A | B16: =IF(A16<>"","contel-"&TEXT(COUNTA($A$2:A16),"00"),"") -> contel-15 | C16: SBA | D16: TUPACIGUARA | E16: MG | F16: https://maps.app.goo.gl/68P1u6qzLNHyVJf99 | G16: 1689 | H16: 12708 | I16: DANILO | J16: =SUM(EQUIPE!C16,EQUIPE!E16,EQUIPE!G16,EQUIPE!I16,EQUIPE!K16,EQUIPE!M16,EQUIPE!O16) -> 5900 | K16: 0 | L16: 503.03 | M16: =IFERROR(LEFT( IF(INDEX('ETAPA OBRA'!C:C,MATCH($B16,'ETAPA OBRA'!$B:$B,0))="x",'ETAPA OBRA'!C$1&", ","")& IF(INDEX('ETAPA OBRA'!D:D,MATCH($B16,'ETAPA OBRA'!$B:$B,0))="x",'ETAPA OBRA'!D$1&", ","")& IF(INDEX('ETAPA OBRA'!F:F,MATCH($B16,'ETAPA OBRA'!$B:$B,0))="x",'ETAPA OBRA'!F$1&", ","")& IF(INDEX('ETAPA OBRA'!G:G,MATCH($B16,'ETAPA OBRA'!$B:$B,0))="x",'ETAPA OBRA'!G$1&", ","")& IF(INDEX('ETAPA OBRA'!H:H,MATCH($B16,'ETAPA OBRA'!$B:$B,0))="x",'ETAPA OBRA'!H$1&", ","")& IF(INDEX('ETAPA OBRA'!I:I,MATCH($B16,'ETAPA OBRA'!$B:$B,0))="x",'ETAPA OBRA'!I$1&", ","")& IF(INDEX('ETAPA OBRA'!J:J,MATCH($B16,'ETAPA OBRA'!$B:$B,0))="x",'ETAPA OBRA'!J$1&", ","")& IF(INDEX('ETAPA OBRA'!K:K,MATCH($B16,'ETAPA OBRA'!$B:$B,0))="x",'ETAPA OBRA'!K$1&", ","")& IF(INDEX('ETAPA OBRA'!L:L,MATCH($B16,'ETAPA OBRA'!$B:$B,0))="x",'ETAPA OBRA'!L$1&", ","")& IF(INDEX('ETAPA OBRA'!M:M,MATCH($B16,'ETAPA OBRA'!$B:$B,0))="x",'ETAPA OBRA'!M$1&", ","")& IF(INDEX('ETAPA OBRA'!N:N,MATCH($B16,'ETAPA OBRA'!$B:$B,0))="x",'ETAPA OBRA'!N$1&", ","")& IF(INDEX('ETAPA OBRA'!O:O,MATCH($B16,'ETAPA OBRA'!$B:$B,0))="x",'ETAPA OBRA'!O$1&", ","")& IF(INDEX('ETAPA OBRA'!P:P,MATCH($B16,'ETAPA OBRA'!$B:$B,0))="x",'ETAPA OBRA'!P$1&", ","")& IF(INDEX('ETAPA OBRA'!Q:Q,MATCH($B16,'ETAPA OBRA'!$B:$B,0))="x",'ETAPA OBRA'!Q$1&", ","")& IF(INDEX('ETAPA OBRA'!R:R,MATCH($B16,'ETAPA OBRA'!$B:$B,0))="x",'ETAPA OBRA'!R$1&", ","")& IF(INDEX('ETAPA OBRA'!S:S,MATCH($B16,'ETAPA OBRA'!$B:$B,0))="x",'ETAPA OBRA'!S$1&", ","")& IF(INDEX('ETAPA OBRA'!T:T,MATCH($B16,'ETAPA OBRA'!$B:$B,0))="x",'ETAPA OBRA'!T$1&", ","")& IF(INDEX('ETAPA OBRA'!U:U,MATCH($B16,'ETAPA OBRA'!$B:$B,0))="x",'ETAPA OBRA'!U$1&", ",""),LEN( IF(INDEX('ETAPA OBRA'!C:C,MATCH($B16,'ETAPA OBRA'!$B:$B,0))="x",'ETAPA OBRA'!C$1&", ","")& IF(INDEX('ETAPA OBRA'!D:D,MATCH($B16,'ETAPA OBRA'!$B:$B,0))="x",'ETAPA OBRA'!D$1&", ","")& IF(INDEX('ETAPA OBRA'!F:F,MATCH($B16,'ETAPA OBRA'!$B:$B,0))="x",'ETAPA OBRA'!F$1&", ","")& IF(INDEX('ETAPA OBRA'!G:G,MATCH($B16,'ETAPA OBRA'!$B:$B,0))="x",'ETAPA OBRA'!G$1&", ","")& IF(INDEX('ETAPA OBRA'!H:H,MATCH($B16,'ETAPA OBRA'!$B:$B,0))="x",'ETAPA OBRA'!H$1&", ","")& IF(INDEX('ETAPA OBRA'!I:I,MATCH($B16,'ETAPA OBRA'!$B:$B,0))="x",'ETAPA OBRA'!I$1&", ","")& IF(INDEX('ETAPA OBRA'!J:J,MATCH($B16,'ETAPA OBRA'!$B:$B,0))="x",'ETAPA OBRA'!J$1&", ","")& IF(INDEX('ETAPA OBRA'!K:K,MATCH($B16,'ETAPA OBRA'!$B:$B,0))="x",'ETAPA OBRA'!K$1&", ","")& IF(INDEX('ETAPA OBRA'!L:L,MATCH($B16,'ETAPA OBRA'!$B:$B,0))="x",'ETAPA OBRA'!L$1&", ","")& IF(INDEX('ETAPA OBRA'!M:M,MATCH($B16,'ETAPA OBRA'!$B:$B,0))="x",'ETAPA OBRA'!M$1&", ","")& IF(INDEX('ETAPA OBRA'!N:N,MATCH($B16,'ETAPA OBRA'!$B:$B,0))="x",'ETAPA OBRA'!N$1&", ","")& IF(INDEX('ETAPA OBRA'!O:O,MATCH($B16,'ETAPA OBRA'!$B:$B,0))="x",'ETAPA OBRA'!O$1&", ","")& IF(INDEX('ETAPA OBRA'!P:P,MATCH($B16,'ETAPA OBRA'!$B:$B,0))="x",'ETAPA OBRA'!P$1&", ","")& IF(INDEX('ETAPA OBRA'!Q:Q,MATCH($B16,'ETAPA OBRA'!$B:$B,0))="x",'ETAPA OBRA'!Q$1&", ","")& IF(INDEX('ETAPA OBRA'!R:R,MATCH($B16,'ETAPA OBRA'!$B:$B,0))="x",'ETAPA OBRA'!R$1&", ","")& IF(INDEX('ETAPA OBRA'!S:S,MATCH($B16,'ETAPA OBRA'!$B:$B,0))="x",'ETAPA OBRA'!S$1&", ","")& IF(INDEX('ETAPA OBRA'!T:T,MATCH($B16,'ETAPA OBRA'!$B:$B,0))="x",'ETAPA OBRA'!T$1&", ","")& IF(INDEX('ETAPA OBRA'!U:U,MATCH($B16,'ETAPA OBRA'!$B:$B,0))="x",'ETAPA OBRA'!U$1&", ","") )-2),"") -> Finalizado | N16: =IF(M16="","Não iniciada", IF(ISNUMBER(FIND("Cancelada",M16)),"Cancelada", IF(ISNUMBER(FIND("Paralisada",M16)),"Paralisada", IF(ISNUMBER(FIND("Finalizado",M16)),"Finalizado", "Em andamento")))) -> Finalizado | O16: 10686 | P16: =SUM($J16:$L16) -> 6403.03 | Q16: =O16-P16 -> 4282.97 | R16: =IF(O16=0,0,Q16/O16) -> 0.40080198 | S16: =IF(R16>=0.2,"✅ OK - Fechar Parceiro","⚠️ Ajustar Custos (<20%)") -> ✅ OK - Fechar Parceiro | T16: =Cronograma[[#This Row],[STATUS]] -> ✅ CONCLUÍDO
A17: BR72051-A | B17: =IF(A17<>"","contel-"&TEXT(COUNTA($A$2:A17),"00"),"") -> contel-16 | C17: SBA | D17: ÁGUA BOA | E17: MG | F17: https://maps.app.goo.gl/fWBGywBc7ew56GDf6 | G17: 1690 | H17: 12709 | I17: PEDRO | J17: =SUM(EQUIPE!C17,EQUIPE!E17,EQUIPE!G17,EQUIPE!I17,EQUIPE!K17,EQUIPE!M17,EQUIPE!O17) -> 2600 | K17: 690 | L17: 405.79 | M17: =IFERROR(LEFT( IF(INDEX('ETAPA OBRA'!C:C,MATCH($B17,'ETAPA OBRA'!$B:$B,0))="x",'ETAPA OBRA'!C$1&", ","")& IF(INDEX('ETAPA OBRA'!D:D,MATCH($B17,'ETAPA OBRA'!$B:$B,0))="x",'ETAPA OBRA'!D$1&", ","")& IF(INDEX('ETAPA OBRA'!F:F,MATCH($B17,'ETAPA OBRA'!$B:$B,0))="x",'ETAPA OBRA'!F$1&", ","")& IF(INDEX('ETAPA OBRA'!G:G,MATCH($B17,'ETAPA OBRA'!$B:$B,0))="x",'ETAPA OBRA'!G$1&", ","")& IF(INDEX('ETAPA OBRA'!H:H,MATCH($B17,'ETAPA OBRA'!$B:$B,0))="x",'ETAPA OBRA'!H$1&", ","")& IF(INDEX('ETAPA OBRA'!I:I,MATCH($B17,'ETAPA OBRA'!$B:$B,0))="x",'ETAPA OBRA'!I$1&", ","")& IF(INDEX('ETAPA OBRA'!J:J,MATCH($B17,'ETAPA OBRA'!$B:$B,0))="x",'ETAPA OBRA'!J$1&", ","")& IF(INDEX('ETAPA OBRA'!K:K,MATCH($B17,'ETAPA OBRA'!$B:$B,0))="x",'ETAPA OBRA'!K$1&", ","")& IF(INDEX('ETAPA OBRA'!L:L,MATCH($B17,'ETAPA OBRA'!$B:$B,0))="x",'ETAPA OBRA'!L$1&", ","")& IF(INDEX('ETAPA OBRA'!M:M,MATCH($B17,'ETAPA OBRA'!$B:$B,0))="x",'ETAPA OBRA'!M$1&", ","")& IF(INDEX('ETAPA OBRA'!N:N,MATCH($B17,'ETAPA OBRA'!$B:$B,0))="x",'ETAPA OBRA'!N$1&", ","")& IF(INDEX('ETAPA OBRA'!O:O,MATCH($B17,'ETAPA OBRA'!$B:$B,0))="x",'ETAPA OBRA'!O$1&", ","")& IF(INDEX('ETAPA OBRA'!P:P,MATCH($B17,'ETAPA OBRA'!$B:$B,0))="x",'ETAPA OBRA'!P$1&", ","")& IF(INDEX('ETAPA OBRA'!Q:Q,MATCH($B17,'ETAPA OBRA'!$B:$B,0))="x",'ETAPA OBRA'!Q$1&", ","")& IF(INDEX('ETAPA OBRA'!R:R,MATCH($B17,'ETAPA OBRA'!$B:$B,0))="x",'ETAPA OBRA'!R$1&", ","")& IF(INDEX('ETAPA OBRA'!S:S,MATCH($B17,'ETAPA OBRA'!$B:$B,0))="x",'ETAPA OBRA'!S$1&", ","")& IF(INDEX('ETAPA OBRA'!T:T,MATCH($B17,'ETAPA OBRA'!$B:$B,0))="x",'ETAPA OBRA'!T$1&", ","")& IF(INDEX('ETAPA OBRA'!U:U,MATCH($B17,'ETAPA OBRA'!$B:$B,0))="x",'ETAPA OBRA'!U$1&", ",""),LEN( IF(INDEX('ETAPA OBRA'!C:C,MATCH($B17,'ETAPA OBRA'!$B:$B,0))="x",'ETAPA OBRA'!C$1&", ","")& IF(INDEX('ETAPA OBRA'!D:D,MATCH($B17,'ETAPA OBRA'!$B:$B,0))="x",'ETAPA OBRA'!D$1&", ","")& IF(INDEX('ETAPA OBRA'!F:F,MATCH($B17,'ETAPA OBRA'!$B:$B,0))="x",'ETAPA OBRA'!F$1&", ","")& IF(INDEX('ETAPA OBRA'!G:G,MATCH($B17,'ETAPA OBRA'!$B:$B,0))="x",'ETAPA OBRA'!G$1&", ","")& IF(INDEX('ETAPA OBRA'!H:H,MATCH($B17,'ETAPA OBRA'!$B:$B,0))="x",'ETAPA OBRA'!H$1&", ","")& IF(INDEX('ETAPA OBRA'!I:I,MATCH($B17,'ETAPA OBRA'!$B:$B,0))="x",'ETAPA OBRA'!I$1&", ","")& IF(INDEX('ETAPA OBRA'!J:J,MATCH($B17,'ETAPA OBRA'!$B:$B,0))="x",'ETAPA OBRA'!J$1&", ","")& IF(INDEX('ETAPA OBRA'!K:K,MATCH($B17,'ETAPA OBRA'!$B:$B,0))="x",'ETAPA OBRA'!K$1&", ","")& IF(INDEX('ETAPA OBRA'!L:L,MATCH($B17,'ETAPA OBRA'!$B:$B,0))="x",'ETAPA OBRA'!L$1&", ","")& IF(INDEX('ETAPA OBRA'!M:M,MATCH($B17,'ETAPA OBRA'!$B:$B,0))="x",'ETAPA OBRA'!M$1&", ","")& IF(INDEX('ETAPA OBRA'!N:N,MATCH($B17,'ETAPA OBRA'!$B:$B,0))="x",'ETAPA OBRA'!N$1&", ","")& IF(INDEX('ETAPA OBRA'!O:O,MATCH($B17,'ETAPA OBRA'!$B:$B,0))="x",'ETAPA OBRA'!O$1&", ","")& IF(INDEX('ETAPA OBRA'!P:P,MATCH($B17,'ETAPA OBRA'!$B:$B,0))="x",'ETAPA OBRA'!P$1&", ","")& IF(INDEX('ETAPA OBRA'!Q:Q,MATCH($B17,'ETAPA OBRA'!$B:$B,0))="x",'ETAPA OBRA'!Q$1&", ","")& IF(INDEX('ETAPA OBRA'!R:R,MATCH($B17,'ETAPA OBRA'!$B:$B,0))="x",'ETAPA OBRA'!R$1&", ","")& IF(INDEX('ETAPA OBRA'!S:S,MATCH($B17,'ETAPA OBRA'!$B:$B,0))="x",'ETAPA OBRA'!S$1&", ","")& IF(INDEX('ETAPA OBRA'!T:T,MATCH($B17,'ETAPA OBRA'!$B:$B,0))="x",'ETAPA OBRA'!T$1&", ","")& IF(INDEX('ETAPA OBRA'!U:U,MATCH($B17,'ETAPA OBRA'!$B:$B,0))="x",'ETAPA OBRA'!U$1&", ","") )-2),"") -> Finalizado | N17: =IF(M17="","Não iniciada", IF(ISNUMBER(FIND("Cancelada",M17)),"Cancelada", IF(ISNUMBER(FIND("Paralisada",M17)),"Paralisada", IF(ISNUMBER(FIND("Finalizado",M17)),"Finalizado", "Em andamento")))) -> Finalizado | O17: 9043.36 | P17: =SUM($J17:$L17) -> 3695.79 | Q17: =O17-P17 -> 5347.57 | R17: =IF(O17=0,0,Q17/O17) -> 0.59132557 | S17: =IF(R17>=0.2,"✅ OK - Fechar Parceiro","⚠️ Ajustar Custos (<20%)") -> ✅ OK - Fechar Parceiro | T17: =Cronograma[[#This Row],[STATUS]] -> ✅ CONCLUÍDO
A18: BR72113-A | B18: =IF(A18<>"","contel-"&TEXT(COUNTA($A$2:A18),"00"),"") -> contel-17 | C18: SBA | D18: UBERLÂNDIA | E18: MG | F18: https://maps.app.goo.gl/1tFooPuf357rJP9D8 | G18: 1691 | H18: 12710 | I18: DANILO | J18: =SUM(EQUIPE!C18,EQUIPE!E18,EQUIPE!G18,EQUIPE!I18,EQUIPE!K18,EQUIPE!M18,EQUIPE!O18) -> 7100 | K18: 0 | L18: 813.03 | M18: =IFERROR(LEFT( IF(INDEX('ETAPA OBRA'!C:C,MATCH($B18,'ETAPA OBRA'!$B:$B,0))="x",'ETAPA OBRA'!C$1&", ","")& IF(INDEX('ETAPA OBRA'!D:D,MATCH($B18,'ETAPA OBRA'!$B:$B,0))="x",'ETAPA OBRA'!D$1&", ","")& IF(INDEX('ETAPA OBRA'!F:F,MATCH($B18,'ETAPA OBRA'!$B:$B,0))="x",'ETAPA OBRA'!F$1&", ","")& IF(INDEX('ETAPA OBRA'!G:G,MATCH($B18,'ETAPA OBRA'!$B:$B,0))="x",'ETAPA OBRA'!G$1&", ","")& IF(INDEX('ETAPA OBRA'!H:H,MATCH($B18,'ETAPA OBRA'!$B:$B,0))="x",'ETAPA OBRA'!H$1&", ","")& IF(INDEX('ETAPA OBRA'!I:I,MATCH($B18,'ETAPA OBRA'!$B:$B,0))="x",'ETAPA OBRA'!I$1&", ","")& IF(INDEX('ETAPA OBRA'!J:J,MATCH($B18,'ETAPA OBRA'!$B:$B,0))="x",'ETAPA OBRA'!J$1&", ","")& IF(INDEX('ETAPA OBRA'!K:K,MATCH($B18,'ETAPA OBRA'!$B:$B,0))="x",'ETAPA OBRA'!K$1&", ","")& IF(INDEX('ETAPA OBRA'!L:L,MATCH($B18,'ETAPA OBRA'!$B:$B,0))="x",'ETAPA OBRA'!L$1&", ","")& IF(INDEX('ETAPA OBRA'!M:M,MATCH($B18,'ETAPA OBRA'!$B:$B,0))="x",'ETAPA OBRA'!M$1&", ","")& IF(INDEX('ETAPA OBRA'!N:N,MATCH($B18,'ETAPA OBRA'!$B:$B,0))="x",'ETAPA OBRA'!N$1&", ","")& IF(INDEX('ETAPA OBRA'!O:O,MATCH($B18,'ETAPA OBRA'!$B:$B,0))="x",'ETAPA OBRA'!O$1&", ","")& IF(INDEX('ETAPA OBRA'!P:P,MATCH($B18,'ETAPA OBRA'!$B:$B,0))="x",'ETAPA OBRA'!P$1&", ","")& IF(INDEX('ETAPA OBRA'!Q:Q,MATCH($B18,'ETAPA OBRA'!$B:$B,0))="x",'ETAPA OBRA'!Q$1&", ","")& IF(INDEX('ETAPA OBRA'!R:R,MATCH($B18,'ETAPA OBRA'!$B:$B,0))="x",'ETAPA OBRA'!R$1&", ","")& IF(INDEX('ETAPA OBRA'!S:S,MATCH($B18,'ETAPA OBRA'!$B:$B,0))="x",'ETAPA OBRA'!S$1&", ","")& IF(INDEX('ETAPA OBRA'!T:T,MATCH($B18,'ETAPA OBRA'!$B:$B,0))="x",'ETAPA OBRA'!T$1&", ","")& IF(INDEX('ETAPA OBRA'!U:U,MATCH($B18,'ETAPA OBRA'!$B:$B,0))="x",'ETAPA OBRA'!U$1&", ",""),LEN( IF(INDEX('ETAPA OBRA'!C:C,MATCH($B18,'ETAPA OBRA'!$B:$B,0))="x",'ETAPA OBRA'!C$1&", ","")& IF(INDEX('ETAPA OBRA'!D:D,MATCH($B18,'ETAPA OBRA'!$B:$B,0))="x",'ETAPA OBRA'!D$1&", ","")& IF(INDEX('ETAPA OBRA'!F:F,MATCH($B18,'ETAPA OBRA'!$B:$B,0))="x",'ETAPA OBRA'!F$1&", ","")& IF(INDEX('ETAPA OBRA'!G:G,MATCH($B18,'ETAPA OBRA'!$B:$B,0))="x",'ETAPA OBRA'!G$1&", ","")& IF(INDEX('ETAPA OBRA'!H:H,MATCH($B18,'ETAPA OBRA'!$B:$B,0))="x",'ETAPA OBRA'!H$1&", ","")& IF(INDEX('ETAPA OBRA'!I:I,MATCH($B18,'ETAPA OBRA'!$B:$B,0))="x",'ETAPA OBRA'!I$1&", ","")& IF(INDEX('ETAPA OBRA'!J:J,MATCH($B18,'ETAPA OBRA'!$B:$B,0))="x",'ETAPA OBRA'!J$1&", ","")& IF(INDEX('ETAPA OBRA'!K:K,MATCH($B18,'ETAPA OBRA'!$B:$B,0))="x",'ETAPA OBRA'!K$1&", ","")& IF(INDEX('ETAPA OBRA'!L:L,MATCH($B18,'ETAPA OBRA'!$B:$B,0))="x",'ETAPA OBRA'!L$1&", ","")& IF(INDEX('ETAPA OBRA'!M:M,MATCH($B18,'ETAPA OBRA'!$B:$B,0))="x",'ETAPA OBRA'!M$1&", ","")& IF(INDEX('ETAPA OBRA'!N:N,MATCH($B18,'ETAPA OBRA'!$B:$B,0))="x",'ETAPA OBRA'!N$1&", ","")& IF(INDEX('ETAPA OBRA'!O:O,MATCH($B18,'ETAPA OBRA'!$B:$B,0))="x",'ETAPA OBRA'!O$1&", ","")& IF(INDEX('ETAPA OBRA'!P:P,MATCH($B18,'ETAPA OBRA'!$B:$B,0))="x",'ETAPA OBRA'!P$1&", ","")& IF(INDEX('ETAPA OBRA'!Q:Q,MATCH($B18,'ETAPA OBRA'!$B:$B,0))="x",'ETAPA OBRA'!Q$1&", ","")& IF(INDEX('ETAPA OBRA'!R:R,MATCH($B18,'ETAPA OBRA'!$B:$B,0))="x",'ETAPA OBRA'!R$1&", ","")& IF(INDEX('ETAPA OBRA'!S:S,MATCH($B18,'ETAPA OBRA'!$B:$B,0))="x",'ETAPA OBRA'!S$1&", ","")& IF(INDEX('ETAPA OBRA'!T:T,MATCH($B18,'ETAPA OBRA'!$B:$B,0))="x",'ETAPA OBRA'!T$1&", ","")& IF(INDEX('ETAPA OBRA'!U:U,MATCH($B18,'ETAPA OBRA'!$B:$B,0))="x",'ETAPA OBRA'!U$1&", ","") )-2),"") -> Finalizado | N18: =IF(M18="","Não iniciada", IF(ISNUMBER(FIND("Cancelada",M18)),"Cancelada", IF(ISNUMBER(FIND("Paralisada",M18)),"Paralisada", IF(ISNUMBER(FIND("Finalizado",M18)),"Finalizado", "Em andamento")))) -> Finalizado | O18: 14054.63 | P18: =SUM($J18:$L18) -> 7913.03 | Q18: =O18-P18 -> 6141.6 | R18: =IF(O18=0,0,Q18/O18) -> 0.43698055 | S18: =IF(R18>=0.2,"✅ OK - Fechar Parceiro","⚠️ Ajustar Custos (<20%)") -> ✅ OK - Fechar Parceiro | T18: =Cronograma[[#This Row],[STATUS]] -> ✅ CONCLUÍDO
A19: BR80008-A | B19: =IF(A19<>"","contel-"&TEXT(COUNTA($A$2:A19),"00"),"") -> contel-18 | C19: SBA | D19: ONDA VERDE | E19: SP | F19: https://maps.app.goo.gl/a3MkFUiYZv8tBiR68 | G19: 1692 | H19: 12725 | I19: PEDRO | J19: =SUM(EQUIPE!C19,EQUIPE!E19,EQUIPE!G19,EQUIPE!I19,EQUIPE!K19,EQUIPE!M19,EQUIPE!O19) -> 4000 | K19: 2506.37 | L19: 551.14 | M19: =IFERROR(LEFT( IF(INDEX('ETAPA OBRA'!C:C,MATCH($B19,'ETAPA OBRA'!$B:$B,0))="x",'ETAPA OBRA'!C$1&", ","")& IF(INDEX('ETAPA OBRA'!D:D,MATCH($B19,'ETAPA OBRA'!$B:$B,0))="x",'ETAPA OBRA'!D$1&", ","")& IF(INDEX('ETAPA OBRA'!F:F,MATCH($B19,'ETAPA OBRA'!$B:$B,0))="x",'ETAPA OBRA'!F$1&", ","")& IF(INDEX('ETAPA OBRA'!G:G,MATCH($B19,'ETAPA OBRA'!$B:$B,0))="x",'ETAPA OBRA'!G$1&", ","")& IF(INDEX('ETAPA OBRA'!H:H,MATCH($B19,'ETAPA OBRA'!$B:$B,0))="x",'ETAPA OBRA'!H$1&", ","")& IF(INDEX('ETAPA OBRA'!I:I,MATCH($B19,'ETAPA OBRA'!$B:$B,0))="x",'ETAPA OBRA'!I$1&", ","")& IF(INDEX('ETAPA OBRA'!J:J,MATCH($B19,'ETAPA OBRA'!$B:$B,0))="x",'ETAPA OBRA'!J$1&", ","")& IF(INDEX('ETAPA OBRA'!K:K,MATCH($B19,'ETAPA OBRA'!$B:$B,0))="x",'ETAPA OBRA'!K$1&", ","")& IF(INDEX('ETAPA OBRA'!L:L,MATCH($B19,'ETAPA OBRA'!$B:$B,0))="x",'ETAPA OBRA'!L$1&", ","")& IF(INDEX('ETAPA OBRA'!M:M,MATCH($B19,'ETAPA OBRA'!$B:$B,0))="x",'ETAPA OBRA'!M$1&", ","")& IF(INDEX('ETAPA OBRA'!N:N,MATCH($B19,'ETAPA OBRA'!$B:$B,0))="x",'ETAPA OBRA'!N$1&", ","")& IF(INDEX('ETAPA OBRA'!O:O,MATCH($B19,'ETAPA OBRA'!$B:$B,0))="x",'ETAPA OBRA'!O$1&", ","")& IF(INDEX('ETAPA OBRA'!P:P,MATCH($B19,'ETAPA OBRA'!$B:$B,0))="x",'ETAPA OBRA'!P$1&", ","")& IF(INDEX('ETAPA OBRA'!Q:Q,MATCH($B19,'ETAPA OBRA'!$B:$B,0))="x",'ETAPA OBRA'!Q$1&", ","")& IF(INDEX('ETAPA OBRA'!R:R,MATCH($B19,'ETAPA OBRA'!$B:$B,0))="x",'ETAPA OBRA'!R$1&", ","")& IF(INDEX('ETAPA OBRA'!S:S,MATCH($B19,'ETAPA OBRA'!$B:$B,0))="x",'ETAPA OBRA'!S$1&", ","")& IF(INDEX('ETAPA OBRA'!T:T,MATCH($B19,'ETAPA OBRA'!$B:$B,0))="x",'ETAPA OBRA'!T$1&", ","")& IF(INDEX('ETAPA OBRA'!U:U,MATCH($B19,'ETAPA OBRA'!$B:$B,0))="x",'ETAPA OBRA'!U$1&", ",""),LEN( IF(INDEX('ETAPA OBRA'!C:C,MATCH($B19,'ETAPA OBRA'!$B:$B,0))="x",'ETAPA OBRA'!C$1&", ","")& IF(INDEX('ETAPA OBRA'!D:D,MATCH($B19,'ETAPA OBRA'!$B:$B,0))="x",'ETAPA OBRA'!D$1&", ","")& IF(INDEX('ETAPA OBRA'!F:F,MATCH($B19,'ETAPA OBRA'!$B:$B,0))="x",'ETAPA OBRA'!F$1&", ","")& IF(INDEX('ETAPA OBRA'!G:G,MATCH($B19,'ETAPA OBRA'!$B:$B,0))="x",'ETAPA OBRA'!G$1&", ","")& IF(INDEX('ETAPA OBRA'!H:H,MATCH($B19,'ETAPA OBRA'!$B:$B,0))="x",'ETAPA OBRA'!H$1&", ","")& IF(INDEX('ETAPA OBRA'!I:I,MATCH($B19,'ETAPA OBRA'!$B:$B,0))="x",'ETAPA OBRA'!I$1&", ","")& IF(INDEX('ETAPA OBRA'!J:J,MATCH($B19,'ETAPA OBRA'!$B:$B,0))="x",'ETAPA OBRA'!J$1&", ","")& IF(INDEX('ETAPA OBRA'!K:K,MATCH($B19,'ETAPA OBRA'!$B:$B,0))="x",'ETAPA OBRA'!K$1&", ","")& IF(INDEX('ETAPA OBRA'!L:L,MATCH($B19,'ETAPA OBRA'!$B:$B,0))="x",'ETAPA OBRA'!L$1&", ","")& IF(INDEX('ETAPA OBRA'!M:M,MATCH($B19,'ETAPA OBRA'!$B:$B,0))="x",'ETAPA OBRA'!M$1&", ","")& IF(INDEX('ETAPA OBRA'!N:N,MATCH($B19,'ETAPA OBRA'!$B:$B,0))="x",'ETAPA OBRA'!N$1&", ","")& IF(INDEX('ETAPA OBRA'!O:O,MATCH($B19,'ETAPA OBRA'!$B:$B,0))="x",'ETAPA OBRA'!O$1&", ","")& IF(INDEX('ETAPA OBRA'!P:P,MATCH($B19,'ETAPA OBRA'!$B:$B,0))="x",'ETAPA OBRA'!P$1&", ","")& IF(INDEX('ETAPA OBRA'!Q:Q,MATCH($B19,'ETAPA OBRA'!$B:$B,0))="x",'ETAPA OBRA'!Q$1&", ","")& IF(INDEX('ETAPA OBRA'!R:R,MATCH($B19,'ETAPA OBRA'!$B:$B,0))="x",'ETAPA OBRA'!R$1&", ","")& IF(INDEX('ETAPA OBRA'!S:S,MATCH($B19,'ETAPA OBRA'!$B:$B,0))="x",'ETAPA OBRA'!S$1&", ","")& IF(INDEX('ETAPA OBRA'!T:T,MATCH($B19,'ETAPA OBRA'!$B:$B,0))="x",'ETAPA OBRA'!T$1&", ","")& IF(INDEX('ETAPA OBRA'!U:U,MATCH($B19,'ETAPA OBRA'!$B:$B,0))="x",'ETAPA OBRA'!U$1&", ","") )-2),"") -> Finalizado | N19: =IF(M19="","Não iniciada", IF(ISNUMBER(FIND("Cancelada",M19)),"Cancelada", IF(ISNUMBER(FIND("Paralisada",M19)),"Paralisada", IF(ISNUMBER(FIND("Finalizado",M19)),"Finalizado", "Em andamento")))) -> Finalizado | O19: 11578.6 | P19: =SUM($J19:$L19) -> 7057.51 | Q19: =O19-P19 -> 4521.09 | R19: =IF(O19=0,0,Q19/O19) -> 0.39046949 | S19: =IF(R19>=0.2,"✅ OK - Fechar Parceiro","⚠️ Ajustar Custos (<20%)") -> ✅ OK - Fechar Parceiro | T19: =Cronograma[[#This Row],[STATUS]] -> ✅ CONCLUÍDO
A20: SPVTR004 | B20: =IF(A20<>"","contel-"&TEXT(COUNTA($A$2:A20),"00"),"") -> contel-19 | C20: HLB | D20: VOTORANTIM | E20: SP | F20: https://maps.app.goo.gl/Th38PhYKAncLipZ27 | G20: 1693 | H20: 12706 | I20: DANILO | J20: =SUM(EQUIPE!C20,EQUIPE!E20,EQUIPE!G20,EQUIPE!I20,EQUIPE!K20,EQUIPE!M20,EQUIPE!O20) -> 67992.1 | K20: 0 | L20: 1631.45 | M20: =IFERROR(LEFT( IF(INDEX('ETAPA OBRA'!C:C,MATCH($B20,'ETAPA OBRA'!$B:$B,0))="x",'ETAPA OBRA'!C$1&", ","")& IF(INDEX('ETAPA OBRA'!D:D,MATCH($B20,'ETAPA OBRA'!$B:$B,0))="x",'ETAPA OBRA'!D$1&", ","")& IF(INDEX('ETAPA OBRA'!F:F,MATCH($B20,'ETAPA OBRA'!$B:$B,0))="x",'ETAPA OBRA'!F$1&", ","")& IF(INDEX('ETAPA OBRA'!G:G,MATCH($B20,'ETAPA OBRA'!$B:$B,0))="x",'ETAPA OBRA'!G$1&", ","")& IF(INDEX('ETAPA OBRA'!H:H,MATCH($B20,'ETAPA OBRA'!$B:$B,0))="x",'ETAPA OBRA'!H$1&", ","")& IF(INDEX('ETAPA OBRA'!I:I,MATCH($B20,'ETAPA OBRA'!$B:$B,0))="x",'ETAPA OBRA'!I$1&", ","")& IF(INDEX('ETAPA OBRA'!J:J,MATCH($B20,'ETAPA OBRA'!$B:$B,0))="x",'ETAPA OBRA'!J$1&", ","")& IF(INDEX('ETAPA OBRA'!K:K,MATCH($B20,'ETAPA OBRA'!$B:$B,0))="x",'ETAPA OBRA'!K$1&", ","")& IF(INDEX('ETAPA OBRA'!L:L,MATCH($B20,'ETAPA OBRA'!$B:$B,0))="x",'ETAPA OBRA'!L$1&", ","")& IF(INDEX('ETAPA OBRA'!M:M,MATCH($B20,'ETAPA OBRA'!$B:$B,0))="x",'ETAPA OBRA'!M$1&", ","")& IF(INDEX('ETAPA OBRA'!N:N,MATCH($B20,'ETAPA OBRA'!$B:$B,0))="x",'ETAPA OBRA'!N$1&", ","")& IF(INDEX('ETAPA OBRA'!O:O,MATCH($B20,'ETAPA OBRA'!$B:$B,0))="x",'ETAPA OBRA'!O$1&", ","")& IF(INDEX('ETAPA OBRA'!P:P,MATCH($B20,'ETAPA OBRA'!$B:$B,0))="x",'ETAPA OBRA'!P$1&", ","")& IF(INDEX('ETAPA OBRA'!Q:Q,MATCH($B20,'ETAPA OBRA'!$B:$B,0))="x",'ETAPA OBRA'!Q$1&", ","")& IF(INDEX('ETAPA OBRA'!R:R,MATCH($B20,'ETAPA OBRA'!$B:$B,0))="x",'ETAPA OBRA'!R$1&", ","")& IF(INDEX('ETAPA OBRA'!S:S,MATCH($B20,'ETAPA OBRA'!$B:$B,0))="x",'ETAPA OBRA'!S$1&", ","")& IF(INDEX('ETAPA OBRA'!T:T,MATCH($B20,'ETAPA OBRA'!$B:$B,0))="x",'ETAPA OBRA'!T$1&", ","")& IF(INDEX('ETAPA OBRA'!U:U,MATCH($B20,'ETAPA OBRA'!$B:$B,0))="x",'ETAPA OBRA'!U$1&", ",""),LEN( IF(INDEX('ETAPA OBRA'!C:C,MATCH($B20,'ETAPA OBRA'!$B:$B,0))="x",'ETAPA OBRA'!C$1&", ","")& IF(INDEX('ETAPA OBRA'!D:D,MATCH($B20,'ETAPA OBRA'!$B:$B,0))="x",'ETAPA OBRA'!D$1&", ","")& IF(INDEX('ETAPA OBRA'!F:F,MATCH($B20,'ETAPA OBRA'!$B:$B,0))="x",'ETAPA OBRA'!F$1&", ","")& IF(INDEX('ETAPA OBRA'!G:G,MATCH($B20,'ETAPA OBRA'!$B:$B,0))="x",'ETAPA OBRA'!G$1&", ","")& IF(INDEX('ETAPA OBRA'!H:H,MATCH($B20,'ETAPA OBRA'!$B:$B,0))="x",'ETAPA OBRA'!H$1&", ","")& IF(INDEX('ETAPA OBRA'!I:I,MATCH($B20,'ETAPA OBRA'!$B:$B,0))="x",'ETAPA OBRA'!I$1&", ","")& IF(INDEX('ETAPA OBRA'!J:J,MATCH($B20,'ETAPA OBRA'!$B:$B,0))="x",'ETAPA OBRA'!J$1&", ","")& IF(INDEX('ETAPA OBRA'!K:K,MATCH($B20,'ETAPA OBRA'!$B:$B,0))="x",'ETAPA OBRA'!K$1&", ","")& IF(INDEX('ETAPA OBRA'!L:L,MATCH($B20,'ETAPA OBRA'!$B:$B,0))="x",'ETAPA OBRA'!L$1&", ","")& IF(INDEX('ETAPA OBRA'!M:M,MATCH($B20,'ETAPA OBRA'!$B:$B,0))="x",'ETAPA OBRA'!M$1&", ","")& IF(INDEX('ETAPA OBRA'!N:N,MATCH($B20,'ETAPA OBRA'!$B:$B,0))="x",'ETAPA OBRA'!N$1&", ","")& IF(INDEX('ETAPA OBRA'!O:O,MATCH($B20,'ETAPA OBRA'!$B:$B,0))="x",'ETAPA OBRA'!O$1&", ","")& IF(INDEX('ETAPA OBRA'!P:P,MATCH($B20,'ETAPA OBRA'!$B:$B,0))="x",'ETAPA OBRA'!P$1&", ","")& IF(INDEX('ETAPA OBRA'!Q:Q,MATCH($B20,'ETAPA OBRA'!$B:$B,0))="x",'ETAPA OBRA'!Q$1&", ","")& IF(INDEX('ETAPA OBRA'!R:R,MATCH($B20,'ETAPA OBRA'!$B:$B,0))="x",'ETAPA OBRA'!R$1&", ","")& IF(INDEX('ETAPA OBRA'!S:S,MATCH($B20,'ETAPA OBRA'!$B:$B,0))="x",'ETAPA OBRA'!S$1&", ","")& IF(INDEX('ETAPA OBRA'!T:T,MATCH($B20,'ETAPA OBRA'!$B:$B,0))="x",'ETAPA OBRA'!T$1&", ","")& IF(INDEX('ETAPA OBRA'!U:U,MATCH($B20,'ETAPA OBRA'!$B:$B,0))="x",'ETAPA OBRA'!U$1&", ","") )-2),"") -> Finalizado | N20: =IF(M20="","Não iniciada", IF(ISNUMBER(FIND("Cancelada",M20)),"Cancelada", IF(ISNUMBER(FIND("Paralisada",M20)),"Paralisada", IF(ISNUMBER(FIND("Finalizado",M20)),"Finalizado", "Em andamento")))) -> Finalizado | O20: 96659.33 | P20: =SUM($J20:$L20) -> 69623.55 | Q20: =O20-P20 -> 27035.78 | R20: =IF(O20=0,0,Q20/O20) -> 0.27970171 | S20: =IF(R20>=0.2,"✅ OK - Fechar Parceiro","⚠️ Ajustar Custos (<20%)") -> ✅ OK - Fechar Parceiro | T20: =Cronograma[[#This Row],[STATUS]] -> ✅ CONCLUÍDO
A21: BR88343-R | B21: =IF(A21<>"","contel-"&TEXT(COUNTA($A$2:A21),"00"),"") -> contel-20 | C21: SBA | D21: GOIÂNIA | E21: GO | F21: https://maps.app.goo.gl/P8HNKAFEt5Vyn9ov6 | G21: 1699 | H21: 12890 | I21: PEDRO | J21: =SUM(EQUIPE!C21,EQUIPE!E21,EQUIPE!G21,EQUIPE!I21,EQUIPE!K21,EQUIPE!M21,EQUIPE!O21) -> 0 | K21: 0 | L21: 22969.73 | M21: =IFERROR(LEFT( IF(INDEX('ETAPA OBRA'!C:C,MATCH($B21,'ETAPA OBRA'!$B:$B,0))="x",'ETAPA OBRA'!C$1&", ","")& IF(INDEX('ETAPA OBRA'!D:D,MATCH($B21,'ETAPA OBRA'!$B:$B,0))="x",'ETAPA OBRA'!D$1&", ","")& IF(INDEX('ETAPA OBRA'!F:F,MATCH($B21,'ETAPA OBRA'!$B:$B,0))="x",'ETAPA OBRA'!F$1&", ","")& IF(INDEX('ETAPA OBRA'!G:G,MATCH($B21,'ETAPA OBRA'!$B:$B,0))="x",'ETAPA OBRA'!G$1&", ","")& IF(INDEX('ETAPA OBRA'!H:H,MATCH($B21,'ETAPA OBRA'!$B:$B,0))="x",'ETAPA OBRA'!H$1&", ","")& IF(INDEX('ETAPA OBRA'!I:I,MATCH($B21,'ETAPA OBRA'!$B:$B,0))="x",'ETAPA OBRA'!I$1&", ","")& IF(INDEX('ETAPA OBRA'!J:J,MATCH($B21,'ETAPA OBRA'!$B:$B,0))="x",'ETAPA OBRA'!J$1&", ","")& IF(INDEX('ETAPA OBRA'!K:K,MATCH($B21,'ETAPA OBRA'!$B:$B,0))="x",'ETAPA OBRA'!K$1&", ","")& IF(INDEX('ETAPA OBRA'!L:L,MATCH($B21,'ETAPA OBRA'!$B:$B,0))="x",'ETAPA OBRA'!L$1&", ","")& IF(INDEX('ETAPA OBRA'!M:M,MATCH($B21,'ETAPA OBRA'!$B:$B,0))="x",'ETAPA OBRA'!M$1&", ","")& IF(INDEX('ETAPA OBRA'!N:N,MATCH($B21,'ETAPA OBRA'!$B:$B,0))="x",'ETAPA OBRA'!N$1&", ","")& IF(INDEX('ETAPA OBRA'!O:O,MATCH($B21,'ETAPA OBRA'!$B:$B,0))="x",'ETAPA OBRA'!O$1&", ","")& IF(INDEX('ETAPA OBRA'!P:P,MATCH($B21,'ETAPA OBRA'!$B:$B,0))="x",'ETAPA OBRA'!P$1&", ","")& IF(INDEX('ETAPA OBRA'!Q:Q,MATCH($B21,'ETAPA OBRA'!$B:$B,0))="x",'ETAPA OBRA'!Q$1&", ","")& IF(INDEX('ETAPA OBRA'!R:R,MATCH($B21,'ETAPA OBRA'!$B:$B,0))="x",'ETAPA OBRA'!R$1&", ","")& IF(INDEX('ETAPA OBRA'!S:S,MATCH($B21,'ETAPA OBRA'!$B:$B,0))="x",'ETAPA OBRA'!S$1&", ","")& IF(INDEX('ETAPA OBRA'!T:T,MATCH($B21,'ETAPA OBRA'!$B:$B,0))="x",'ETAPA OBRA'!T$1&", ","")& IF(INDEX('ETAPA OBRA'!U:U,MATCH($B21,'ETAPA OBRA'!$B:$B,0))="x",'ETAPA OBRA'!U$1&", ",""),LEN( IF(INDEX('ETAPA OBRA'!C:C,MATCH($B21,'ETAPA OBRA'!$B:$B,0))="x",'ETAPA OBRA'!C$1&", ","")& IF(INDEX('ETAPA OBRA'!D:D,MATCH($B21,'ETAPA OBRA'!$B:$B,0))="x",'ETAPA OBRA'!D$1&", ","")& IF(INDEX('ETAPA OBRA'!F:F,MATCH($B21,'ETAPA OBRA'!$B:$B,0))="x",'ETAPA OBRA'!F$1&", ","")& IF(INDEX('ETAPA OBRA'!G:G,MATCH($B21,'ETAPA OBRA'!$B:$B,0))="x",'ETAPA OBRA'!G$1&", ","")& IF(INDEX('ETAPA OBRA'!H:H,MATCH($B21,'ETAPA OBRA'!$B:$B,0))="x",'ETAPA OBRA'!H$1&", ","")& IF(INDEX('ETAPA OBRA'!I:I,MATCH($B21,'ETAPA OBRA'!$B:$B,0))="x",'ETAPA OBRA'!I$1&", ","")& IF(INDEX('ETAPA OBRA'!J:J,MATCH($B21,'ETAPA OBRA'!$B:$B,0))="x",'ETAPA OBRA'!J$1&", ","")& IF(INDEX('ETAPA OBRA'!K:K,MATCH($B21,'ETAPA OBRA'!$B:$B,0))="x",'ETAPA OBRA'!K$1&", ","")& IF(INDEX('ETAPA OBRA'!L:L,MATCH($B21,'ETAPA OBRA'!$B:$B,0))="x",'ETAPA OBRA'!L$1&", ","")& IF(INDEX('ETAPA OBRA'!M:M,MATCH($B21,'ETAPA OBRA'!$B:$B,0))="x",'ETAPA OBRA'!M$1&", ","")& IF(INDEX('ETAPA OBRA'!N:N,MATCH($B21,'ETAPA OBRA'!$B:$B,0))="x",'ETAPA OBRA'!N$1&", ","")& IF(INDEX('ETAPA OBRA'!O:O,MATCH($B21,'ETAPA OBRA'!$B:$B,0))="x",'ETAPA OBRA'!O$1&", ","")& IF(INDEX('ETAPA OBRA'!P:P,MATCH($B21,'ETAPA OBRA'!$B:$B,0))="x",'ETAPA OBRA'!P$1&", ","")& IF(INDEX('ETAPA OBRA'!Q:Q,MATCH($B21,'ETAPA OBRA'!$B:$B,0))="x",'ETAPA OBRA'!Q$1&", ","")& IF(INDEX('ETAPA OBRA'!R:R,MATCH($B21,'ETAPA OBRA'!$B:$B,0))="x",'ETAPA OBRA'!R$1&", ","")& IF(INDEX('ETAPA OBRA'!S:S,MATCH($B21,'ETAPA OBRA'!$B:$B,0))="x",'ETAPA OBRA'!S$1&", ","")& IF(INDEX('ETAPA OBRA'!T:T,MATCH($B21,'ETAPA OBRA'!$B:$B,0))="x",'ETAPA OBRA'!T$1&", ","")& IF(INDEX('ETAPA OBRA'!U:U,MATCH($B21,'ETAPA OBRA'!$B:$B,0))="x",'ETAPA OBRA'!U$1&", ","") )-2),"") -> Finalizado | N21: =IF(M21="","Não iniciada", IF(ISNUMBER(FIND("Cancelada",M21)),"Cancelada", IF(ISNUMBER(FIND("Paralisada",M21)),"Paralisada", IF(ISNUMBER(FIND("Finalizado",M21)),"Finalizado", "Em andamento")))) -> Finalizado | O21: 31000 | P21: =SUM($J21:$L21) -> 22969.73 | Q21: =O21-P21 -> 8030.27 | R21: =IF(O21=0,0,Q21/O21) -> 0.25904097 | S21: =IF(R21>=0.2,"✅ OK - Fechar Parceiro","⚠️ Ajustar Custos (<20%)") -> ✅ OK - Fechar Parceiro | T21: =Cronograma[[#This Row],[STATUS]] -> ✅ CONCLUÍDO
A22: SCP-ALY-001 | B22: =IF(A22<>"","contel-"&TEXT(COUNTA($A$2:A22),"00"),"") -> contel-21 | C22: HLB | D22: AGROLÂNDIA | E22: SC | F22: https://maps.app.goo.gl/NaUq9UiMxWyawAK88 | G22: 1703 | H22: 15333 | I22: DANILO | J22: =SUM(EQUIPE!C22,EQUIPE!E22,EQUIPE!G22,EQUIPE!I22,EQUIPE!K22,EQUIPE!M22,EQUIPE!O22) -> 68500 | K22: 0 | L22: 0 | M22: =IFERROR(LEFT( IF(INDEX('ETAPA OBRA'!C:C,MATCH($B22,'ETAPA OBRA'!$B:$B,0))="x",'ETAPA OBRA'!C$1&", ","")& IF(INDEX('ETAPA OBRA'!D:D,MATCH($B22,'ETAPA OBRA'!$B:$B,0))="x",'ETAPA OBRA'!D$1&", ","")& IF(INDEX('ETAPA OBRA'!F:F,MATCH($B22,'ETAPA OBRA'!$B:$B,0))="x",'ETAPA OBRA'!F$1&", ","")& IF(INDEX('ETAPA OBRA'!G:G,MATCH($B22,'ETAPA OBRA'!$B:$B,0))="x",'ETAPA OBRA'!G$1&", ","")& IF(INDEX('ETAPA OBRA'!H:H,MATCH($B22,'ETAPA OBRA'!$B:$B,0))="x",'ETAPA OBRA'!H$1&", ","")& IF(INDEX('ETAPA OBRA'!I:I,MATCH($B22,'ETAPA OBRA'!$B:$B,0))="x",'ETAPA OBRA'!I$1&", ","")& IF(INDEX('ETAPA OBRA'!J:J,MATCH($B22,'ETAPA OBRA'!$B:$B,0))="x",'ETAPA OBRA'!J$1&", ","")& IF(INDEX('ETAPA OBRA'!K:K,MATCH($B22,'ETAPA OBRA'!$B:$B,0))="x",'ETAPA OBRA'!K$1&", ","")& IF(INDEX('ETAPA OBRA'!L:L,MATCH($B22,'ETAPA OBRA'!$B:$B,0))="x",'ETAPA OBRA'!L$1&", ","")& IF(INDEX('ETAPA OBRA'!M:M,MATCH($B22,'ETAPA OBRA'!$B:$B,0))="x",'ETAPA OBRA'!M$1&", ","")& IF(INDEX('ETAPA OBRA'!N:N,MATCH($B22,'ETAPA OBRA'!$B:$B,0))="x",'ETAPA OBRA'!N$1&", ","")& IF(INDEX('ETAPA OBRA'!O:O,MATCH($B22,'ETAPA OBRA'!$B:$B,0))="x",'ETAPA OBRA'!O$1&", ","")& IF(INDEX('ETAPA OBRA'!P:P,MATCH($B22,'ETAPA OBRA'!$B:$B,0))="x",'ETAPA OBRA'!P$1&", ","")& IF(INDEX('ETAPA OBRA'!Q:Q,MATCH($B22,'ETAPA OBRA'!$B:$B,0))="x",'ETAPA OBRA'!Q$1&", ","")& IF(INDEX('ETAPA OBRA'!R:R,MATCH($B22,'ETAPA OBRA'!$B:$B,0))="x",'ETAPA OBRA'!R$1&", ","")& IF(INDEX('ETAPA OBRA'!S:S,MATCH($B22,'ETAPA OBRA'!$B:$B,0))="x",'ETAPA OBRA'!S$1&", ","")& IF(INDEX('ETAPA OBRA'!T:T,MATCH($B22,'ETAPA OBRA'!$B:$B,0))="x",'ETAPA OBRA'!T$1&", ","")& IF(INDEX('ETAPA OBRA'!U:U,MATCH($B22,'ETAPA OBRA'!$B:$B,0))="x",'ETAPA OBRA'!U$1&", ",""),LEN( IF(INDEX('ETAPA OBRA'!C:C,MATCH($B22,'ETAPA OBRA'!$B:$B,0))="x",'ETAPA OBRA'!C$1&", ","")& IF(INDEX('ETAPA OBRA'!D:D,MATCH($B22,'ETAPA OBRA'!$B:$B,0))="x",'ETAPA OBRA'!D$1&", ","")& IF(INDEX('ETAPA OBRA'!F:F,MATCH($B22,'ETAPA OBRA'!$B:$B,0))="x",'ETAPA OBRA'!F$1&", ","")& IF(INDEX('ETAPA OBRA'!G:G,MATCH($B22,'ETAPA OBRA'!$B:$B,0))="x",'ETAPA OBRA'!G$1&", ","")& IF(INDEX('ETAPA OBRA'!H:H,MATCH($B22,'ETAPA OBRA'!$B:$B,0))="x",'ETAPA OBRA'!H$1&", ","")& IF(INDEX('ETAPA OBRA'!I:I,MATCH($B22,'ETAPA OBRA'!$B:$B,0))="x",'ETAPA OBRA'!I$1&", ","")& IF(INDEX('ETAPA OBRA'!J:J,MATCH($B22,'ETAPA OBRA'!$B:$B,0))="x",'ETAPA OBRA'!J$1&", ","")& IF(INDEX('ETAPA OBRA'!K:K,MATCH($B22,'ETAPA OBRA'!$B:$B,0))="x",'ETAPA OBRA'!K$1&", ","")& IF(INDEX('ETAPA OBRA'!L:L,MATCH($B22,'ETAPA OBRA'!$B:$B,0))="x",'ETAPA OBRA'!L$1&", ","")& IF(INDEX('ETAPA OBRA'!M:M,MATCH($B22,'ETAPA OBRA'!$B:$B,0))="x",'ETAPA OBRA'!M$1&", ","")& IF(INDEX('ETAPA OBRA'!N:N,MATCH($B22,'ETAPA OBRA'!$B:$B,0))="x",'ETAPA OBRA'!N$1&", ","")& IF(INDEX('ETAPA OBRA'!O:O,MATCH($B22,'ETAPA OBRA'!$B:$B,0))="x",'ETAPA OBRA'!O$1&", ","")& IF(INDEX('ETAPA OBRA'!P:P,MATCH($B22,'ETAPA OBRA'!$B:$B,0))="x",'ETAPA OBRA'!P$1&", ","")& IF(INDEX('ETAPA OBRA'!Q:Q,MATCH($B22,'ETAPA OBRA'!$B:$B,0))="x",'ETAPA OBRA'!Q$1&", ","")& IF(INDEX('ETAPA OBRA'!R:R,MATCH($B22,'ETAPA OBRA'!$B:$B,0))="x",'ETAPA OBRA'!R$1&", ","")& IF(INDEX('ETAPA OBRA'!S:S,MATCH($B22,'ETAPA OBRA'!$B:$B,0))="x",'ETAPA OBRA'!S$1&", ","")& IF(INDEX('ETAPA OBRA'!T:T,MATCH($B22,'ETAPA OBRA'!$B:$B,0))="x",'ETAPA OBRA'!T$1&", ","")& IF(INDEX('ETAPA OBRA'!U:U,MATCH($B22,'ETAPA OBRA'!$B:$B,0))="x",'ETAPA OBRA'!U$1&", ","") )-2),"") -> Finalizado | N22: =IF(M22="","Não iniciada", IF(ISNUMBER(FIND("Cancelada",M22)),"Cancelada", IF(ISNUMBER(FIND("Paralisada",M22)),"Paralisada", IF(ISNUMBER(FIND("Finalizado",M22)),"Finalizado", "Em andamento")))) -> Finalizado | O22: 124301.29 | P22: =SUM($J22:$L22) -> 68500 | Q22: =O22-P22 -> 55801.29 | R22: =IF(O22=0,0,Q22/O22) -> 0.44891964 | S22: =IF(R22>=0.2,"✅ OK - Fechar Parceiro","⚠️ Ajustar Custos (<20%)") -> ✅ OK - Fechar Parceiro | T22: =Cronograma[[#This Row],[STATUS]] -> ✅ CONCLUÍDO
A23: BR56770-A | B23: =IF(A23<>"","contel-"&TEXT(COUNTA($A$2:A23),"00"),"") -> contel-22 | C23: SBA | D23: MARIPÁ | E23: PR | F23: https://maps.app.goo.gl/MZEmbX8dZ75Y1n2FA | G23: 1704 | H23: 15339 | I23: HENRIQUE | J23: =SUM(EQUIPE!C23,EQUIPE!E23,EQUIPE!G23,EQUIPE!I23,EQUIPE!K23,EQUIPE!M23,EQUIPE!O23) -> 4700 | K23: 0 | L23: 976.47 | M23: =IFERROR(LEFT( IF(INDEX('ETAPA OBRA'!C:C,MATCH($B23,'ETAPA OBRA'!$B:$B,0))="x",'ETAPA OBRA'!C$1&", ","")& IF(INDEX('ETAPA OBRA'!D:D,MATCH($B23,'ETAPA OBRA'!$B:$B,0))="x",'ETAPA OBRA'!D$1&", ","")& IF(INDEX('ETAPA OBRA'!F:F,MATCH($B23,'ETAPA OBRA'!$B:$B,0))="x",'ETAPA OBRA'!F$1&", ","")& IF(INDEX('ETAPA OBRA'!G:G,MATCH($B23,'ETAPA OBRA'!$B:$B,0))="x",'ETAPA OBRA'!G$1&", ","")& IF(INDEX('ETAPA OBRA'!H:H,MATCH($B23,'ETAPA OBRA'!$B:$B,0))="x",'ETAPA OBRA'!H$1&", ","")& IF(INDEX('ETAPA OBRA'!I:I,MATCH($B23,'ETAPA OBRA'!$B:$B,0))="x",'ETAPA OBRA'!I$1&", ","")& IF(INDEX('ETAPA OBRA'!J:J,MATCH($B23,'ETAPA OBRA'!$B:$B,0))="x",'ETAPA OBRA'!J$1&", ","")& IF(INDEX('ETAPA OBRA'!K:K,MATCH($B23,'ETAPA OBRA'!$B:$B,0))="x",'ETAPA OBRA'!K$1&", ","")& IF(INDEX('ETAPA OBRA'!L:L,MATCH($B23,'ETAPA OBRA'!$B:$B,0))="x",'ETAPA OBRA'!L$1&", ","")& IF(INDEX('ETAPA OBRA'!M:M,MATCH($B23,'ETAPA OBRA'!$B:$B,0))="x",'ETAPA OBRA'!M$1&", ","")& IF(INDEX('ETAPA OBRA'!N:N,MATCH($B23,'ETAPA OBRA'!$B:$B,0))="x",'ETAPA OBRA'!N$1&", ","")& IF(INDEX('ETAPA OBRA'!O:O,MATCH($B23,'ETAPA OBRA'!$B:$B,0))="x",'ETAPA OBRA'!O$1&", ","")& IF(INDEX('ETAPA OBRA'!P:P,MATCH($B23,'ETAPA OBRA'!$B:$B,0))="x",'ETAPA OBRA'!P$1&", ","")& IF(INDEX('ETAPA OBRA'!Q:Q,MATCH($B23,'ETAPA OBRA'!$B:$B,0))="x",'ETAPA OBRA'!Q$1&", ","")& IF(INDEX('ETAPA OBRA'!R:R,MATCH($B23,'ETAPA OBRA'!$B:$B,0))="x",'ETAPA OBRA'!R$1&", ","")& IF(INDEX('ETAPA OBRA'!S:S,MATCH($B23,'ETAPA OBRA'!$B:$B,0))="x",'ETAPA OBRA'!S$1&", ","")& IF(INDEX('ETAPA OBRA'!T:T,MATCH($B23,'ETAPA OBRA'!$B:$B,0))="x",'ETAPA OBRA'!T$1&", ","")& IF(INDEX('ETAPA OBRA'!U:U,MATCH($B23,'ETAPA OBRA'!$B:$B,0))="x",'ETAPA OBRA'!U$1&", ",""),LEN( IF(INDEX('ETAPA OBRA'!C:C,MATCH($B23,'ETAPA OBRA'!$B:$B,0))="x",'ETAPA OBRA'!C$1&", ","")& IF(INDEX('ETAPA OBRA'!D:D,MATCH($B23,'ETAPA OBRA'!$B:$B,0))="x",'ETAPA OBRA'!D$1&", ","")& IF(INDEX('ETAPA OBRA'!F:F,MATCH($B23,'ETAPA OBRA'!$B:$B,0))="x",'ETAPA OBRA'!F$1&", ","")& IF(INDEX('ETAPA OBRA'!G:G,MATCH($B23,'ETAPA OBRA'!$B:$B,0))="x",'ETAPA OBRA'!G$1&", ","")& IF(INDEX('ETAPA OBRA'!H:H,MATCH($B23,'ETAPA OBRA'!$B:$B,0))="x",'ETAPA OBRA'!H$1&", ","")& IF(INDEX('ETAPA OBRA'!I:I,MATCH($B23,'ETAPA OBRA'!$B:$B,0))="x",'ETAPA OBRA'!I$1&", ","")& IF(INDEX('ETAPA OBRA'!J:J,MATCH($B23,'ETAPA OBRA'!$B:$B,0))="x",'ETAPA OBRA'!J$1&", ","")& IF(INDEX('ETAPA OBRA'!K:K,MATCH($B23,'ETAPA OBRA'!$B:$B,0))="x",'ETAPA OBRA'!K$1&", ","")& IF(INDEX('ETAPA OBRA'!L:L,MATCH($B23,'ETAPA OBRA'!$B:$B,0))="x",'ETAPA OBRA'!L$1&", ","")& IF(INDEX('ETAPA OBRA'!M:M,MATCH($B23,'ETAPA OBRA'!$B:$B,0))="x",'ETAPA OBRA'!M$1&", ","")& IF(INDEX('ETAPA OBRA'!N:N,MATCH($B23,'ETAPA OBRA'!$B:$B,0))="x",'ETAPA OBRA'!N$1&", ","")& IF(INDEX('ETAPA OBRA'!O:O,MATCH($B23,'ETAPA OBRA'!$B:$B,0))="x",'ETAPA OBRA'!O$1&", ","")& IF(INDEX('ETAPA OBRA'!P:P,MATCH($B23,'ETAPA OBRA'!$B:$B,0))="x",'ETAPA OBRA'!P$1&", ","")& IF(INDEX('ETAPA OBRA'!Q:Q,MATCH($B23,'ETAPA OBRA'!$B:$B,0))="x",'ETAPA OBRA'!Q$1&", ","")& IF(INDEX('ETAPA OBRA'!R:R,MATCH($B23,'ETAPA OBRA'!$B:$B,0))="x",'ETAPA OBRA'!R$1&", ","")& IF(INDEX('ETAPA OBRA'!S:S,MATCH($B23,'ETAPA OBRA'!$B:$B,0))="x",'ETAPA OBRA'!S$1&", ","")& IF(INDEX('ETAPA OBRA'!T:T,MATCH($B23,'ETAPA OBRA'!$B:$B,0))="x",'ETAPA OBRA'!T$1&", ","")& IF(INDEX('ETAPA OBRA'!U:U,MATCH($B23,'ETAPA OBRA'!$B:$B,0))="x",'ETAPA OBRA'!U$1&", ","") )-2),"") -> Finalizado | N23: =IF(M23="","Não iniciada", IF(ISNUMBER(FIND("Cancelada",M23)),"Cancelada", IF(ISNUMBER(FIND("Paralisada",M23)),"Paralisada", IF(ISNUMBER(FIND("Finalizado",M23)),"Finalizado", "Em andamento")))) -> Finalizado | O23: 26179.15 | P23: =SUM($J23:$L23) -> 5676.47 | Q23: =O23-P23 -> 20502.68 | R23: =IF(O23=0,0,Q23/O23) -> 0.78316828 | S23: =IF(R23>=0.2,"✅ OK - Fechar Parceiro","⚠️ Ajustar Custos (<20%)") -> ✅ OK - Fechar Parceiro | T23: =Cronograma[[#This Row],[STATUS]] -> ✅ CONCLUÍDO
A24: BR67246-A | B24: =IF(A24<>"","contel-"&TEXT(COUNTA($A$2:A24),"00"),"") -> contel-23 | C24: SBA | D24: SANTO ANTONIO DE JESUS | E24: BA | F24: https://maps.app.goo.gl/oNpjFDZUnzw5kCBu5 | G24: 1705 | H24: 15375 | I24: HENRIQUE | J24: =SUM(EQUIPE!C24,EQUIPE!E24,EQUIPE!G24,EQUIPE!I24,EQUIPE!K24,EQUIPE!M24,EQUIPE!O24) -> 7000 | K24: 1887.66 | L24: 1242.55 | M24: =IFERROR(LEFT( IF(INDEX('ETAPA OBRA'!C:C,MATCH($B24,'ETAPA OBRA'!$B:$B,0))="x",'ETAPA OBRA'!C$1&", ","")& IF(INDEX('ETAPA OBRA'!D:D,MATCH($B24,'ETAPA OBRA'!$B:$B,0))="x",'ETAPA OBRA'!D$1&", ","")& IF(INDEX('ETAPA OBRA'!F:F,MATCH($B24,'ETAPA OBRA'!$B:$B,0))="x",'ETAPA OBRA'!F$1&", ","")& IF(INDEX('ETAPA OBRA'!G:G,MATCH($B24,'ETAPA OBRA'!$B:$B,0))="x",'ETAPA OBRA'!G$1&", ","")& IF(INDEX('ETAPA OBRA'!H:H,MATCH($B24,'ETAPA OBRA'!$B:$B,0))="x",'ETAPA OBRA'!H$1&", ","")& IF(INDEX('ETAPA OBRA'!I:I,MATCH($B24,'ETAPA OBRA'!$B:$B,0))="x",'ETAPA OBRA'!I$1&", ","")& IF(INDEX('ETAPA OBRA'!J:J,MATCH($B24,'ETAPA OBRA'!$B:$B,0))="x",'ETAPA OBRA'!J$1&", ","")& IF(INDEX('ETAPA OBRA'!K:K,MATCH($B24,'ETAPA OBRA'!$B:$B,0))="x",'ETAPA OBRA'!K$1&", ","")& IF(INDEX('ETAPA OBRA'!L:L,MATCH($B24,'ETAPA OBRA'!$B:$B,0))="x",'ETAPA OBRA'!L$1&", ","")& IF(INDEX('ETAPA OBRA'!M:M,MATCH($B24,'ETAPA OBRA'!$B:$B,0))="x",'ETAPA OBRA'!M$1&", ","")& IF(INDEX('ETAPA OBRA'!N:N,MATCH($B24,'ETAPA OBRA'!$B:$B,0))="x",'ETAPA OBRA'!N$1&", ","")& IF(INDEX('ETAPA OBRA'!O:O,MATCH($B24,'ETAPA OBRA'!$B:$B,0))="x",'ETAPA OBRA'!O$1&", ","")& IF(INDEX('ETAPA OBRA'!P:P,MATCH($B24,'ETAPA OBRA'!$B:$B,0))="x",'ETAPA OBRA'!P$1&", ","")& IF(INDEX('ETAPA OBRA'!Q:Q,MATCH($B24,'ETAPA OBRA'!$B:$B,0))="x",'ETAPA OBRA'!Q$1&", ","")& IF(INDEX('ETAPA OBRA'!R:R,MATCH($B24,'ETAPA OBRA'!$B:$B,0))="x",'ETAPA OBRA'!R$1&", ","")& IF(INDEX('ETAPA OBRA'!S:S,MATCH($B24,'ETAPA OBRA'!$B:$B,0))="x",'ETAPA OBRA'!S$1&", ","")& IF(INDEX('ETAPA OBRA'!T:T,MATCH($B24,'ETAPA OBRA'!$B:$B,0))="x",'ETAPA OBRA'!T$1&", ","")& IF(INDEX('ETAPA OBRA'!U:U,MATCH($B24,'ETAPA OBRA'!$B:$B,0))="x",'ETAPA OBRA'!U$1&", ",""),LEN( IF(INDEX('ETAPA OBRA'!C:C,MATCH($B24,'ETAPA OBRA'!$B:$B,0))="x",'ETAPA OBRA'!C$1&", ","")& IF(INDEX('ETAPA OBRA'!D:D,MATCH($B24,'ETAPA OBRA'!$B:$B,0))="x",'ETAPA OBRA'!D$1&", ","")& IF(INDEX('ETAPA OBRA'!F:F,MATCH($B24,'ETAPA OBRA'!$B:$B,0))="x",'ETAPA OBRA'!F$1&", ","")& IF(INDEX('ETAPA OBRA'!G:G,MATCH($B24,'ETAPA OBRA'!$B:$B,0))="x",'ETAPA OBRA'!G$1&", ","")& IF(INDEX('ETAPA OBRA'!H:H,MATCH($B24,'ETAPA OBRA'!$B:$B,0))="x",'ETAPA OBRA'!H$1&", ","")& IF(INDEX('ETAPA OBRA'!I:I,MATCH($B24,'ETAPA OBRA'!$B:$B,0))="x",'ETAPA OBRA'!I$1&", ","")& IF(INDEX('ETAPA OBRA'!J:J,MATCH($B24,'ETAPA OBRA'!$B:$B,0))="x",'ETAPA OBRA'!J$1&", ","")& IF(INDEX('ETAPA OBRA'!K:K,MATCH($B24,'ETAPA OBRA'!$B:$B,0))="x",'ETAPA OBRA'!K$1&", ","")& IF(INDEX('ETAPA OBRA'!L:L,MATCH($B24,'ETAPA OBRA'!$B:$B,0))="x",'ETAPA OBRA'!L$1&", ","")& IF(INDEX('ETAPA OBRA'!M:M,MATCH($B24,'ETAPA OBRA'!$B:$B,0))="x",'ETAPA OBRA'!M$1&", ","")& IF(INDEX('ETAPA OBRA'!N:N,MATCH($B24,'ETAPA OBRA'!$B:$B,0))="x",'ETAPA OBRA'!N$1&", ","")& IF(INDEX('ETAPA OBRA'!O:O,MATCH($B24,'ETAPA OBRA'!$B:$B,0))="x",'ETAPA OBRA'!O$1&", ","")& IF(INDEX('ETAPA OBRA'!P:P,MATCH($B24,'ETAPA OBRA'!$B:$B,0))="x",'ETAPA OBRA'!P$1&", ","")& IF(INDEX('ETAPA OBRA'!Q:Q,MATCH($B24,'ETAPA OBRA'!$B:$B,0))="x",'ETAPA OBRA'!Q$1&", ","")& IF(INDEX('ETAPA OBRA'!R:R,MATCH($B24,'ETAPA OBRA'!$B:$B,0))="x",'ETAPA OBRA'!R$1&", ","")& IF(INDEX('ETAPA OBRA'!S:S,MATCH($B24,'ETAPA OBRA'!$B:$B,0))="x",'ETAPA OBRA'!S$1&", ","")& IF(INDEX('ETAPA OBRA'!T:T,MATCH($B24,'ETAPA OBRA'!$B:$B,0))="x",'ETAPA OBRA'!T$1&", ","")& IF(INDEX('ETAPA OBRA'!U:U,MATCH($B24,'ETAPA OBRA'!$B:$B,0))="x",'ETAPA OBRA'!U$1&", ","") )-2),"") -> Finalizado | N24: =IF(M24="","Não iniciada", IF(ISNUMBER(FIND("Cancelada",M24)),"Cancelada", IF(ISNUMBER(FIND("Paralisada",M24)),"Paralisada", IF(ISNUMBER(FIND("Finalizado",M24)),"Finalizado", "Em andamento")))) -> Finalizado | O24: 15777 | P24: =SUM($J24:$L24) -> 10130.21 | Q24: =O24-P24 -> 5646.79 | R24: =IF(O24=0,0,Q24/O24) -> 0.35791278 | S24: =IF(R24>=0.2,"✅ OK - Fechar Parceiro","⚠️ Ajustar Custos (<20%)") -> ✅ OK - Fechar Parceiro | T24: =Cronograma[[#This Row],[STATUS]] -> ✅ CONCLUÍDO
A25: BR67084-R | B25: =IF(A25<>"","contel-"&TEXT(COUNTA($A$2:A25),"00"),"") -> contel-24 | C25: SBA | D25: BRASILIA | E25: DF | F25: https://maps.app.goo.gl/VUg623hsokWvzGNL7 | G25: 1707 | H25: 15839 | I25: PEDRO | J25: =SUM(EQUIPE!C25,EQUIPE!E25,EQUIPE!G25,EQUIPE!I25,EQUIPE!K25,EQUIPE!M25,EQUIPE!O25) -> 6000 | K25: 5882.71 | L25: 1060.22 | M25: =IFERROR(LEFT( IF(INDEX('ETAPA OBRA'!C:C,MATCH($B25,'ETAPA OBRA'!$B:$B,0))="x",'ETAPA OBRA'!C$1&", ","")& IF(INDEX('ETAPA OBRA'!D:D,MATCH($B25,'ETAPA OBRA'!$B:$B,0))="x",'ETAPA OBRA'!D$1&", ","")& IF(INDEX('ETAPA OBRA'!F:F,MATCH($B25,'ETAPA OBRA'!$B:$B,0))="x",'ETAPA OBRA'!F$1&", ","")& IF(INDEX('ETAPA OBRA'!G:G,MATCH($B25,'ETAPA OBRA'!$B:$B,0))="x",'ETAPA OBRA'!G$1&", ","")& IF(INDEX('ETAPA OBRA'!H:H,MATCH($B25,'ETAPA OBRA'!$B:$B,0))="x",'ETAPA OBRA'!H$1&", ","")& IF(INDEX('ETAPA OBRA'!I:I,MATCH($B25,'ETAPA OBRA'!$B:$B,0))="x",'ETAPA OBRA'!I$1&", ","")& IF(INDEX('ETAPA OBRA'!J:J,MATCH($B25,'ETAPA OBRA'!$B:$B,0))="x",'ETAPA OBRA'!J$1&", ","")& IF(INDEX('ETAPA OBRA'!K:K,MATCH($B25,'ETAPA OBRA'!$B:$B,0))="x",'ETAPA OBRA'!K$1&", ","")& IF(INDEX('ETAPA OBRA'!L:L,MATCH($B25,'ETAPA OBRA'!$B:$B,0))="x",'ETAPA OBRA'!L$1&", ","")& IF(INDEX('ETAPA OBRA'!M:M,MATCH($B25,'ETAPA OBRA'!$B:$B,0))="x",'ETAPA OBRA'!M$1&", ","")& IF(INDEX('ETAPA OBRA'!N:N,MATCH($B25,'ETAPA OBRA'!$B:$B,0))="x",'ETAPA OBRA'!N$1&", ","")& IF(INDEX('ETAPA OBRA'!O:O,MATCH($B25,'ETAPA OBRA'!$B:$B,0))="x",'ETAPA OBRA'!O$1&", ","")& IF(INDEX('ETAPA OBRA'!P:P,MATCH($B25,'ETAPA OBRA'!$B:$B,0))="x",'ETAPA OBRA'!P$1&", ","")& IF(INDEX('ETAPA OBRA'!Q:Q,MATCH($B25,'ETAPA OBRA'!$B:$B,0))="x",'ETAPA OBRA'!Q$1&", ","")& IF(INDEX('ETAPA OBRA'!R:R,MATCH($B25,'ETAPA OBRA'!$B:$B,0))="x",'ETAPA OBRA'!R$1&", ","")& IF(INDEX('ETAPA OBRA'!S:S,MATCH($B25,'ETAPA OBRA'!$B:$B,0))="x",'ETAPA OBRA'!S$1&", ","")& IF(INDEX('ETAPA OBRA'!T:T,MATCH($B25,'ETAPA OBRA'!$B:$B,0))="x",'ETAPA OBRA'!T$1&", ","")& IF(INDEX('ETAPA OBRA'!U:U,MATCH($B25,'ETAPA OBRA'!$B:$B,0))="x",'ETAPA OBRA'!U$1&", ",""),LEN( IF(INDEX('ETAPA OBRA'!C:C,MATCH($B25,'ETAPA OBRA'!$B:$B,0))="x",'ETAPA OBRA'!C$1&", ","")& IF(INDEX('ETAPA OBRA'!D:D,MATCH($B25,'ETAPA OBRA'!$B:$B,0))="x",'ETAPA OBRA'!D$1&", ","")& IF(INDEX('ETAPA OBRA'!F:F,MATCH($B25,'ETAPA OBRA'!$B:$B,0))="x",'ETAPA OBRA'!F$1&", ","")& IF(INDEX('ETAPA OBRA'!G:G,MATCH($B25,'ETAPA OBRA'!$B:$B,0))="x",'ETAPA OBRA'!G$1&", ","")& IF(INDEX('ETAPA OBRA'!H:H,MATCH($B25,'ETAPA OBRA'!$B:$B,0))="x",'ETAPA OBRA'!H$1&", ","")& IF(INDEX('ETAPA OBRA'!I:I,MATCH($B25,'ETAPA OBRA'!$B:$B,0))="x",'ETAPA OBRA'!I$1&", ","")& IF(INDEX('ETAPA OBRA'!J:J,MATCH($B25,'ETAPA OBRA'!$B:$B,0))="x",'ETAPA OBRA'!J$1&", ","")& IF(INDEX('ETAPA OBRA'!K:K,MATCH($B25,'ETAPA OBRA'!$B:$B,0))="x",'ETAPA OBRA'!K$1&", ","")& IF(INDEX('ETAPA OBRA'!L:L,MATCH($B25,'ETAPA OBRA'!$B:$B,0))="x",'ETAPA OBRA'!L$1&", ","")& IF(INDEX('ETAPA OBRA'!M:M,MATCH($B25,'ETAPA OBRA'!$B:$B,0))="x",'ETAPA OBRA'!M$1&", ","")& IF(INDEX('ETAPA OBRA'!N:N,MATCH($B25,'ETAPA OBRA'!$B:$B,0))="x",'ETAPA OBRA'!N$1&", ","")& IF(INDEX('ETAPA OBRA'!O:O,MATCH($B25,'ETAPA OBRA'!$B:$B,0))="x",'ETAPA OBRA'!O$1&", ","")& IF(INDEX('ETAPA OBRA'!P:P,MATCH($B25,'ETAPA OBRA'!$B:$B,0))="x",'ETAPA OBRA'!P$1&", ","")& IF(INDEX('ETAPA OBRA'!Q:Q,MATCH($B25,'ETAPA OBRA'!$B:$B,0))="x",'ETAPA OBRA'!Q$1&", ","")& IF(INDEX('ETAPA OBRA'!R:R,MATCH($B25,'ETAPA OBRA'!$B:$B,0))="x",'ETAPA OBRA'!R$1&", ","")& IF(INDEX('ETAPA OBRA'!S:S,MATCH($B25,'ETAPA OBRA'!$B:$B,0))="x",'ETAPA OBRA'!S$1&", ","")& IF(INDEX('ETAPA OBRA'!T:T,MATCH($B25,'ETAPA OBRA'!$B:$B,0))="x",'ETAPA OBRA'!T$1&", ","")& IF(INDEX('ETAPA OBRA'!U:U,MATCH($B25,'ETAPA OBRA'!$B:$B,0))="x",'ETAPA OBRA'!U$1&", ","") )-2),"") -> Paralisada | N25: =IF(M25="","Não iniciada", IF(ISNUMBER(FIND("Cancelada",M25)),"Cancelada", IF(ISNUMBER(FIND("Paralisada",M25)),"Paralisada", IF(ISNUMBER(FIND("Finalizado",M25)),"Finalizado", "Em andamento")))) -> Paralisada | O25: 33367.08 | P25: =SUM($J25:$L25) -> 12942.93 | Q25: =O25-P25 -> 20424.15 | R25: =IF(O25=0,0,Q25/O25) -> 0.61210481 | S25: =IF(R25>=0.2,"✅ OK - Fechar Parceiro","⚠️ Ajustar Custos (<20%)") -> ✅ OK - Fechar Parceiro | T25: =Cronograma[[#This Row],[STATUS]] -> ⚠️ PARALISADO
A26: BR66924-R | B26: =IF(A26<>"","contel-"&TEXT(COUNTA($A$2:A26),"00"),"") -> contel-25 | C26: SBA | D26: BRASILIA | E26: DF | F26: https://maps.app.goo.gl/N5Xkt4MkHP63V4dR9 | G26: 1708 | H26: 15835 | I26: PEDRO | J26: =SUM(EQUIPE!C26,EQUIPE!E26,EQUIPE!G26,EQUIPE!I26,EQUIPE!K26,EQUIPE!M26,EQUIPE!O26) -> 10000 | K26: 6199.93 | L26: 2925.99 | M26: =IFERROR(LEFT( IF(INDEX('ETAPA OBRA'!C:C,MATCH($B26,'ETAPA OBRA'!$B:$B,0))="x",'ETAPA OBRA'!C$1&", ","")& IF(INDEX('ETAPA OBRA'!D:D,MATCH($B26,'ETAPA OBRA'!$B:$B,0))="x",'ETAPA OBRA'!D$1&", ","")& IF(INDEX('ETAPA OBRA'!F:F,MATCH($B26,'ETAPA OBRA'!$B:$B,0))="x",'ETAPA OBRA'!F$1&", ","")& IF(INDEX('ETAPA OBRA'!G:G,MATCH($B26,'ETAPA OBRA'!$B:$B,0))="x",'ETAPA OBRA'!G$1&", ","")& IF(INDEX('ETAPA OBRA'!H:H,MATCH($B26,'ETAPA OBRA'!$B:$B,0))="x",'ETAPA OBRA'!H$1&", ","")& IF(INDEX('ETAPA OBRA'!I:I,MATCH($B26,'ETAPA OBRA'!$B:$B,0))="x",'ETAPA OBRA'!I$1&", ","")& IF(INDEX('ETAPA OBRA'!J:J,MATCH($B26,'ETAPA OBRA'!$B:$B,0))="x",'ETAPA OBRA'!J$1&", ","")& IF(INDEX('ETAPA OBRA'!K:K,MATCH($B26,'ETAPA OBRA'!$B:$B,0))="x",'ETAPA OBRA'!K$1&", ","")& IF(INDEX('ETAPA OBRA'!L:L,MATCH($B26,'ETAPA OBRA'!$B:$B,0))="x",'ETAPA OBRA'!L$1&", ","")& IF(INDEX('ETAPA OBRA'!M:M,MATCH($B26,'ETAPA OBRA'!$B:$B,0))="x",'ETAPA OBRA'!M$1&", ","")& IF(INDEX('ETAPA OBRA'!N:N,MATCH($B26,'ETAPA OBRA'!$B:$B,0))="x",'ETAPA OBRA'!N$1&", ","")& IF(INDEX('ETAPA OBRA'!O:O,MATCH($B26,'ETAPA OBRA'!$B:$B,0))="x",'ETAPA OBRA'!O$1&", ","")& IF(INDEX('ETAPA OBRA'!P:P,MATCH($B26,'ETAPA OBRA'!$B:$B,0))="x",'ETAPA OBRA'!P$1&", ","")& IF(INDEX('ETAPA OBRA'!Q:Q,MATCH($B26,'ETAPA OBRA'!$B:$B,0))="x",'ETAPA OBRA'!Q$1&", ","")& IF(INDEX('ETAPA OBRA'!R:R,MATCH($B26,'ETAPA OBRA'!$B:$B,0))="x",'ETAPA OBRA'!R$1&", ","")& IF(INDEX('ETAPA OBRA'!S:S,MATCH($B26,'ETAPA OBRA'!$B:$B,0))="x",'ETAPA OBRA'!S$1&", ","")& IF(INDEX('ETAPA OBRA'!T:T,MATCH($B26,'ETAPA OBRA'!$B:$B,0))="x",'ETAPA OBRA'!T$1&", ","")& IF(INDEX('ETAPA OBRA'!U:U,MATCH($B26,'ETAPA OBRA'!$B:$B,0))="x",'ETAPA OBRA'!U$1&", ",""),LEN( IF(INDEX('ETAPA OBRA'!C:C,MATCH($B26,'ETAPA OBRA'!$B:$B,0))="x",'ETAPA OBRA'!C$1&", ","")& IF(INDEX('ETAPA OBRA'!D:D,MATCH($B26,'ETAPA OBRA'!$B:$B,0))="x",'ETAPA OBRA'!D$1&", ","")& IF(INDEX('ETAPA OBRA'!F:F,MATCH($B26,'ETAPA OBRA'!$B:$B,0))="x",'ETAPA OBRA'!F$1&", ","")& IF(INDEX('ETAPA OBRA'!G:G,MATCH($B26,'ETAPA OBRA'!$B:$B,0))="x",'ETAPA OBRA'!G$1&", ","")& IF(INDEX('ETAPA OBRA'!H:H,MATCH($B26,'ETAPA OBRA'!$B:$B,0))="x",'ETAPA OBRA'!H$1&", ","")& IF(INDEX('ETAPA OBRA'!I:I,MATCH($B26,'ETAPA OBRA'!$B:$B,0))="x",'ETAPA OBRA'!I$1&", ","")& IF(INDEX('ETAPA OBRA'!J:J,MATCH($B26,'ETAPA OBRA'!$B:$B,0))="x",'ETAPA OBRA'!J$1&", ","")& IF(INDEX('ETAPA OBRA'!K:K,MATCH($B26,'ETAPA OBRA'!$B:$B,0))="x",'ETAPA OBRA'!K$1&", ","")& IF(INDEX('ETAPA OBRA'!L:L,MATCH($B26,'ETAPA OBRA'!$B:$B,0))="x",'ETAPA OBRA'!L$1&", ","")& IF(INDEX('ETAPA OBRA'!M:M,MATCH($B26,'ETAPA OBRA'!$B:$B,0))="x",'ETAPA OBRA'!M$1&", ","")& IF(INDEX('ETAPA OBRA'!N:N,MATCH($B26,'ETAPA OBRA'!$B:$B,0))="x",'ETAPA OBRA'!N$1&", ","")& IF(INDEX('ETAPA OBRA'!O:O,MATCH($B26,'ETAPA OBRA'!$B:$B,0))="x",'ETAPA OBRA'!O$1&", ","")& IF(INDEX('ETAPA OBRA'!P:P,MATCH($B26,'ETAPA OBRA'!$B:$B,0))="x",'ETAPA OBRA'!P$1&", ","")& IF(INDEX('ETAPA OBRA'!Q:Q,MATCH($B26,'ETAPA OBRA'!$B:$B,0))="x",'ETAPA OBRA'!Q$1&", ","")& IF(INDEX('ETAPA OBRA'!R:R,MATCH($B26,'ETAPA OBRA'!$B:$B,0))="x",'ETAPA OBRA'!R$1&", ","")& IF(INDEX('ETAPA OBRA'!S:S,MATCH($B26,'ETAPA OBRA'!$B:$B,0))="x",'ETAPA OBRA'!S$1&", ","")& IF(INDEX('ETAPA OBRA'!T:T,MATCH($B26,'ETAPA OBRA'!$B:$B,0))="x",'ETAPA OBRA'!T$1&", ","")& IF(INDEX('ETAPA OBRA'!U:U,MATCH($B26,'ETAPA OBRA'!$B:$B,0))="x",'ETAPA OBRA'!U$1&", ","") )-2),"") -> Finalizado | N26: =IF(M26="","Não iniciada", IF(ISNUMBER(FIND("Cancelada",M26)),"Cancelada", IF(ISNUMBER(FIND("Paralisada",M26)),"Paralisada", IF(ISNUMBER(FIND("Finalizado",M26)),"Finalizado", "Em andamento")))) -> Finalizado | O26: 41818.77 | P26: =SUM($J26:$L26) -> 19125.92 | Q26: =O26-P26 -> 22692.85 | R26: =IF(O26=0,0,Q26/O26) -> 0.54264748 | S26: =IF(R26>=0.2,"✅ OK - Fechar Parceiro","⚠️ Ajustar Custos (<20%)") -> ✅ OK - Fechar Parceiro | T26: =Cronograma[[#This Row],[STATUS]] -> ✅ CONCLUÍDO
... A35: BR67360-A | B35: =IF(A35<>"","contel-"&TEXT(COUNTA($A$2:A35),"00"),"") -> contel-34 | C35: SBA | D35: JACOBINA | E35: BA | F35: https://maps.app.goo.gl/T1N7nRJkEsbzh7ZR8 | G35: 1736 | H35: 15864 | I35: HENRIQUE | J35: =SUM(EQUIPE!C35,EQUIPE!E35,EQUIPE!G35,EQUIPE!I35,EQUIPE!K35,EQUIPE!M35,EQUIPE!O35) -> 9500 | K35: 1907.5 | L35: 1366.03 | M35: =IFERROR(LEFT( IF(INDEX('ETAPA OBRA'!C:C,MATCH($B35,'ETAPA OBRA'!$B:$B,0))="x",'ETAPA OBRA'!C$1&", ","")& IF(INDEX('ETAPA OBRA'!D:D,MATCH($B35,'ETAPA OBRA'!$B:$B,0))="x",'ETAPA OBRA'!D$1&", ","")& IF(INDEX('ETAPA OBRA'!F:F,MATCH($B35,'ETAPA OBRA'!$B:$B,0))="x",'ETAPA OBRA'!F$1&", ","")& IF(INDEX('ETAPA OBRA'!G:G,MATCH($B35,'ETAPA OBRA'!$B:$B,0))="x",'ETAPA OBRA'!G$1&", ","")& IF(INDEX('ETAPA OBRA'!H:H,MATCH($B35,'ETAPA OBRA'!$B:$B,0))="x",'ETAPA OBRA'!H$1&", ","")& IF(INDEX('ETAPA OBRA'!I:I,MATCH($B35,'ETAPA OBRA'!$B:$B,0))="x",'ETAPA OBRA'!I$1&", ","")& IF(INDEX('ETAPA OBRA'!J:J,MATCH($B35,'ETAPA OBRA'!$B:$B,0))="x",'ETAPA OBRA'!J$1&", ","")& IF(INDEX('ETAPA OBRA'!K:K,MATCH($B35,'ETAPA OBRA'!$B:$B,0))="x",'ETAPA OBRA'!K$1&", ","")& IF(INDEX('ETAPA OBRA'!L:L,MATCH($B35,'ETAPA OBRA'!$B:$B,0))="x",'ETAPA OBRA'!L$1&", ","")& IF(INDEX('ETAPA OBRA'!M:M,MATCH($B35,'ETAPA OBRA'!$B:$B,0))="x",'ETAPA OBRA'!M$1&", ","")& IF(INDEX('ETAPA OBRA'!N:N,MATCH($B35,'ETAPA OBRA'!$B:$B,0))="x",'ETAPA OBRA'!N$1&", ","")& IF(INDEX('ETAPA OBRA'!O:O,MATCH($B35,'ETAPA OBRA'!$B:$B,0))="x",'ETAPA OBRA'!O$1&", ","")& IF(INDEX('ETAPA OBRA'!P:P,MATCH($B35,'ETAPA OBRA'!$B:$B,0))="x",'ETAPA OBRA'!P$1&", ","")& IF(INDEX('ETAPA OBRA'!Q:Q,MATCH($B35,'ETAPA OBRA'!$B:$B,0))="x",'ETAPA OBRA'!Q$1&", ","")& IF(INDEX('ETAPA OBRA'!R:R,MATCH($B35,'ETAPA OBRA'!$B:$B,0))="x",'ETAPA OBRA'!R$1&", ","")& IF(INDEX('ETAPA OBRA'!S:S,MATCH($B35,'ETAPA OBRA'!$B:$B,0))="x",'ETAPA OBRA'!S$1&", ","")& IF(INDEX('ETAPA OBRA'!T:T,MATCH($B35,'ETAPA OBRA'!$B:$B,0))="x",'ETAPA OBRA'!T$1&", ","")& IF(INDEX('ETAPA OBRA'!U:U,MATCH($B35,'ETAPA OBRA'!$B:$B,0))="x",'ETAPA OBRA'!U$1&", ",""),LEN( IF(INDEX('ETAPA OBRA'!C:C,MATCH($B35,'ETAPA OBRA'!$B:$B,0))="x",'ETAPA OBRA'!C$1&", ","")& IF(INDEX('ETAPA OBRA'!D:D,MATCH($B35,'ETAPA OBRA'!$B:$B,0))="x",'ETAPA OBRA'!D$1&", ","")& IF(INDEX('ETAPA OBRA'!F:F,MATCH($B35,'ETAPA OBRA'!$B:$B,0))="x",'ETAPA OBRA'!F$1&", ","")& IF(INDEX('ETAPA OBRA'!G:G,MATCH($B35,'ETAPA OBRA'!$B:$B,0))="x",'ETAPA OBRA'!G$1&", ","")& IF(INDEX('ETAPA OBRA'!H:H,MATCH($B35,'ETAPA OBRA'!$B:$B,0))="x",'ETAPA OBRA'!H$1&", ","")& IF(INDEX('ETAPA OBRA'!I:I,MATCH($B35,'ETAPA OBRA'!$B:$B,0))="x",'ETAPA OBRA'!I$1&", ","")& IF(INDEX('ETAPA OBRA'!J:J,MATCH($B35,'ETAPA OBRA'!$B:$B,0))="x",'ETAPA OBRA'!J$1&", ","")& IF(INDEX('ETAPA OBRA'!K:K,MATCH($B35,'ETAPA OBRA'!$B:$B,0))="x",'ETAPA OBRA'!K$1&", ","")& IF(INDEX('ETAPA OBRA'!L:L,MATCH($B35,'ETAPA OBRA'!$B:$B,0))="x",'ETAPA OBRA'!L$1&", ","")& IF(INDEX('ETAPA OBRA'!M:M,MATCH($B35,'ETAPA OBRA'!$B:$B,0))="x",'ETAPA OBRA'!M$1&", ","")& IF(INDEX('ETAPA OBRA'!N:N,MATCH($B35,'ETAPA OBRA'!$B:$B,0))="x",'ETAPA OBRA'!N$1&", ","")& IF(INDEX('ETAPA OBRA'!O:O,MATCH($B35,'ETAPA OBRA'!$B:$B,0))="x",'ETAPA OBRA'!O$1&", ","")& IF(INDEX('ETAPA OBRA'!P:P,MATCH($B35,'ETAPA OBRA'!$B:$B,0))="x",'ETAPA OBRA'!P$1&", ","")& IF(INDEX('ETAPA OBRA'!Q:Q,MATCH($B35,'ETAPA OBRA'!$B:$B,0))="x",'ETAPA OBRA'!Q$1&", ","")& IF(INDEX('ETAPA OBRA'!R:R,MATCH($B35,'ETAPA OBRA'!$B:$B,0))="x",'ETAPA OBRA'!R$1&", ","")& IF(INDEX('ETAPA OBRA'!S:S,MATCH($B35,'ETAPA OBRA'!$B:$B,0))="x",'ETAPA OBRA'!S$1&", ","")& IF(INDEX('ETAPA OBRA'!T:T,MATCH($B35,'ETAPA OBRA'!$B:$B,0))="x",'ETAPA OBRA'!T$1&", ","")& IF(INDEX('ETAPA OBRA'!U:U,MATCH($B35,'ETAPA OBRA'!$B:$B,0))="x",'ETAPA OBRA'!U$1&", ","") )-2),"") -> Finalizado | N35: =IF(M35="","Não iniciada", IF(ISNUMBER(FIND("Cancelada",M35)),"Cancelada", IF(ISNUMBER(FIND("Paralisada",M35)),"Paralisada", IF(ISNUMBER(FIND("Finalizado",M35)),"Finalizado", "Em andamento")))) -> Finalizado | O35: 24565.64 | P35: =SUM($J35:$L35) -> 12773.53 | Q35: =O35-P35 -> 11792.11 | R35: =IF(O35=0,0,Q35/O35) -> 0.48002454 | S35: =IF(R35>=0.2,"✅ OK - Fechar Parceiro","⚠️ Ajustar Custos (<20%)") -> ✅ OK - Fechar Parceiro | T35: =Cronograma[[#This Row],[STATUS]] -> ✅ CONCLUÍDO
A36: TABOCA | B36: =IF(A36<>"","contel-"&TEXT(COUNTA($A$2:A36),"00"),"") -> contel-35 | C36: TABOCA | D36: PRESIDENTE FIGUEIREDO | E36: AM | F36: https://maps.app.goo.gl/R79HG9WpuJaawnCV8 | G36: 1738 | H36: 15913 | I36: ELIAS | J36: =SUM(EQUIPE!C36,EQUIPE!E36,EQUIPE!G36,EQUIPE!I36,EQUIPE!K36,EQUIPE!M36,EQUIPE!O36) -> 0 | L36: 398787.69 | M36: =IFERROR(LEFT( IF(INDEX('ETAPA OBRA'!C:C,MATCH($B36,'ETAPA OBRA'!$B:$B,0))="x",'ETAPA OBRA'!C$1&", ","")& IF(INDEX('ETAPA OBRA'!D:D,MATCH($B36,'ETAPA OBRA'!$B:$B,0))="x",'ETAPA OBRA'!D$1&", ","")& IF(INDEX('ETAPA OBRA'!F:F,MATCH($B36,'ETAPA OBRA'!$B:$B,0))="x",'ETAPA OBRA'!F$1&", ","")& IF(INDEX('ETAPA OBRA'!G:G,MATCH($B36,'ETAPA OBRA'!$B:$B,0))="x",'ETAPA OBRA'!G$1&", ","")& IF(INDEX('ETAPA OBRA'!H:H,MATCH($B36,'ETAPA OBRA'!$B:$B,0))="x",'ETAPA OBRA'!H$1&", ","")& IF(INDEX('ETAPA OBRA'!I:I,MATCH($B36,'ETAPA OBRA'!$B:$B,0))="x",'ETAPA OBRA'!I$1&", ","")& IF(INDEX('ETAPA OBRA'!J:J,MATCH($B36,'ETAPA OBRA'!$B:$B,0))="x",'ETAPA OBRA'!J$1&", ","")& IF(INDEX('ETAPA OBRA'!K:K,MATCH($B36,'ETAPA OBRA'!$B:$B,0))="x",'ETAPA OBRA'!K$1&", ","")& IF(INDEX('ETAPA OBRA'!L:L,MATCH($B36,'ETAPA OBRA'!$B:$B,0))="x",'ETAPA OBRA'!L$1&", ","")& IF(INDEX('ETAPA OBRA'!M:M,MATCH($B36,'ETAPA OBRA'!$B:$B,0))="x",'ETAPA OBRA'!M$1&", ","")& IF(INDEX('ETAPA OBRA'!N:N,MATCH($B36,'ETAPA OBRA'!$B:$B,0))="x",'ETAPA OBRA'!N$1&", ","")& IF(INDEX('ETAPA OBRA'!O:O,MATCH($B36,'ETAPA OBRA'!$B:$B,0))="x",'ETAPA OBRA'!O$1&", ","")& IF(INDEX('ETAPA OBRA'!P:P,MATCH($B36,'ETAPA OBRA'!$B:$B,0))="x",'ETAPA OBRA'!P$1&", ","")& IF(INDEX('ETAPA OBRA'!Q:Q,MATCH($B36,'ETAPA OBRA'!$B:$B,0))="x",'ETAPA OBRA'!Q$1&", ","")& IF(INDEX('ETAPA OBRA'!R:R,MATCH($B36,'ETAPA OBRA'!$B:$B,0))="x",'ETAPA OBRA'!R$1&", ","")& IF(INDEX('ETAPA OBRA'!S:S,MATCH($B36,'ETAPA OBRA'!$B:$B,0))="x",'ETAPA OBRA'!S$1&", ","")& IF(INDEX('ETAPA OBRA'!T:T,MATCH($B36,'ETAPA OBRA'!$B:$B,0))="x",'ETAPA OBRA'!T$1&", ","")& IF(INDEX('ETAPA OBRA'!U:U,MATCH($B36,'ETAPA OBRA'!$B:$B,0))="x",'ETAPA OBRA'!U$1&", ",""),LEN( IF(INDEX('ETAPA OBRA'!C:C,MATCH($B36,'ETAPA OBRA'!$B:$B,0))="x",'ETAPA OBRA'!C$1&", ","")& IF(INDEX('ETAPA OBRA'!D:D,MATCH($B36,'ETAPA OBRA'!$B:$B,0))="x",'ETAPA OBRA'!D$1&", ","")& IF(INDEX('ETAPA OBRA'!F:F,MATCH($B36,'ETAPA OBRA'!$B:$B,0))="x",'ETAPA OBRA'!F$1&", ","")& IF(INDEX('ETAPA OBRA'!G:G,MATCH($B36,'ETAPA OBRA'!$B:$B,0))="x",'ETAPA OBRA'!G$1&", ","")& IF(INDEX('ETAPA OBRA'!H:H,MATCH($B36,'ETAPA OBRA'!$B:$B,0))="x",'ETAPA OBRA'!H$1&", ","")& IF(INDEX('ETAPA OBRA'!I:I,MATCH($B36,'ETAPA OBRA'!$B:$B,0))="x",'ETAPA OBRA'!I$1&", ","")& IF(INDEX('ETAPA OBRA'!J:J,MATCH($B36,'ETAPA OBRA'!$B:$B,0))="x",'ETAPA OBRA'!J$1&", ","")& IF(INDEX('ETAPA OBRA'!K:K,MATCH($B36,'ETAPA OBRA'!$B:$B,0))="x",'ETAPA OBRA'!K$1&", ","")& IF(INDEX('ETAPA OBRA'!L:L,MATCH($B36,'ETAPA OBRA'!$B:$B,0))="x",'ETAPA OBRA'!L$1&", ","")& IF(INDEX('ETAPA OBRA'!M:M,MATCH($B36,'ETAPA OBRA'!$B:$B,0))="x",'ETAPA OBRA'!M$1&", ","")& IF(INDEX('ETAPA OBRA'!N:N,MATCH($B36,'ETAPA OBRA'!$B:$B,0))="x",'ETAPA OBRA'!N$1&", ","")& IF(INDEX('ETAPA OBRA'!O:O,MATCH($B36,'ETAPA OBRA'!$B:$B,0))="x",'ETAPA OBRA'!O$1&", ","")& IF(INDEX('ETAPA OBRA'!P:P,MATCH($B36,'ETAPA OBRA'!$B:$B,0))="x",'ETAPA OBRA'!P$1&", ","")& IF(INDEX('ETAPA OBRA'!Q:Q,MATCH($B36,'ETAPA OBRA'!$B:$B,0))="x",'ETAPA OBRA'!Q$1&", ","")& IF(INDEX('ETAPA OBRA'!R:R,MATCH($B36,'ETAPA OBRA'!$B:$B,0))="x",'ETAPA OBRA'!R$1&", ","")& IF(INDEX('ETAPA OBRA'!S:S,MATCH($B36,'ETAPA OBRA'!$B:$B,0))="x",'ETAPA OBRA'!S$1&", ","")& IF(INDEX('ETAPA OBRA'!T:T,MATCH($B36,'ETAPA OBRA'!$B:$B,0))="x",'ETAPA OBRA'!T$1&", ","")& IF(INDEX('ETAPA OBRA'!U:U,MATCH($B36,'ETAPA OBRA'!$B:$B,0))="x",'ETAPA OBRA'!U$1&", ","") )-2),"") -> Execução | N36: =IF(M36="","Não iniciada", IF(ISNUMBER(FIND("Cancelada",M36)),"Cancelada", IF(ISNUMBER(FIND("Paralisada",M36)),"Paralisada", IF(ISNUMBER(FIND("Finalizado",M36)),"Finalizado", "Em andamento")))) -> Em andamento | O36: =659900+13987.65+45356 -> 719243.65 | P36: =SUM($J36:$L36) -> 398787.69 | Q36: =O36-P36 -> 320455.96 | R36: =IF(O36=0,0,Q36/O36) -> 0.44554576 | S36: =IF(R36>=0.2,"✅ OK - Fechar Parceiro","⚠️ Ajustar Custos (<20%)") -> ✅ OK - Fechar Parceiro | T36: =Cronograma[[#This Row],[STATUS]] -> 🕓 EM ANDAMENTO
A37: BR67041-A | B37: =IF(A37<>"","contel-"&TEXT(COUNTA($A$2:A37),"00"),"") -> contel-36 | C37: SBA | D37: BRASILIA | E37: DF | F37: https://maps.app.goo.gl/weuBtUozD4HYXUj97 | G37: 1740 | H37: 15902 | I37: DANILO | J37: =SUM(EQUIPE!C37,EQUIPE!E37,EQUIPE!G37,EQUIPE!I37,EQUIPE!K37,EQUIPE!M37,EQUIPE!O37) -> 9800 | K37: 2777.43 | L37: 9180.9 | M37: =IFERROR(LEFT( IF(INDEX('ETAPA OBRA'!C:C,MATCH($B37,'ETAPA OBRA'!$B:$B,0))="x",'ETAPA OBRA'!C$1&", ","")& IF(INDEX('ETAPA OBRA'!D:D,MATCH($B37,'ETAPA OBRA'!$B:$B,0))="x",'ETAPA OBRA'!D$1&", ","")& IF(INDEX('ETAPA OBRA'!F:F,MATCH($B37,'ETAPA OBRA'!$B:$B,0))="x",'ETAPA OBRA'!F$1&", ","")& IF(INDEX('ETAPA OBRA'!G:G,MATCH($B37,'ETAPA OBRA'!$B:$B,0))="x",'ETAPA OBRA'!G$1&", ","")& IF(INDEX('ETAPA OBRA'!H:H,MATCH($B37,'ETAPA OBRA'!$B:$B,0))="x",'ETAPA OBRA'!H$1&", ","")& IF(INDEX('ETAPA OBRA'!I:I,MATCH($B37,'ETAPA OBRA'!$B:$B,0))="x",'ETAPA OBRA'!I$1&", ","")& IF(INDEX('ETAPA OBRA'!J:J,MATCH($B37,'ETAPA OBRA'!$B:$B,0))="x",'ETAPA OBRA'!J$1&", ","")& IF(INDEX('ETAPA OBRA'!K:K,MATCH($B37,'ETAPA OBRA'!$B:$B,0))="x",'ETAPA OBRA'!K$1&", ","")& IF(INDEX('ETAPA OBRA'!L:L,MATCH($B37,'ETAPA OBRA'!$B:$B,0))="x",'ETAPA OBRA'!L$1&", ","")& IF(INDEX('ETAPA OBRA'!M:M,MATCH($B37,'ETAPA OBRA'!$B:$B,0))="x",'ETAPA OBRA'!M$1&", ","")& IF(INDEX('ETAPA OBRA'!N:N,MATCH($B37,'ETAPA OBRA'!$B:$B,0))="x",'ETAPA OBRA'!N$1&", ","")& IF(INDEX('ETAPA OBRA'!O:O,MATCH($B37,'ETAPA OBRA'!$B:$B,0))="x",'ETAPA OBRA'!O$1&", ","")& IF(INDEX('ETAPA OBRA'!P:P,MATCH($B37,'ETAPA OBRA'!$B:$B,0))="x",'ETAPA OBRA'!P$1&", ","")& IF(INDEX('ETAPA OBRA'!Q:Q,MATCH($B37,'ETAPA OBRA'!$B:$B,0))="x",'ETAPA OBRA'!Q$1&", ","")& IF(INDEX('ETAPA OBRA'!R:R,MATCH($B37,'ETAPA OBRA'!$B:$B,0))="x",'ETAPA OBRA'!R$1&", ","")& IF(INDEX('ETAPA OBRA'!S:S,MATCH($B37,'ETAPA OBRA'!$B:$B,0))="x",'ETAPA OBRA'!S$1&", ","")& IF(INDEX('ETAPA OBRA'!T:T,MATCH($B37,'ETAPA OBRA'!$B:$B,0))="x",'ETAPA OBRA'!T$1&", ","")& IF(INDEX('ETAPA OBRA'!U:U,MATCH($B37,'ETAPA OBRA'!$B:$B,0))="x",'ETAPA OBRA'!U$1&", ",""),LEN( IF(INDEX('ETAPA OBRA'!C:C,MATCH($B37,'ETAPA OBRA'!$B:$B,0))="x",'ETAPA OBRA'!C$1&", ","")& IF(INDEX('ETAPA OBRA'!D:D,MATCH($B37,'ETAPA OBRA'!$B:$B,0))="x",'ETAPA OBRA'!D$1&", ","")& IF(INDEX('ETAPA OBRA'!F:F,MATCH($B37,'ETAPA OBRA'!$B:$B,0))="x",'ETAPA OBRA'!F$1&", ","")& IF(INDEX('ETAPA OBRA'!G:G,MATCH($B37,'ETAPA OBRA'!$B:$B,0))="x",'ETAPA OBRA'!G$1&", ","")& IF(INDEX('ETAPA OBRA'!H:H,MATCH($B37,'ETAPA OBRA'!$B:$B,0))="x",'ETAPA OBRA'!H$1&", ","")& IF(INDEX('ETAPA OBRA'!I:I,MATCH($B37,'ETAPA OBRA'!$B:$B,0))="x",'ETAPA OBRA'!I$1&", ","")& IF(INDEX('ETAPA OBRA'!J:J,MATCH($B37,'ETAPA OBRA'!$B:$B,0))="x",'ETAPA OBRA'!J$1&", ","")& IF(INDEX('ETAPA OBRA'!K:K,MATCH($B37,'ETAPA OBRA'!$B:$B,0))="x",'ETAPA OBRA'!K$1&", ","")& IF(INDEX('ETAPA OBRA'!L:L,MATCH($B37,'ETAPA OBRA'!$B:$B,0))="x",'ETAPA OBRA'!L$1&", ","")& IF(INDEX('ETAPA OBRA'!M:M,MATCH($B37,'ETAPA OBRA'!$B:$B,0))="x",'ETAPA OBRA'!M$1&", ","")& IF(INDEX('ETAPA OBRA'!N:N,MATCH($B37,'ETAPA OBRA'!$B:$B,0))="x",'ETAPA OBRA'!N$1&", ","")& IF(INDEX('ETAPA OBRA'!O:O,MATCH($B37,'ETAPA OBRA'!$B:$B,0))="x",'ETAPA OBRA'!O$1&", ","")& IF(INDEX('ETAPA OBRA'!P:P,MATCH($B37,'ETAPA OBRA'!$B:$B,0))="x",'ETAPA OBRA'!P$1&", ","")& IF(INDEX('ETAPA OBRA'!Q:Q,MATCH($B37,'ETAPA OBRA'!$B:$B,0))="x",'ETAPA OBRA'!Q$1&", ","")& IF(INDEX('ETAPA OBRA'!R:R,MATCH($B37,'ETAPA OBRA'!$B:$B,0))="x",'ETAPA OBRA'!R$1&", ","")& IF(INDEX('ETAPA OBRA'!S:S,MATCH($B37,'ETAPA OBRA'!$B:$B,0))="x",'ETAPA OBRA'!S$1&", ","")& IF(INDEX('ETAPA OBRA'!T:T,MATCH($B37,'ETAPA OBRA'!$B:$B,0))="x",'ETAPA OBRA'!T$1&", ","")& IF(INDEX('ETAPA OBRA'!U:U,MATCH($B37,'ETAPA OBRA'!$B:$B,0))="x",'ETAPA OBRA'!U$1&", ","") )-2),"") -> Finalizado | N37: =IF(M37="","Não iniciada", IF(ISNUMBER(FIND("Cancelada",M37)),"Cancelada", IF(ISNUMBER(FIND("Paralisada",M37)),"Paralisada", IF(ISNUMBER(FIND("Finalizado",M37)),"Finalizado", "Em andamento")))) -> Finalizado | O37: 33703.44 | P37: =SUM($J37:$L37) -> 21758.33 | Q37: =O37-P37 -> 11945.11 | R37: =IF(O37=0,0,Q37/O37) -> 0.35441812 | S37: =IF(R37>=0.2,"✅ OK - Fechar Parceiro","⚠️ Ajustar Custos (<20%)") -> ✅ OK - Fechar Parceiro | T37: =Cronograma[[#This Row],[STATUS]] -> ✅ CONCLUÍDO
A38: PABXX004 | B38: =IF(A38<>"","contel-"&TEXT(COUNTA($A$2:A38),"00"),"") -> contel-37 | C38: HLB | D38: BAIAO | E38: PA | F38: https://maps.app.goo.gl/KJjNZ6fD7giBqKgNA | G38: 1741 | H38: 15925 | I38: PEDRO | J38: =SUM(EQUIPE!C38,EQUIPE!E38,EQUIPE!G38,EQUIPE!I38,EQUIPE!K38,EQUIPE!M38,EQUIPE!O38) -> 2800 | K38: 3000 | L38: 5290.7 | M38: =IFERROR(LEFT( IF(INDEX('ETAPA OBRA'!C:C,MATCH($B38,'ETAPA OBRA'!$B:$B,0))="x",'ETAPA OBRA'!C$1&", ","")& IF(INDEX('ETAPA OBRA'!D:D,MATCH($B38,'ETAPA OBRA'!$B:$B,0))="x",'ETAPA OBRA'!D$1&", ","")& IF(INDEX('ETAPA OBRA'!F:F,MATCH($B38,'ETAPA OBRA'!$B:$B,0))="x",'ETAPA OBRA'!F$1&", ","")& IF(INDEX('ETAPA OBRA'!G:G,MATCH($B38,'ETAPA OBRA'!$B:$B,0))="x",'ETAPA OBRA'!G$1&", ","")& IF(INDEX('ETAPA OBRA'!H:H,MATCH($B38,'ETAPA OBRA'!$B:$B,0))="x",'ETAPA OBRA'!H$1&", ","")& IF(INDEX('ETAPA OBRA'!I:I,MATCH($B38,'ETAPA OBRA'!$B:$B,0))="x",'ETAPA OBRA'!I$1&", ","")& IF(INDEX('ETAPA OBRA'!J:J,MATCH($B38,'ETAPA OBRA'!$B:$B,0))="x",'ETAPA OBRA'!J$1&", ","")& IF(INDEX('ETAPA OBRA'!K:K,MATCH($B38,'ETAPA OBRA'!$B:$B,0))="x",'ETAPA OBRA'!K$1&", ","")& IF(INDEX('ETAPA OBRA'!L:L,MATCH($B38,'ETAPA OBRA'!$B:$B,0))="x",'ETAPA OBRA'!L$1&", ","")& IF(INDEX('ETAPA OBRA'!M:M,MATCH($B38,'ETAPA OBRA'!$B:$B,0))="x",'ETAPA OBRA'!M$1&", ","")& IF(INDEX('ETAPA OBRA'!N:N,MATCH($B38,'ETAPA OBRA'!$B:$B,0))="x",'ETAPA OBRA'!N$1&", ","")& IF(INDEX('ETAPA OBRA'!O:O,MATCH($B38,'ETAPA OBRA'!$B:$B,0))="x",'ETAPA OBRA'!O$1&", ","")& IF(INDEX('ETAPA OBRA'!P:P,MATCH($B38,'ETAPA OBRA'!$B:$B,0))="x",'ETAPA OBRA'!P$1&", ","")& IF(INDEX('ETAPA OBRA'!Q:Q,MATCH($B38,'ETAPA OBRA'!$B:$B,0))="x",'ETAPA OBRA'!Q$1&", ","")& IF(INDEX('ETAPA OBRA'!R:R,MATCH($B38,'ETAPA OBRA'!$B:$B,0))="x",'ETAPA OBRA'!R$1&", ","")& IF(INDEX('ETAPA OBRA'!S:S,MATCH($B38,'ETAPA OBRA'!$B:$B,0))="x",'ETAPA OBRA'!S$1&", ","")& IF(INDEX('ETAPA OBRA'!T:T,MATCH($B38,'ETAPA OBRA'!$B:$B,0))="x",'ETAPA OBRA'!T$1&", ","")& IF(INDEX('ETAPA OBRA'!U:U,MATCH($B38,'ETAPA OBRA'!$B:$B,0))="x",'ETAPA OBRA'!U$1&", ",""),LEN( IF(INDEX('ETAPA OBRA'!C:C,MATCH($B38,'ETAPA OBRA'!$B:$B,0))="x",'ETAPA OBRA'!C$1&", ","")& IF(INDEX('ETAPA OBRA'!D:D,MATCH($B38,'ETAPA OBRA'!$B:$B,0))="x",'ETAPA OBRA'!D$1&", ","")& IF(INDEX('ETAPA OBRA'!F:F,MATCH($B38,'ETAPA OBRA'!$B:$B,0))="x",'ETAPA OBRA'!F$1&", ","")& IF(INDEX('ETAPA OBRA'!G:G,MATCH($B38,'ETAPA OBRA'!$B:$B,0))="x",'ETAPA OBRA'!G$1&", ","")& IF(INDEX('ETAPA OBRA'!H:H,MATCH($B38,'ETAPA OBRA'!$B:$B,0))="x",'ETAPA OBRA'!H$1&", ","")& IF(INDEX('ETAPA OBRA'!I:I,MATCH($B38,'ETAPA OBRA'!$B:$B,0))="x",'ETAPA OBRA'!I$1&", ","")& IF(INDEX('ETAPA OBRA'!J:J,MATCH($B38,'ETAPA OBRA'!$B:$B,0))="x",'ETAPA OBRA'!J$1&", ","")& IF(INDEX('ETAPA OBRA'!K:K,MATCH($B38,'ETAPA OBRA'!$B:$B,0))="x",'ETAPA OBRA'!K$1&", ","")& IF(INDEX('ETAPA OBRA'!L:L,MATCH($B38,'ETAPA OBRA'!$B:$B,0))="x",'ETAPA OBRA'!L$1&", ","")& IF(INDEX('ETAPA OBRA'!M:M,MATCH($B38,'ETAPA OBRA'!$B:$B,0))="x",'ETAPA OBRA'!M$1&", ","")& IF(INDEX('ETAPA OBRA'!N:N,MATCH($B38,'ETAPA OBRA'!$B:$B,0))="x",'ETAPA OBRA'!N$1&", ","")& IF(INDEX('ETAPA OBRA'!O:O,MATCH($B38,'ETAPA OBRA'!$B:$B,0))="x",'ETAPA OBRA'!O$1&", ","")& IF(INDEX('ETAPA OBRA'!P:P,MATCH($B38,'ETAPA OBRA'!$B:$B,0))="x",'ETAPA OBRA'!P$1&", ","")& IF(INDEX('ETAPA OBRA'!Q:Q,MATCH($B38,'ETAPA OBRA'!$B:$B,0))="x",'ETAPA OBRA'!Q$1&", ","")& IF(INDEX('ETAPA OBRA'!R:R,MATCH($B38,'ETAPA OBRA'!$B:$B,0))="x",'ETAPA OBRA'!R$1&", ","")& IF(INDEX('ETAPA OBRA'!S:S,MATCH($B38,'ETAPA OBRA'!$B:$B,0))="x",'ETAPA OBRA'!S$1&", ","")& IF(INDEX('ETAPA OBRA'!T:T,MATCH($B38,'ETAPA OBRA'!$B:$B,0))="x",'ETAPA OBRA'!T$1&", ","")& IF(INDEX('ETAPA OBRA'!U:U,MATCH($B38,'ETAPA OBRA'!$B:$B,0))="x",'ETAPA OBRA'!U$1&", ","") )-2),"") -> Finalizado | N38: =IF(M38="","Não iniciada", IF(ISNUMBER(FIND("Cancelada",M38)),"Cancelada", IF(ISNUMBER(FIND("Paralisada",M38)),"Paralisada", IF(ISNUMBER(FIND("Finalizado",M38)),"Finalizado", "Em andamento")))) -> Finalizado | O38: 23000 | P38: =SUM($J38:$L38) -> 11090.7 | Q38: =O38-P38 -> 11909.3 | R38: =IF(O38=0,0,Q38/O38) -> 0.51779565 | S38: =IF(R38>=0.2,"✅ OK - Fechar Parceiro","⚠️ Ajustar Custos (<20%)") -> ✅ OK - Fechar Parceiro | T38: =Cronograma[[#This Row],[STATUS]] -> ✅ CONCLUÍDO
A39: ROGVR003 | B39: =IF(A39<>"","contel-"&TEXT(COUNTA($A$2:A39),"00"),"") -> contel-38 | C39: HLB | D39: GOVERNADOR JORGE TEIXEIRA | E39: RO | F39: https://maps.app.goo.gl/G5rypL41VaPKyhY96 | G39: 1742 | H39: 15926 | I39: PEDRO | J39: =SUM(EQUIPE!C39,EQUIPE!E39,EQUIPE!G39,EQUIPE!I39,EQUIPE!K39,EQUIPE!M39,EQUIPE!O39) -> 3000 | K39: 3950 | L39: 3271.47 | M39: =IFERROR(LEFT( IF(INDEX('ETAPA OBRA'!C:C,MATCH($B39,'ETAPA OBRA'!$B:$B,0))="x",'ETAPA OBRA'!C$1&", ","")& IF(INDEX('ETAPA OBRA'!D:D,MATCH($B39,'ETAPA OBRA'!$B:$B,0))="x",'ETAPA OBRA'!D$1&", ","")& IF(INDEX('ETAPA OBRA'!F:F,MATCH($B39,'ETAPA OBRA'!$B:$B,0))="x",'ETAPA OBRA'!F$1&", ","")& IF(INDEX('ETAPA OBRA'!G:G,MATCH($B39,'ETAPA OBRA'!$B:$B,0))="x",'ETAPA OBRA'!G$1&", ","")& IF(INDEX('ETAPA OBRA'!H:H,MATCH($B39,'ETAPA OBRA'!$B:$B,0))="x",'ETAPA OBRA'!H$1&", ","")& IF(INDEX('ETAPA OBRA'!I:I,MATCH($B39,'ETAPA OBRA'!$B:$B,0))="x",'ETAPA OBRA'!I$1&", ","")& IF(INDEX('ETAPA OBRA'!J:J,MATCH($B39,'ETAPA OBRA'!$B:$B,0))="x",'ETAPA OBRA'!J$1&", ","")& IF(INDEX('ETAPA OBRA'!K:K,MATCH($B39,'ETAPA OBRA'!$B:$B,0))="x",'ETAPA OBRA'!K$1&", ","")& IF(INDEX('ETAPA OBRA'!L:L,MATCH($B39,'ETAPA OBRA'!$B:$B,0))="x",'ETAPA OBRA'!L$1&", ","")& IF(INDEX('ETAPA OBRA'!M:M,MATCH($B39,'ETAPA OBRA'!$B:$B,0))="x",'ETAPA OBRA'!M$1&", ","")& IF(INDEX('ETAPA OBRA'!N:N,MATCH($B39,'ETAPA OBRA'!$B:$B,0))="x",'ETAPA OBRA'!N$1&", ","")& IF(INDEX('ETAPA OBRA'!O:O,MATCH($B39,'ETAPA OBRA'!$B:$B,0))="x",'ETAPA OBRA'!O$1&", ","")& IF(INDEX('ETAPA OBRA'!P:P,MATCH($B39,'ETAPA OBRA'!$B:$B,0))="x",'ETAPA OBRA'!P$1&", ","")& IF(INDEX('ETAPA OBRA'!Q:Q,MATCH($B39,'ETAPA OBRA'!$B:$B,0))="x",'ETAPA OBRA'!Q$1&", ","")& IF(INDEX('ETAPA OBRA'!R:R,MATCH($B39,'ETAPA OBRA'!$B:$B,0))="x",'ETAPA OBRA'!R$1&", ","")& IF(INDEX('ETAPA OBRA'!S:S,MATCH($B39,'ETAPA OBRA'!$B:$B,0))="x",'ETAPA OBRA'!S$1&", ","")& IF(INDEX('ETAPA OBRA'!T:T,MATCH($B39,'ETAPA OBRA'!$B:$B,0))="x",'ETAPA OBRA'!T$1&", ","")& IF(INDEX('ETAPA OBRA'!U:U,MATCH($B39,'ETAPA OBRA'!$B:$B,0))="x",'ETAPA OBRA'!U$1&", ",""),LEN( IF(INDEX('ETAPA OBRA'!C:C,MATCH($B39,'ETAPA OBRA'!$B:$B,0))="x",'ETAPA OBRA'!C$1&", ","")& IF(INDEX('ETAPA OBRA'!D:D,MATCH($B39,'ETAPA OBRA'!$B:$B,0))="x",'ETAPA OBRA'!D$1&", ","")& IF(INDEX('ETAPA OBRA'!F:F,MATCH($B39,'ETAPA OBRA'!$B:$B,0))="x",'ETAPA OBRA'!F$1&", ","")& IF(INDEX('ETAPA OBRA'!G:G,MATCH($B39,'ETAPA OBRA'!$B:$B,0))="x",'ETAPA OBRA'!G$1&", ","")& IF(INDEX('ETAPA OBRA'!H:H,MATCH($B39,'ETAPA OBRA'!$B:$B,0))="x",'ETAPA OBRA'!H$1&", ","")& IF(INDEX('ETAPA OBRA'!I:I,MATCH($B39,'ETAPA OBRA'!$B:$B,0))="x",'ETAPA OBRA'!I$1&", ","")& IF(INDEX('ETAPA OBRA'!J:J,MATCH($B39,'ETAPA OBRA'!$B:$B,0))="x",'ETAPA OBRA'!J$1&", ","")& IF(INDEX('ETAPA OBRA'!K:K,MATCH($B39,'ETAPA OBRA'!$B:$B,0))="x",'ETAPA OBRA'!K$1&", ","")& IF(INDEX('ETAPA OBRA'!L:L,MATCH($B39,'ETAPA OBRA'!$B:$B,0))="x",'ETAPA OBRA'!L$1&", ","")& IF(INDEX('ETAPA OBRA'!M:M,MATCH($B39,'ETAPA OBRA'!$B:$B,0))="x",'ETAPA OBRA'!M$1&", ","")& IF(INDEX('ETAPA OBRA'!N:N,MATCH($B39,'ETAPA OBRA'!$B:$B,0))="x",'ETAPA OBRA'!N$1&", ","")& IF(INDEX('ETAPA OBRA'!O:O,MATCH($B39,'ETAPA OBRA'!$B:$B,0))="x",'ETAPA OBRA'!O$1&", ","")& IF(INDEX('ETAPA OBRA'!P:P,MATCH($B39,'ETAPA OBRA'!$B:$B,0))="x",'ETAPA OBRA'!P$1&", ","")& IF(INDEX('ETAPA OBRA'!Q:Q,MATCH($B39,'ETAPA OBRA'!$B:$B,0))="x",'ETAPA OBRA'!Q$1&", ","")& IF(INDEX('ETAPA OBRA'!R:R,MATCH($B39,'ETAPA OBRA'!$B:$B,0))="x",'ETAPA OBRA'!R$1&", ","")& IF(INDEX('ETAPA OBRA'!S:S,MATCH($B39,'ETAPA OBRA'!$B:$B,0))="x",'ETAPA OBRA'!S$1&", ","")& IF(INDEX('ETAPA OBRA'!T:T,MATCH($B39,'ETAPA OBRA'!$B:$B,0))="x",'ETAPA OBRA'!T$1&", ","")& IF(INDEX('ETAPA OBRA'!U:U,MATCH($B39,'ETAPA OBRA'!$B:$B,0))="x",'ETAPA OBRA'!U$1&", ","") )-2),"") -> Finalizado | N39: =IF(M39="","Não iniciada", IF(ISNUMBER(FIND("Cancelada",M39)),"Cancelada", IF(ISNUMBER(FIND("Paralisada",M39)),"Paralisada", IF(ISNUMBER(FIND("Finalizado",M39)),"Finalizado", "Em andamento")))) -> Finalizado | O39: 22000 | P39: =SUM($J39:$L39) -> 10221.47 | Q39: =O39-P39 -> 11778.53 | R39: =IF(O39=0,0,Q39/O39) -> 0.53538773 | S39: =IF(R39>=0.2,"✅ OK - Fechar Parceiro","⚠️ Ajustar Custos (<20%)") -> ✅ OK - Fechar Parceiro | T39: =Cronograma[[#This Row],[STATUS]] -> ✅ CONCLUÍDO
A40: BSA039T1 | B40: =IF(A40<>"","contel-"&TEXT(COUNTA($A$2:A40),"00"),"") -> contel-39 | C40: ATC | D40: BRASILIA | E40: DF | F40: https://maps.app.goo.gl/i999QxrEM8jV9vnk6 | G40: 1743 | H40: 3941 | I40: DIOGO | J40: =SUM(EQUIPE!C40,EQUIPE!E40,EQUIPE!G40,EQUIPE!I40,EQUIPE!K40,EQUIPE!M40,EQUIPE!O40) -> 17500 | K40: 0 | L40: 0 | M40: =IFERROR(LEFT( IF(INDEX('ETAPA OBRA'!C:C,MATCH($B40,'ETAPA OBRA'!$B:$B,0))="x",'ETAPA OBRA'!C$1&", ","")& IF(INDEX('ETAPA OBRA'!D:D,MATCH($B40,'ETAPA OBRA'!$B:$B,0))="x",'ETAPA OBRA'!D$1&", ","")& IF(INDEX('ETAPA OBRA'!F:F,MATCH($B40,'ETAPA OBRA'!$B:$B,0))="x",'ETAPA OBRA'!F$1&", ","")& IF(INDEX('ETAPA OBRA'!G:G,MATCH($B40,'ETAPA OBRA'!$B:$B,0))="x",'ETAPA OBRA'!G$1&", ","")& IF(INDEX('ETAPA OBRA'!H:H,MATCH($B40,'ETAPA OBRA'!$B:$B,0))="x",'ETAPA OBRA'!H$1&", ","")& IF(INDEX('ETAPA OBRA'!I:I,MATCH($B40,'ETAPA OBRA'!$B:$B,0))="x",'ETAPA OBRA'!I$1&", ","")& IF(INDEX('ETAPA OBRA'!J:J,MATCH($B40,'ETAPA OBRA'!$B:$B,0))="x",'ETAPA OBRA'!J$1&", ","")& IF(INDEX('ETAPA OBRA'!K:K,MATCH($B40,'ETAPA OBRA'!$B:$B,0))="x",'ETAPA OBRA'!K$1&", ","")& IF(INDEX('ETAPA OBRA'!L:L,MATCH($B40,'ETAPA OBRA'!$B:$B,0))="x",'ETAPA OBRA'!L$1&", ","")& IF(INDEX('ETAPA OBRA'!M:M,MATCH($B40,'ETAPA OBRA'!$B:$B,0))="x",'ETAPA OBRA'!M$1&", ","")& IF(INDEX('ETAPA OBRA'!N:N,MATCH($B40,'ETAPA OBRA'!$B:$B,0))="x",'ETAPA OBRA'!N$1&", ","")& IF(INDEX('ETAPA OBRA'!O:O,MATCH($B40,'ETAPA OBRA'!$B:$B,0))="x",'ETAPA OBRA'!O$1&", ","")& IF(INDEX('ETAPA OBRA'!P:P,MATCH($B40,'ETAPA OBRA'!$B:$B,0))="x",'ETAPA OBRA'!P$1&", ","")& IF(INDEX('ETAPA OBRA'!Q:Q,MATCH($B40,'ETAPA OBRA'!$B:$B,0))="x",'ETAPA OBRA'!Q$1&", ","")& IF(INDEX('ETAPA OBRA'!R:R,MATCH($B40,'ETAPA OBRA'!$B:$B,0))="x",'ETAPA OBRA'!R$1&", ","")& IF(INDEX('ETAPA OBRA'!S:S,MATCH($B40,'ETAPA OBRA'!$B:$B,0))="x",'ETAPA OBRA'!S$1&", ","")& IF(INDEX('ETAPA OBRA'!T:T,MATCH($B40,'ETAPA OBRA'!$B:$B,0))="x",'ETAPA OBRA'!T$1&", ","")& IF(INDEX('ETAPA OBRA'!U:U,MATCH($B40,'ETAPA OBRA'!$B:$B,0))="x",'ETAPA OBRA'!U$1&", ",""),LEN( IF(INDEX('ETAPA OBRA'!C:C,MATCH($B40,'ETAPA OBRA'!$B:$B,0))="x",'ETAPA OBRA'!C$1&", ","")& IF(INDEX('ETAPA OBRA'!D:D,MATCH($B40,'ETAPA OBRA'!$B:$B,0))="x",'ETAPA OBRA'!D$1&", ","")& IF(INDEX('ETAPA OBRA'!F:F,MATCH($B40,'ETAPA OBRA'!$B:$B,0))="x",'ETAPA OBRA'!F$1&", ","")& IF(INDEX('ETAPA OBRA'!G:G,MATCH($B40,'ETAPA OBRA'!$B:$B,0))="x",'ETAPA OBRA'!G$1&", ","")& IF(INDEX('ETAPA OBRA'!H:H,MATCH($B40,'ETAPA OBRA'!$B:$B,0))="x",'ETAPA OBRA'!H$1&", ","")& IF(INDEX('ETAPA OBRA'!I:I,MATCH($B40,'ETAPA OBRA'!$B:$B,0))="x",'ETAPA OBRA'!I$1&", ","")& IF(INDEX('ETAPA OBRA'!J:J,MATCH($B40,'ETAPA OBRA'!$B:$B,0))="x",'ETAPA OBRA'!J$1&", ","")& IF(INDEX('ETAPA OBRA'!K:K,MATCH($B40,'ETAPA OBRA'!$B:$B,0))="x",'ETAPA OBRA'!K$1&", ","")& IF(INDEX('ETAPA OBRA'!L:L,MATCH($B40,'ETAPA OBRA'!$B:$B,0))="x",'ETAPA OBRA'!L$1&", ","")& IF(INDEX('ETAPA OBRA'!M:M,MATCH($B40,'ETAPA OBRA'!$B:$B,0))="x",'ETAPA OBRA'!M$1&", ","")& IF(INDEX('ETAPA OBRA'!N:N,MATCH($B40,'ETAPA OBRA'!$B:$B,0))="x",'ETAPA OBRA'!N$1&", ","")& IF(INDEX('ETAPA OBRA'!O:O,MATCH($B40,'ETAPA OBRA'!$B:$B,0))="x",'ETAPA OBRA'!O$1&", ","")& IF(INDEX('ETAPA OBRA'!P:P,MATCH($B40,'ETAPA OBRA'!$B:$B,0))="x",'ETAPA OBRA'!P$1&", ","")& IF(INDEX('ETAPA OBRA'!Q:Q,MATCH($B40,'ETAPA OBRA'!$B:$B,0))="x",'ETAPA OBRA'!Q$1&", ","")& IF(INDEX('ETAPA OBRA'!R:R,MATCH($B40,'ETAPA OBRA'!$B:$B,0))="x",'ETAPA OBRA'!R$1&", ","")& IF(INDEX('ETAPA OBRA'!S:S,MATCH($B40,'ETAPA OBRA'!$B:$B,0))="x",'ETAPA OBRA'!S$1&", ","")& IF(INDEX('ETAPA OBRA'!T:T,MATCH($B40,'ETAPA OBRA'!$B:$B,0))="x",'ETAPA OBRA'!T$1&", ","")& IF(INDEX('ETAPA OBRA'!U:U,MATCH($B40,'ETAPA OBRA'!$B:$B,0))="x",'ETAPA OBRA'!U$1&", ","") )-2),"") -> Finalizado | N40: =IF(M40="","Não iniciada", IF(ISNUMBER(FIND("Cancelada",M40)),"Cancelada", IF(ISNUMBER(FIND("Paralisada",M40)),"Paralisada", IF(ISNUMBER(FIND("Finalizado",M40)),"Finalizado", "Em andamento")))) -> Finalizado | O40: 39109.17 | P40: =SUM($J40:$L40) -> 17500 | Q40: =O40-P40 -> 21609.17 | R40: =IF(O40=0,0,Q40/O40) -> 0.55253461 | S40: =IF(R40>=0.2,"✅ OK - Fechar Parceiro","⚠️ Ajustar Custos (<20%)") -> ✅ OK - Fechar Parceiro | T40: =Cronograma[[#This Row],[STATUS]] -> ✅ CONCLUÍDO
A41: BR88222-A | B41: =IF(A41<>"","contel-"&TEXT(COUNTA($A$2:A41),"00"),"") -> contel-40 | C41: SBA | D41: MANAUS | E41: AM | F41: https://maps.app.goo.gl/N1wQuUwkLKh5rKzy5 | G41: 1744 | H41: 15956 | I41: DANILO | J41: =SUM(EQUIPE!C41,EQUIPE!E41,EQUIPE!G41,EQUIPE!I41,EQUIPE!K41,EQUIPE!M41,EQUIPE!O41) -> 7000 | K41: 384.22 | L41: 182.42 | M41: =IFERROR(LEFT( IF(INDEX('ETAPA OBRA'!C:C,MATCH($B41,'ETAPA OBRA'!$B:$B,0))="x",'ETAPA OBRA'!C$1&", ","")& IF(INDEX('ETAPA OBRA'!D:D,MATCH($B41,'ETAPA OBRA'!$B:$B,0))="x",'ETAPA OBRA'!D$1&", ","")& IF(INDEX('ETAPA OBRA'!F:F,MATCH($B41,'ETAPA OBRA'!$B:$B,0))="x",'ETAPA OBRA'!F$1&", ","")& IF(INDEX('ETAPA OBRA'!G:G,MATCH($B41,'ETAPA OBRA'!$B:$B,0))="x",'ETAPA OBRA'!G$1&", ","")& IF(INDEX('ETAPA OBRA'!H:H,MATCH($B41,'ETAPA OBRA'!$B:$B,0))="x",'ETAPA OBRA'!H$1&", ","")& IF(INDEX('ETAPA OBRA'!I:I,MATCH($B41,'ETAPA OBRA'!$B:$B,0))="x",'ETAPA OBRA'!I$1&", ","")& IF(INDEX('ETAPA OBRA'!J:J,MATCH($B41,'ETAPA OBRA'!$B:$B,0))="x",'ETAPA OBRA'!J$1&", ","")& IF(INDEX('ETAPA OBRA'!K:K,MATCH($B41,'ETAPA OBRA'!$B:$B,0))="x",'ETAPA OBRA'!K$1&", ","")& IF(INDEX('ETAPA OBRA'!L:L,MATCH($B41,'ETAPA OBRA'!$B:$B,0))="x",'ETAPA OBRA'!L$1&", ","")& IF(INDEX('ETAPA OBRA'!M:M,MATCH($B41,'ETAPA OBRA'!$B:$B,0))="x",'ETAPA OBRA'!M$1&", ","")& IF(INDEX('ETAPA OBRA'!N:N,MATCH($B41,'ETAPA OBRA'!$B:$B,0))="x",'ETAPA OBRA'!N$1&", ","")& IF(INDEX('ETAPA OBRA'!O:O,MATCH($B41,'ETAPA OBRA'!$B:$B,0))="x",'ETAPA OBRA'!O$1&", ","")& IF(INDEX('ETAPA OBRA'!P:P,MATCH($B41,'ETAPA OBRA'!$B:$B,0))="x",'ETAPA OBRA'!P$1&", ","")& IF(INDEX('ETAPA OBRA'!Q:Q,MATCH($B41,'ETAPA OBRA'!$B:$B,0))="x",'ETAPA OBRA'!Q$1&", ","")& IF(INDEX('ETAPA OBRA'!R:R,MATCH($B41,'ETAPA OBRA'!$B:$B,0))="x",'ETAPA OBRA'!R$1&", ","")& IF(INDEX('ETAPA OBRA'!S:S,MATCH($B41,'ETAPA OBRA'!$B:$B,0))="x",'ETAPA OBRA'!S$1&", ","")& IF(INDEX('ETAPA OBRA'!T:T,MATCH($B41,'ETAPA OBRA'!$B:$B,0))="x",'ETAPA OBRA'!T$1&", ","")& IF(INDEX('ETAPA OBRA'!U:U,MATCH($B41,'ETAPA OBRA'!$B:$B,0))="x",'ETAPA OBRA'!U$1&", ",""),LEN( IF(INDEX('ETAPA OBRA'!C:C,MATCH($B41,'ETAPA OBRA'!$B:$B,0))="x",'ETAPA OBRA'!C$1&", ","")& IF(INDEX('ETAPA OBRA'!D:D,MATCH($B41,'ETAPA OBRA'!$B:$B,0))="x",'ETAPA OBRA'!D$1&", ","")& IF(INDEX('ETAPA OBRA'!F:F,MATCH($B41,'ETAPA OBRA'!$B:$B,0))="x",'ETAPA OBRA'!F$1&", ","")& IF(INDEX('ETAPA OBRA'!G:G,MATCH($B41,'ETAPA OBRA'!$B:$B,0))="x",'ETAPA OBRA'!G$1&", ","")& IF(INDEX('ETAPA OBRA'!H:H,MATCH($B41,'ETAPA OBRA'!$B:$B,0))="x",'ETAPA OBRA'!H$1&", ","")& IF(INDEX('ETAPA OBRA'!I:I,MATCH($B41,'ETAPA OBRA'!$B:$B,0))="x",'ETAPA OBRA'!I$1&", ","")& IF(INDEX('ETAPA OBRA'!J:J,MATCH($B41,'ETAPA OBRA'!$B:$B,0))="x",'ETAPA OBRA'!J$1&", ","")& IF(INDEX('ETAPA OBRA'!K:K,MATCH($B41,'ETAPA OBRA'!$B:$B,0))="x",'ETAPA OBRA'!K$1&", ","")& IF(INDEX('ETAPA OBRA'!L:L,MATCH($B41,'ETAPA OBRA'!$B:$B,0))="x",'ETAPA OBRA'!L$1&", ","")& IF(INDEX('ETAPA OBRA'!M:M,MATCH($B41,'ETAPA OBRA'!$B:$B,0))="x",'ETAPA OBRA'!M$1&", ","")& IF(INDEX('ETAPA OBRA'!N:N,MATCH($B41,'ETAPA OBRA'!$B:$B,0))="x",'ETAPA OBRA'!N$1&", ","")& IF(INDEX('ETAPA OBRA'!O:O,MATCH($B41,'ETAPA OBRA'!$B:$B,0))="x",'ETAPA OBRA'!O$1&", ","")& IF(INDEX('ETAPA OBRA'!P:P,MATCH($B41,'ETAPA OBRA'!$B:$B,0))="x",'ETAPA OBRA'!P$1&", ","")& IF(INDEX('ETAPA OBRA'!Q:Q,MATCH($B41,'ETAPA OBRA'!$B:$B,0))="x",'ETAPA OBRA'!Q$1&", ","")& IF(INDEX('ETAPA OBRA'!R:R,MATCH($B41,'ETAPA OBRA'!$B:$B,0))="x",'ETAPA OBRA'!R$1&", ","")& IF(INDEX('ETAPA OBRA'!S:S,MATCH($B41,'ETAPA OBRA'!$B:$B,0))="x",'ETAPA OBRA'!S$1&", ","")& IF(INDEX('ETAPA OBRA'!T:T,MATCH($B41,'ETAPA OBRA'!$B:$B,0))="x",'ETAPA OBRA'!T$1&", ","")& IF(INDEX('ETAPA OBRA'!U:U,MATCH($B41,'ETAPA OBRA'!$B:$B,0))="x",'ETAPA OBRA'!U$1&", ","") )-2),"") -> Finalizado | N41: =IF(M41="","Não iniciada", IF(ISNUMBER(FIND("Cancelada",M41)),"Cancelada", IF(ISNUMBER(FIND("Paralisada",M41)),"Paralisada", IF(ISNUMBER(FIND("Finalizado",M41)),"Finalizado", "Em andamento")))) -> Finalizado | O41: 22240.32 | P41: =SUM($J41:$L41) -> 7566.64 | Q41: =O41-P41 -> 14673.68 | R41: =IF(O41=0,0,Q41/O41) -> 0.65977828 | S41: =IF(R41>=0.2,"✅ OK - Fechar Parceiro","⚠️ Ajustar Custos (<20%)") -> ✅ OK - Fechar Parceiro | T41: =Cronograma[[#This Row],[STATUS]] -> ✅ CONCLUÍDO
A42: TNSIMMU0001 | B42: =IF(A42<>"","contel-"&TEXT(COUNTA($A$2:A42),"00"),"") -> contel-41 | C42: TBSA | D42: MOMBUCA | E42: SP | F42: https://maps.app.goo.gl/XbAM1sR9FwVJQKhz9 | G42: 1745 | H42: 15969 | I42: DANIEL | J42: =SUM(EQUIPE!C42,EQUIPE!E42,EQUIPE!G42,EQUIPE!I42,EQUIPE!K42,EQUIPE!M42,EQUIPE!O42) -> 16000 | K42: 0 | L42: 421.47 | M42: =IFERROR(LEFT( IF(INDEX('ETAPA OBRA'!C:C,MATCH($B42,'ETAPA OBRA'!$B:$B,0))="x",'ETAPA OBRA'!C$1&", ","")& IF(INDEX('ETAPA OBRA'!D:D,MATCH($B42,'ETAPA OBRA'!$B:$B,0))="x",'ETAPA OBRA'!D$1&", ","")& IF(INDEX('ETAPA OBRA'!F:F,MATCH($B42,'ETAPA OBRA'!$B:$B,0))="x",'ETAPA OBRA'!F$1&", ","")& IF(INDEX('ETAPA OBRA'!G:G,MATCH($B42,'ETAPA OBRA'!$B:$B,0))="x",'ETAPA OBRA'!G$1&", ","")& IF(INDEX('ETAPA OBRA'!H:H,MATCH($B42,'ETAPA OBRA'!$B:$B,0))="x",'ETAPA OBRA'!H$1&", ","")& IF(INDEX('ETAPA OBRA'!I:I,MATCH($B42,'ETAPA OBRA'!$B:$B,0))="x",'ETAPA OBRA'!I$1&", ","")& IF(INDEX('ETAPA OBRA'!J:J,MATCH($B42,'ETAPA OBRA'!$B:$B,0))="x",'ETAPA OBRA'!J$1&", ","")& IF(INDEX('ETAPA OBRA'!K:K,MATCH($B42,'ETAPA OBRA'!$B:$B,0))="x",'ETAPA OBRA'!K$1&", ","")& IF(INDEX('ETAPA OBRA'!L:L,MATCH($B42,'ETAPA OBRA'!$B:$B,0))="x",'ETAPA OBRA'!L$1&", ","")& IF(INDEX('ETAPA OBRA'!M:M,MATCH($B42,'ETAPA OBRA'!$B:$B,0))="x",'ETAPA OBRA'!M$1&", ","")& IF(INDEX('ETAPA OBRA'!N:N,MATCH($B42,'ETAPA OBRA'!$B:$B,0))="x",'ETAPA OBRA'!N$1&", ","")& IF(INDEX('ETAPA OBRA'!O:O,MATCH($B42,'ETAPA OBRA'!$B:$B,0))="x",'ETAPA OBRA'!O$1&", ","")& IF(INDEX('ETAPA OBRA'!P:P,MATCH($B42,'ETAPA OBRA'!$B:$B,0))="x",'ETAPA OBRA'!P$1&", ","")& IF(INDEX('ETAPA OBRA'!Q:Q,MATCH($B42,'ETAPA OBRA'!$B:$B,0))="x",'ETAPA OBRA'!Q$1&", ","")& IF(INDEX('ETAPA OBRA'!R:R,MATCH($B42,'ETAPA OBRA'!$B:$B,0))="x",'ETAPA OBRA'!R$1&", ","")& IF(INDEX('ETAPA OBRA'!S:S,MATCH($B42,'ETAPA OBRA'!$B:$B,0))="x",'ETAPA OBRA'!S$1&", ","")& IF(INDEX('ETAPA OBRA'!T:T,MATCH($B42,'ETAPA OBRA'!$B:$B,0))="x",'ETAPA OBRA'!T$1&", ","")& IF(INDEX('ETAPA OBRA'!U:U,MATCH($B42,'ETAPA OBRA'!$B:$B,0))="x",'ETAPA OBRA'!U$1&", ",""),LEN( IF(INDEX('ETAPA OBRA'!C:C,MATCH($B42,'ETAPA OBRA'!$B:$B,0))="x",'ETAPA OBRA'!C$1&", ","")& IF(INDEX('ETAPA OBRA'!D:D,MATCH($B42,'ETAPA OBRA'!$B:$B,0))="x",'ETAPA OBRA'!D$1&", ","")& IF(INDEX('ETAPA OBRA'!F:F,MATCH($B42,'ETAPA OBRA'!$B:$B,0))="x",'ETAPA OBRA'!F$1&", ","")& IF(INDEX('ETAPA OBRA'!G:G,MATCH($B42,'ETAPA OBRA'!$B:$B,0))="x",'ETAPA OBRA'!G$1&", ","")& IF(INDEX('ETAPA OBRA'!H:H,MATCH($B42,'ETAPA OBRA'!$B:$B,0))="x",'ETAPA OBRA'!H$1&", ","")& IF(INDEX('ETAPA OBRA'!I:I,MATCH($B42,'ETAPA OBRA'!$B:$B,0))="x",'ETAPA OBRA'!I$1&", ","")& IF(INDEX('ETAPA OBRA'!J:J,MATCH($B42,'ETAPA OBRA'!$B:$B,0))="x",'ETAPA OBRA'!J$1&", ","")& IF(INDEX('ETAPA OBRA'!K:K,MATCH($B42,'ETAPA OBRA'!$B:$B,0))="x",'ETAPA OBRA'!K$1&", ","")& IF(INDEX('ETAPA OBRA'!L:L,MATCH($B42,'ETAPA OBRA'!$B:$B,0))="x",'ETAPA OBRA'!L$1&", ","")& IF(INDEX('ETAPA OBRA'!M:M,MATCH($B42,'ETAPA OBRA'!$B:$B,0))="x",'ETAPA OBRA'!M$1&", ","")& IF(INDEX('ETAPA OBRA'!N:N,MATCH($B42,'ETAPA OBRA'!$B:$B,0))="x",'ETAPA OBRA'!N$1&", ","")& IF(INDEX('ETAPA OBRA'!O:O,MATCH($B42,'ETAPA OBRA'!$B:$B,0))="x",'ETAPA OBRA'!O$1&", ","")& IF(INDEX('ETAPA OBRA'!P:P,MATCH($B42,'ETAPA OBRA'!$B:$B,0))="x",'ETAPA OBRA'!P$1&", ","")& IF(INDEX('ETAPA OBRA'!Q:Q,MATCH($B42,'ETAPA OBRA'!$B:$B,0))="x",'ETAPA OBRA'!Q$1&", ","")& IF(INDEX('ETAPA OBRA'!R:R,MATCH($B42,'ETAPA OBRA'!$B:$B,0))="x",'ETAPA OBRA'!R$1&", ","")& IF(INDEX('ETAPA OBRA'!S:S,MATCH($B42,'ETAPA OBRA'!$B:$B,0))="x",'ETAPA OBRA'!S$1&", ","")& IF(INDEX('ETAPA OBRA'!T:T,MATCH($B42,'ETAPA OBRA'!$B:$B,0))="x",'ETAPA OBRA'!T$1&", ","")& IF(INDEX('ETAPA OBRA'!U:U,MATCH($B42,'ETAPA OBRA'!$B:$B,0))="x",'ETAPA OBRA'!U$1&", ","") )-2),"") -> Finalizado | N42: =IF(M42="","Não iniciada", IF(ISNUMBER(FIND("Cancelada",M42)),"Cancelada", IF(ISNUMBER(FIND("Paralisada",M42)),"Paralisada", IF(ISNUMBER(FIND("Finalizado",M42)),"Finalizado", "Em andamento")))) -> Finalizado | O42: 26212.4 | P42: =SUM($J42:$L42) -> 16421.47 | Q42: =O42-P42 -> 9790.93 | R42: =IF(O42=0,0,Q42/O42) -> 0.37352284 | S42: =IF(R42>=0.2,"✅ OK - Fechar Parceiro","⚠️ Ajustar Custos (<20%)") -> ✅ OK - Fechar Parceiro | T42: =Cronograma[[#This Row],[STATUS]] -> ✅ CONCLUÍDO
A43: BR75987-A | B43: =IF(A43<>"","contel-"&TEXT(COUNTA($A$2:A43),"00"),"") -> contel-42 | C43: SBA | D43: LOUVEIRA | E43: SP | F43: https://maps.app.goo.gl/YAEePw8DBaigcEbi7 | G43: 1749 | H43: 16079 | I43: PEDRO | J43: =SUM(EQUIPE!C43,EQUIPE!E43,EQUIPE!G43,EQUIPE!I43,EQUIPE!K43,EQUIPE!M43,EQUIPE!O43) -> 9100 | K43: 5494.36 | L43: 3138.76 | M43: =IFERROR(LEFT( IF(INDEX('ETAPA OBRA'!C:C,MATCH($B43,'ETAPA OBRA'!$B:$B,0))="x",'ETAPA OBRA'!C$1&", ","")& IF(INDEX('ETAPA OBRA'!D:D,MATCH($B43,'ETAPA OBRA'!$B:$B,0))="x",'ETAPA OBRA'!D$1&", ","")& IF(INDEX('ETAPA OBRA'!F:F,MATCH($B43,'ETAPA OBRA'!$B:$B,0))="x",'ETAPA OBRA'!F$1&", ","")& IF(INDEX('ETAPA OBRA'!G:G,MATCH($B43,'ETAPA OBRA'!$B:$B,0))="x",'ETAPA OBRA'!G$1&", ","")& IF(INDEX('ETAPA OBRA'!H:H,MATCH($B43,'ETAPA OBRA'!$B:$B,0))="x",'ETAPA OBRA'!H$1&", ","")& IF(INDEX('ETAPA OBRA'!I:I,MATCH($B43,'ETAPA OBRA'!$B:$B,0))="x",'ETAPA OBRA'!I$1&", ","")& IF(INDEX('ETAPA OBRA'!J:J,MATCH($B43,'ETAPA OBRA'!$B:$B,0))="x",'ETAPA OBRA'!J$1&", ","")& IF(INDEX('ETAPA OBRA'!K:K,MATCH($B43,'ETAPA OBRA'!$B:$B,0))="x",'ETAPA OBRA'!K$1&", ","")& IF(INDEX('ETAPA OBRA'!L:L,MATCH($B43,'ETAPA OBRA'!$B:$B,0))="x",'ETAPA OBRA'!L$1&", ","")& IF(INDEX('ETAPA OBRA'!M:M,MATCH($B43,'ETAPA OBRA'!$B:$B,0))="x",'ETAPA OBRA'!M$1&", ","")& IF(INDEX('ETAPA OBRA'!N:N,MATCH($B43,'ETAPA OBRA'!$B:$B,0))="x",'ETAPA OBRA'!N$1&", ","")& IF(INDEX('ETAPA OBRA'!O:O,MATCH($B43,'ETAPA OBRA'!$B:$B,0))="x",'ETAPA OBRA'!O$1&", ","")& IF(INDEX('ETAPA OBRA'!P:P,MATCH($B43,'ETAPA OBRA'!$B:$B,0))="x",'ETAPA OBRA'!P$1&", ","")& IF(INDEX('ETAPA OBRA'!Q:Q,MATCH($B43,'ETAPA OBRA'!$B:$B,0))="x",'ETAPA OBRA'!Q$1&", ","")& IF(INDEX('ETAPA OBRA'!R:R,MATCH($B43,'ETAPA OBRA'!$B:$B,0))="x",'ETAPA OBRA'!R$1&", ","")& IF(INDEX('ETAPA OBRA'!S:S,MATCH($B43,'ETAPA OBRA'!$B:$B,0))="x",'ETAPA OBRA'!S$1&", ","")& IF(INDEX('ETAPA OBRA'!T:T,MATCH($B43,'ETAPA OBRA'!$B:$B,0))="x",'ETAPA OBRA'!T$1&", ","")& IF(INDEX('ETAPA OBRA'!U:U,MATCH($B43,'ETAPA OBRA'!$B:$B,0))="x",'ETAPA OBRA'!U$1&", ",""),LEN( IF(INDEX('ETAPA OBRA'!C:C,MATCH($B43,'ETAPA OBRA'!$B:$B,0))="x",'ETAPA OBRA'!C$1&", ","")& IF(INDEX('ETAPA OBRA'!D:D,MATCH($B43,'ETAPA OBRA'!$B:$B,0))="x",'ETAPA OBRA'!D$1&", ","")& IF(INDEX('ETAPA OBRA'!F:F,MATCH($B43,'ETAPA OBRA'!$B:$B,0))="x",'ETAPA OBRA'!F$1&", ","")& IF(INDEX('ETAPA OBRA'!G:G,MATCH($B43,'ETAPA OBRA'!$B:$B,0))="x",'ETAPA OBRA'!G$1&", ","")& IF(INDEX('ETAPA OBRA'!H:H,MATCH($B43,'ETAPA OBRA'!$B:$B,0))="x",'ETAPA OBRA'!H$1&", ","")& IF(INDEX('ETAPA OBRA'!I:I,MATCH($B43,'ETAPA OBRA'!$B:$B,0))="x",'ETAPA OBRA'!I$1&", ","")& IF(INDEX('ETAPA OBRA'!J:J,MATCH($B43,'ETAPA OBRA'!$B:$B,0))="x",'ETAPA OBRA'!J$1&", ","")& IF(INDEX('ETAPA OBRA'!K:K,MATCH($B43,'ETAPA OBRA'!$B:$B,0))="x",'ETAPA OBRA'!K$1&", ","")& IF(INDEX('ETAPA OBRA'!L:L,MATCH($B43,'ETAPA OBRA'!$B:$B,0))="x",'ETAPA OBRA'!L$1&", ","")& IF(INDEX('ETAPA OBRA'!M:M,MATCH($B43,'ETAPA OBRA'!$B:$B,0))="x",'ETAPA OBRA'!M$1&", ","")& IF(INDEX('ETAPA OBRA'!N:N,MATCH($B43,'ETAPA OBRA'!$B:$B,0))="x",'ETAPA OBRA'!N$1&", ","")& IF(INDEX('ETAPA OBRA'!O:O,MATCH($B43,'ETAPA OBRA'!$B:$B,0))="x",'ETAPA OBRA'!O$1&", ","")& IF(INDEX('ETAPA OBRA'!P:P,MATCH($B43,'ETAPA OBRA'!$B:$B,0))="x",'ETAPA OBRA'!P$1&", ","")& IF(INDEX('ETAPA OBRA'!Q:Q,MATCH($B43,'ETAPA OBRA'!$B:$B,0))="x",'ETAPA OBRA'!Q$1&", ","")& IF(INDEX('ETAPA OBRA'!R:R,MATCH($B43,'ETAPA OBRA'!$B:$B,0))="x",'ETAPA OBRA'!R$1&", ","")& IF(INDEX('ETAPA OBRA'!S:S,MATCH($B43,'ETAPA OBRA'!$B:$B,0))="x",'ETAPA OBRA'!S$1&", ","")& IF(INDEX('ETAPA OBRA'!T:T,MATCH($B43,'ETAPA OBRA'!$B:$B,0))="x",'ETAPA OBRA'!T$1&", ","")& IF(INDEX('ETAPA OBRA'!U:U,MATCH($B43,'ETAPA OBRA'!$B:$B,0))="x",'ETAPA OBRA'!U$1&", ","") )-2),"") -> Finalizado | N43: =IF(M43="","Não iniciada", IF(ISNUMBER(FIND("Cancelada",M43)),"Cancelada", IF(ISNUMBER(FIND("Paralisada",M43)),"Paralisada", IF(ISNUMBER(FIND("Finalizado",M43)),"Finalizado", "Em andamento")))) -> Finalizado | O43: 24000 | P43: =SUM($J43:$L43) -> 17733.12 | Q43: =O43-P43 -> 6266.88 | R43: =IF(O43=0,0,Q43/O43) -> 0.26112 | S43: =IF(R43>=0.2,"✅ OK - Fechar Parceiro","⚠️ Ajustar Custos (<20%)") -> ✅ OK - Fechar Parceiro | T43: =Cronograma[[#This Row],[STATUS]] -> ✅ CONCLUÍDO
A44: BR67096-R | B44: =IF(A44<>"","contel-"&TEXT(COUNTA($A$2:A44),"00"),"") -> contel-43 | C44: SBA | D44: BRASILIA | E44: DF | F44: https://maps.app.goo.gl/GQsw2YcvcTF9vCbU9 | G44: 1750 | H44: 26516 | I44: PEDRO | J44: =SUM(EQUIPE!C44,EQUIPE!E44,EQUIPE!G44,EQUIPE!I44,EQUIPE!K44,EQUIPE!M44,EQUIPE!O44) -> 4300 | K44: 603.87 | L44: 356.38 | M44: =IFERROR(LEFT( IF(INDEX('ETAPA OBRA'!C:C,MATCH($B44,'ETAPA OBRA'!$B:$B,0))="x",'ETAPA OBRA'!C$1&", ","")& IF(INDEX('ETAPA OBRA'!D:D,MATCH($B44,'ETAPA OBRA'!$B:$B,0))="x",'ETAPA OBRA'!D$1&", ","")& IF(INDEX('ETAPA OBRA'!F:F,MATCH($B44,'ETAPA OBRA'!$B:$B,0))="x",'ETAPA OBRA'!F$1&", ","")& IF(INDEX('ETAPA OBRA'!G:G,MATCH($B44,'ETAPA OBRA'!$B:$B,0))="x",'ETAPA OBRA'!G$1&", ","")& IF(INDEX('ETAPA OBRA'!H:H,MATCH($B44,'ETAPA OBRA'!$B:$B,0))="x",'ETAPA OBRA'!H$1&", ","")& IF(INDEX('ETAPA OBRA'!I:I,MATCH($B44,'ETAPA OBRA'!$B:$B,0))="x",'ETAPA OBRA'!I$1&", ","")& IF(INDEX('ETAPA OBRA'!J:J,MATCH($B44,'ETAPA OBRA'!$B:$B,0))="x",'ETAPA OBRA'!J$1&", ","")& IF(INDEX('ETAPA OBRA'!K:K,MATCH($B44,'ETAPA OBRA'!$B:$B,0))="x",'ETAPA OBRA'!K$1&", ","")& IF(INDEX('ETAPA OBRA'!L:L,MATCH($B44,'ETAPA OBRA'!$B:$B,0))="x",'ETAPA OBRA'!L$1&", ","")& IF(INDEX('ETAPA OBRA'!M:M,MATCH($B44,'ETAPA OBRA'!$B:$B,0))="x",'ETAPA OBRA'!M$1&", ","")& IF(INDEX('ETAPA OBRA'!N:N,MATCH($B44,'ETAPA OBRA'!$B:$B,0))="x",'ETAPA OBRA'!N$1&", ","")& IF(INDEX('ETAPA OBRA'!O:O,MATCH($B44,'ETAPA OBRA'!$B:$B,0))="x",'ETAPA OBRA'!O$1&", ","")& IF(INDEX('ETAPA OBRA'!P:P,MATCH($B44,'ETAPA OBRA'!$B:$B,0))="x",'ETAPA OBRA'!P$1&", ","")& IF(INDEX('ETAPA OBRA'!Q:Q,MATCH($B44,'ETAPA OBRA'!$B:$B,0))="x",'ETAPA OBRA'!Q$1&", ","")& IF(INDEX('ETAPA OBRA'!R:R,MATCH($B44,'ETAPA OBRA'!$B:$B,0))="x",'ETAPA OBRA'!R$1&", ","")& IF(INDEX('ETAPA OBRA'!S:S,MATCH($B44,'ETAPA OBRA'!$B:$B,0))="x",'ETAPA OBRA'!S$1&", ","")& IF(INDEX('ETAPA OBRA'!T:T,MATCH($B44,'ETAPA OBRA'!$B:$B,0))="x",'ETAPA OBRA'!T$1&", ","")& IF(INDEX('ETAPA OBRA'!U:U,MATCH($B44,'ETAPA OBRA'!$B:$B,0))="x",'ETAPA OBRA'!U$1&", ",""),LEN( IF(INDEX('ETAPA OBRA'!C:C,MATCH($B44,'ETAPA OBRA'!$B:$B,0))="x",'ETAPA OBRA'!C$1&", ","")& IF(INDEX('ETAPA OBRA'!D:D,MATCH($B44,'ETAPA OBRA'!$B:$B,0))="x",'ETAPA OBRA'!D$1&", ","")& IF(INDEX('ETAPA OBRA'!F:F,MATCH($B44,'ETAPA OBRA'!$B:$B,0))="x",'ETAPA OBRA'!F$1&", ","")& IF(INDEX('ETAPA OBRA'!G:G,MATCH($B44,'ETAPA OBRA'!$B:$B,0))="x",'ETAPA OBRA'!G$1&", ","")& IF(INDEX('ETAPA OBRA'!H:H,MATCH($B44,'ETAPA OBRA'!$B:$B,0))="x",'ETAPA OBRA'!H$1&", ","")& IF(INDEX('ETAPA OBRA'!I:I,MATCH($B44,'ETAPA OBRA'!$B:$B,0))="x",'ETAPA OBRA'!I$1&", ","")& IF(INDEX('ETAPA OBRA'!J:J,MATCH($B44,'ETAPA OBRA'!$B:$B,0))="x",'ETAPA OBRA'!J$1&", ","")& IF(INDEX('ETAPA OBRA'!K:K,MATCH($B44,'ETAPA OBRA'!$B:$B,0))="x",'ETAPA OBRA'!K$1&", ","")& IF(INDEX('ETAPA OBRA'!L:L,MATCH($B44,'ETAPA OBRA'!$B:$B,0))="x",'ETAPA OBRA'!L$1&", ","")& IF(INDEX('ETAPA OBRA'!M:M,MATCH($B44,'ETAPA OBRA'!$B:$B,0))="x",'ETAPA OBRA'!M$1&", ","")& IF(INDEX('ETAPA OBRA'!N:N,MATCH($B44,'ETAPA OBRA'!$B:$B,0))="x",'ETAPA OBRA'!N$1&", ","")& IF(INDEX('ETAPA OBRA'!O:O,MATCH($B44,'ETAPA OBRA'!$B:$B,0))="x",'ETAPA OBRA'!O$1&", ","")& IF(INDEX('ETAPA OBRA'!P:P,MATCH($B44,'ETAPA OBRA'!$B:$B,0))="x",'ETAPA OBRA'!P$1&", ","")& IF(INDEX('ETAPA OBRA'!Q:Q,MATCH($B44,'ETAPA OBRA'!$B:$B,0))="x",'ETAPA OBRA'!Q$1&", ","")& IF(INDEX('ETAPA OBRA'!R:R,MATCH($B44,'ETAPA OBRA'!$B:$B,0))="x",'ETAPA OBRA'!R$1&", ","")& IF(INDEX('ETAPA OBRA'!S:S,MATCH($B44,'ETAPA OBRA'!$B:$B,0))="x",'ETAPA OBRA'!S$1&", ","")& IF(INDEX('ETAPA OBRA'!T:T,MATCH($B44,'ETAPA OBRA'!$B:$B,0))="x",'ETAPA OBRA'!T$1&", ","")& IF(INDEX('ETAPA OBRA'!U:U,MATCH($B44,'ETAPA OBRA'!$B:$B,0))="x",'ETAPA OBRA'!U$1&", ","") )-2),"") -> Finalizado | N44: =IF(M44="","Não iniciada", IF(ISNUMBER(FIND("Cancelada",M44)),"Cancelada", IF(ISNUMBER(FIND("Paralisada",M44)),"Paralisada", IF(ISNUMBER(FIND("Finalizado",M44)),"Finalizado", "Em andamento")))) -> Finalizado | O44: 14800 | P44: =SUM($J44:$L44) -> 5260.25 | Q44: =O44-P44 -> 9539.75 | R44: =IF(O44=0,0,Q44/O44) -> 0.6445777 | S44: =IF(R44>=0.2,"✅ OK - Fechar Parceiro","⚠️ Ajustar Custos (<20%)") -> ✅ OK - Fechar Parceiro | T44: =Cronograma[[#This Row],[STATUS]] -> ✅ CONCLUÍDO
A45: BR66977-R | B45: =IF(A45<>"","contel-"&TEXT(COUNTA($A$2:A45),"00"),"") -> contel-44 | C45: SBA | D45: BRASILIA | E45: DF | F45: https://maps.app.goo.gl/Kn7DSsa6VLknYCGs5 | G45: 1751 | H45: 16050 | I45: HENRIQUE | J45: =SUM(EQUIPE!C45,EQUIPE!E45,EQUIPE!G45,EQUIPE!I45,EQUIPE!K45,EQUIPE!M45,EQUIPE!O45) -> 1500 | K45: 6000 | L45: 271.47 | M45: =IFERROR(LEFT( IF(INDEX('ETAPA OBRA'!C:C,MATCH($B45,'ETAPA OBRA'!$B:$B,0))="x",'ETAPA OBRA'!C$1&", ","")& IF(INDEX('ETAPA OBRA'!D:D,MATCH($B45,'ETAPA OBRA'!$B:$B,0))="x",'ETAPA OBRA'!D$1&", ","")& IF(INDEX('ETAPA OBRA'!F:F,MATCH($B45,'ETAPA OBRA'!$B:$B,0))="x",'ETAPA OBRA'!F$1&", ","")& IF(INDEX('ETAPA OBRA'!G:G,MATCH($B45,'ETAPA OBRA'!$B:$B,0))="x",'ETAPA OBRA'!G$1&", ","")& IF(INDEX('ETAPA OBRA'!H:H,MATCH($B45,'ETAPA OBRA'!$B:$B,0))="x",'ETAPA OBRA'!H$1&", ","")& IF(INDEX('ETAPA OBRA'!I:I,MATCH($B45,'ETAPA OBRA'!$B:$B,0))="x",'ETAPA OBRA'!I$1&", ","")& IF(INDEX('ETAPA OBRA'!J:J,MATCH($B45,'ETAPA OBRA'!$B:$B,0))="x",'ETAPA OBRA'!J$1&", ","")& IF(INDEX('ETAPA OBRA'!K:K,MATCH($B45,'ETAPA OBRA'!$B:$B,0))="x",'ETAPA OBRA'!K$1&", ","")& IF(INDEX('ETAPA OBRA'!L:L,MATCH($B45,'ETAPA OBRA'!$B:$B,0))="x",'ETAPA OBRA'!L$1&", ","")& IF(INDEX('ETAPA OBRA'!M:M,MATCH($B45,'ETAPA OBRA'!$B:$B,0))="x",'ETAPA OBRA'!M$1&", ","")& IF(INDEX('ETAPA OBRA'!N:N,MATCH($B45,'ETAPA OBRA'!$B:$B,0))="x",'ETAPA OBRA'!N$1&", ","")& IF(INDEX('ETAPA OBRA'!O:O,MATCH($B45,'ETAPA OBRA'!$B:$B,0))="x",'ETAPA OBRA'!O$1&", ","")& IF(INDEX('ETAPA OBRA'!P:P,MATCH($B45,'ETAPA OBRA'!$B:$B,0))="x",'ETAPA OBRA'!P$1&", ","")& IF(INDEX('ETAPA OBRA'!Q:Q,MATCH($B45,'ETAPA OBRA'!$B:$B,0))="x",'ETAPA OBRA'!Q$1&", ","")& IF(INDEX('ETAPA OBRA'!R:R,MATCH($B45,'ETAPA OBRA'!$B:$B,0))="x",'ETAPA OBRA'!R$1&", ","")& IF(INDEX('ETAPA OBRA'!S:S,MATCH($B45,'ETAPA OBRA'!$B:$B,0))="x",'ETAPA OBRA'!S$1&", ","")& IF(INDEX('ETAPA OBRA'!T:T,MATCH($B45,'ETAPA OBRA'!$B:$B,0))="x",'ETAPA OBRA'!T$1&", ","")& IF(INDEX('ETAPA OBRA'!U:U,MATCH($B45,'ETAPA OBRA'!$B:$B,0))="x",'ETAPA OBRA'!U$1&", ",""),LEN( IF(INDEX('ETAPA OBRA'!C:C,MATCH($B45,'ETAPA OBRA'!$B:$B,0))="x",'ETAPA OBRA'!C$1&", ","")& IF(INDEX('ETAPA OBRA'!D:D,MATCH($B45,'ETAPA OBRA'!$B:$B,0))="x",'ETAPA OBRA'!D$1&", ","")& IF(INDEX('ETAPA OBRA'!F:F,MATCH($B45,'ETAPA OBRA'!$B:$B,0))="x",'ETAPA OBRA'!F$1&", ","")& IF(INDEX('ETAPA OBRA'!G:G,MATCH($B45,'ETAPA OBRA'!$B:$B,0))="x",'ETAPA OBRA'!G$1&", ","")& IF(INDEX('ETAPA OBRA'!H:H,MATCH($B45,'ETAPA OBRA'!$B:$B,0))="x",'ETAPA OBRA'!H$1&", ","")& IF(INDEX('ETAPA OBRA'!I:I,MATCH($B45,'ETAPA OBRA'!$B:$B,0))="x",'ETAPA OBRA'!I$1&", ","")& IF(INDEX('ETAPA OBRA'!J:J,MATCH($B45,'ETAPA OBRA'!$B:$B,0))="x",'ETAPA OBRA'!J$1&", ","")& IF(INDEX('ETAPA OBRA'!K:K,MATCH($B45,'ETAPA OBRA'!$B:$B,0))="x",'ETAPA OBRA'!K$1&", ","")& IF(INDEX('ETAPA OBRA'!L:L,MATCH($B45,'ETAPA OBRA'!$B:$B,0))="x",'ETAPA OBRA'!L$1&", ","")& IF(INDEX('ETAPA OBRA'!M:M,MATCH($B45,'ETAPA OBRA'!$B:$B,0))="x",'ETAPA OBRA'!M$1&", ","")& IF(INDEX('ETAPA OBRA'!N:N,MATCH($B45,'ETAPA OBRA'!$B:$B,0))="x",'ETAPA OBRA'!N$1&", ","")& IF(INDEX('ETAPA OBRA'!O:O,MATCH($B45,'ETAPA OBRA'!$B:$B,0))="x",'ETAPA OBRA'!O$1&", ","")& IF(INDEX('ETAPA OBRA'!P:P,MATCH($B45,'ETAPA OBRA'!$B:$B,0))="x",'ETAPA OBRA'!P$1&", ","")& IF(INDEX('ETAPA OBRA'!Q:Q,MATCH($B45,'ETAPA OBRA'!$B:$B,0))="x",'ETAPA OBRA'!Q$1&", ","")& IF(INDEX('ETAPA OBRA'!R:R,MATCH($B45,'ETAPA OBRA'!$B:$B,0))="x",'ETAPA OBRA'!R$1&", ","")& IF(INDEX('ETAPA OBRA'!S:S,MATCH($B45,'ETAPA OBRA'!$B:$B,0))="x",'ETAPA OBRA'!S$1&", ","")& IF(INDEX('ETAPA OBRA'!T:T,MATCH($B45,'ETAPA OBRA'!$B:$B,0))="x",'ETAPA OBRA'!T$1&", ","")& IF(INDEX('ETAPA OBRA'!U:U,MATCH($B45,'ETAPA OBRA'!$B:$B,0))="x",'ETAPA OBRA'!U$1&", ","") )-2),"") -> Finalizado | N45: =IF(M45="","Não iniciada", IF(ISNUMBER(FIND("Cancelada",M45)),"Cancelada", IF(ISNUMBER(FIND("Paralisada",M45)),"Paralisada", IF(ISNUMBER(FIND("Finalizado",M45)),"Finalizado", "Em andamento")))) -> Finalizado | O45: 31132.8 | P45: =SUM($J45:$L45) -> 7771.47 | Q45: =O45-P45 -> 23361.33 | R45: =IF(O45=0,0,Q45/O45) -> 0.75037677 | S45: =IF(R45>=0.2,"✅ OK - Fechar Parceiro","⚠️ Ajustar Custos (<20%)") -> ✅ OK - Fechar Parceiro | T45: =Cronograma[[#This Row],[STATUS]] -> ✅ CONCLUÍDO
A46: DFBSBBV010-K2 | B46: =IF(A46<>"","contel-"&TEXT(COUNTA($A$2:A46),"00"),"") -> contel-45 | C46: HLB | D46: BRASILIA | E46: DF | F46: https://maps.app.goo.gl/bVHR4YzBtG4xjtc59 | G46: 1752 | H46: 16080 | I46: HENRIQUE | J46: =SUM(EQUIPE!C46,EQUIPE!E46,EQUIPE!G46,EQUIPE!I46,EQUIPE!K46,EQUIPE!M46,EQUIPE!O46) -> 10000 | K46: 4152.28 | L46: 2386.95 | M46: =IFERROR(LEFT( IF(INDEX('ETAPA OBRA'!C:C,MATCH($B46,'ETAPA OBRA'!$B:$B,0))="x",'ETAPA OBRA'!C$1&", ","")& IF(INDEX('ETAPA OBRA'!D:D,MATCH($B46,'ETAPA OBRA'!$B:$B,0))="x",'ETAPA OBRA'!D$1&", ","")& IF(INDEX('ETAPA OBRA'!F:F,MATCH($B46,'ETAPA OBRA'!$B:$B,0))="x",'ETAPA OBRA'!F$1&", ","")& IF(INDEX('ETAPA OBRA'!G:G,MATCH($B46,'ETAPA OBRA'!$B:$B,0))="x",'ETAPA OBRA'!G$1&", ","")& IF(INDEX('ETAPA OBRA'!H:H,MATCH($B46,'ETAPA OBRA'!$B:$B,0))="x",'ETAPA OBRA'!H$1&", ","")& IF(INDEX('ETAPA OBRA'!I:I,MATCH($B46,'ETAPA OBRA'!$B:$B,0))="x",'ETAPA OBRA'!I$1&", ","")& IF(INDEX('ETAPA OBRA'!J:J,MATCH($B46,'ETAPA OBRA'!$B:$B,0))="x",'ETAPA OBRA'!J$1&", ","")& IF(INDEX('ETAPA OBRA'!K:K,MATCH($B46,'ETAPA OBRA'!$B:$B,0))="x",'ETAPA OBRA'!K$1&", ","")& IF(INDEX('ETAPA OBRA'!L:L,MATCH($B46,'ETAPA OBRA'!$B:$B,0))="x",'ETAPA OBRA'!L$1&", ","")& IF(INDEX('ETAPA OBRA'!M:M,MATCH($B46,'ETAPA OBRA'!$B:$B,0))="x",'ETAPA OBRA'!M$1&", ","")& IF(INDEX('ETAPA OBRA'!N:N,MATCH($B46,'ETAPA OBRA'!$B:$B,0))="x",'ETAPA OBRA'!N$1&", ","")& IF(INDEX('ETAPA OBRA'!O:O,MATCH($B46,'ETAPA OBRA'!$B:$B,0))="x",'ETAPA OBRA'!O$1&", ","")& IF(INDEX('ETAPA OBRA'!P:P,MATCH($B46,'ETAPA OBRA'!$B:$B,0))="x",'ETAPA OBRA'!P$1&", ","")& IF(INDEX('ETAPA OBRA'!Q:Q,MATCH($B46,'ETAPA OBRA'!$B:$B,0))="x",'ETAPA OBRA'!Q$1&", ","")& IF(INDEX('ETAPA OBRA'!R:R,MATCH($B46,'ETAPA OBRA'!$B:$B,0))="x",'ETAPA OBRA'!R$1&", ","")& IF(INDEX('ETAPA OBRA'!S:S,MATCH($B46,'ETAPA OBRA'!$B:$B,0))="x",'ETAPA OBRA'!S$1&", ","")& IF(INDEX('ETAPA OBRA'!T:T,MATCH($B46,'ETAPA OBRA'!$B:$B,0))="x",'ETAPA OBRA'!T$1&", ","")& IF(INDEX('ETAPA OBRA'!U:U,MATCH($B46,'ETAPA OBRA'!$B:$B,0))="x",'ETAPA OBRA'!U$1&", ",""),LEN( IF(INDEX('ETAPA OBRA'!C:C,MATCH($B46,'ETAPA OBRA'!$B:$B,0))="x",'ETAPA OBRA'!C$1&", ","")& IF(INDEX('ETAPA OBRA'!D:D,MATCH($B46,'ETAPA OBRA'!$B:$B,0))="x",'ETAPA OBRA'!D$1&", ","")& IF(INDEX('ETAPA OBRA'!F:F,MATCH($B46,'ETAPA OBRA'!$B:$B,0))="x",'ETAPA OBRA'!F$1&", ","")& IF(INDEX('ETAPA OBRA'!G:G,MATCH($B46,'ETAPA OBRA'!$B:$B,0))="x",'ETAPA OBRA'!G$1&", ","")& IF(INDEX('ETAPA OBRA'!H:H,MATCH($B46,'ETAPA OBRA'!$B:$B,0))="x",'ETAPA OBRA'!H$1&", ","")& IF(INDEX('ETAPA OBRA'!I:I,MATCH($B46,'ETAPA OBRA'!$B:$B,0))="x",'ETAPA OBRA'!I$1&", ","")& IF(INDEX('ETAPA OBRA'!J:J,MATCH($B46,'ETAPA OBRA'!$B:$B,0))="x",'ETAPA OBRA'!J$1&", ","")& IF(INDEX('ETAPA OBRA'!K:K,MATCH($B46,'ETAPA OBRA'!$B:$B,0))="x",'ETAPA OBRA'!K$1&", ","")& IF(INDEX('ETAPA OBRA'!L:L,MATCH($B46,'ETAPA OBRA'!$B:$B,0))="x",'ETAPA OBRA'!L$1&", ","")& IF(INDEX('ETAPA OBRA'!M:M,MATCH($B46,'ETAPA OBRA'!$B:$B,0))="x",'ETAPA OBRA'!M$1&", ","")& IF(INDEX('ETAPA OBRA'!N:N,MATCH($B46,'ETAPA OBRA'!$B:$B,0))="x",'ETAPA OBRA'!N$1&", ","")& IF(INDEX('ETAPA OBRA'!O:O,MATCH($B46,'ETAPA OBRA'!$B:$B,0))="x",'ETAPA OBRA'!O$1&", ","")& IF(INDEX('ETAPA OBRA'!P:P,MATCH($B46,'ETAPA OBRA'!$B:$B,0))="x",'ETAPA OBRA'!P$1&", ","")& IF(INDEX('ETAPA OBRA'!Q:Q,MATCH($B46,'ETAPA OBRA'!$B:$B,0))="x",'ETAPA OBRA'!Q$1&", ","")& IF(INDEX('ETAPA OBRA'!R:R,MATCH($B46,'ETAPA OBRA'!$B:$B,0))="x",'ETAPA OBRA'!R$1&", ","")& IF(INDEX('ETAPA OBRA'!S:S,MATCH($B46,'ETAPA OBRA'!$B:$B,0))="x",'ETAPA OBRA'!S$1&", ","")& IF(INDEX('ETAPA OBRA'!T:T,MATCH($B46,'ETAPA OBRA'!$B:$B,0))="x",'ETAPA OBRA'!T$1&", ","")& IF(INDEX('ETAPA OBRA'!U:U,MATCH($B46,'ETAPA OBRA'!$B:$B,0))="x",'ETAPA OBRA'!U$1&", ","") )-2),"") -> Finalizado | N46: =IF(M46="","Não iniciada", IF(ISNUMBER(FIND("Cancelada",M46)),"Cancelada", IF(ISNUMBER(FIND("Paralisada",M46)),"Paralisada", IF(ISNUMBER(FIND("Finalizado",M46)),"Finalizado", "Em andamento")))) -> Finalizado | O46: 25374.94 | P46: =SUM($J46:$L46) -> 16539.23 | Q46: =O46-P46 -> 8835.71 | R46: =IF(O46=0,0,Q46/O46) -> 0.34820614 | S46: =IF(R46>=0.2,"✅ OK - Fechar Parceiro","⚠️ Ajustar Custos (<20%)") -> ✅ OK - Fechar Parceiro | T46: =Cronograma[[#This Row],[STATUS]] -> ✅ CONCLUÍDO
A47: BR73340-R | B47: =IF(A47<>"","contel-"&TEXT(COUNTA($A$2:A47),"00"),"") -> contel-46 | C47: SBA | D47: JUIZ DE FORA | E47: MG | F47: https://maps.app.goo.gl/bVHR4YzBtG4xjtc59 | G47: 1754 | H47: 16104 | I47: DANILO | J47: =SUM(EQUIPE!C47,EQUIPE!E47,EQUIPE!G47,EQUIPE!I47,EQUIPE!K47,EQUIPE!M47,EQUIPE!O47) -> 1400 | K47: 849.39 | L47: 103.03 | M47: =IFERROR(LEFT( IF(INDEX('ETAPA OBRA'!C:C,MATCH($B47,'ETAPA OBRA'!$B:$B,0))="x",'ETAPA OBRA'!C$1&", ","")& IF(INDEX('ETAPA OBRA'!D:D,MATCH($B47,'ETAPA OBRA'!$B:$B,0))="x",'ETAPA OBRA'!D$1&", ","")& IF(INDEX('ETAPA OBRA'!F:F,MATCH($B47,'ETAPA OBRA'!$B:$B,0))="x",'ETAPA OBRA'!F$1&", ","")& IF(INDEX('ETAPA OBRA'!G:G,MATCH($B47,'ETAPA OBRA'!$B:$B,0))="x",'ETAPA OBRA'!G$1&", ","")& IF(INDEX('ETAPA OBRA'!H:H,MATCH($B47,'ETAPA OBRA'!$B:$B,0))="x",'ETAPA OBRA'!H$1&", ","")& IF(INDEX('ETAPA OBRA'!I:I,MATCH($B47,'ETAPA OBRA'!$B:$B,0))="x",'ETAPA OBRA'!I$1&", ","")& IF(INDEX('ETAPA OBRA'!J:J,MATCH($B47,'ETAPA OBRA'!$B:$B,0))="x",'ETAPA OBRA'!J$1&", ","")& IF(INDEX('ETAPA OBRA'!K:K,MATCH($B47,'ETAPA OBRA'!$B:$B,0))="x",'ETAPA OBRA'!K$1&", ","")& IF(INDEX('ETAPA OBRA'!L:L,MATCH($B47,'ETAPA OBRA'!$B:$B,0))="x",'ETAPA OBRA'!L$1&", ","")& IF(INDEX('ETAPA OBRA'!M:M,MATCH($B47,'ETAPA OBRA'!$B:$B,0))="x",'ETAPA OBRA'!M$1&", ","")& IF(INDEX('ETAPA OBRA'!N:N,MATCH($B47,'ETAPA OBRA'!$B:$B,0))="x",'ETAPA OBRA'!N$1&", ","")& IF(INDEX('ETAPA OBRA'!O:O,MATCH($B47,'ETAPA OBRA'!$B:$B,0))="x",'ETAPA OBRA'!O$1&", ","")& IF(INDEX('ETAPA OBRA'!P:P,MATCH($B47,'ETAPA OBRA'!$B:$B,0))="x",'ETAPA OBRA'!P$1&", ","")& IF(INDEX('ETAPA OBRA'!Q:Q,MATCH($B47,'ETAPA OBRA'!$B:$B,0))="x",'ETAPA OBRA'!Q$1&", ","")& IF(INDEX('ETAPA OBRA'!R:R,MATCH($B47,'ETAPA OBRA'!$B:$B,0))="x",'ETAPA OBRA'!R$1&", ","")& IF(INDEX('ETAPA OBRA'!S:S,MATCH($B47,'ETAPA OBRA'!$B:$B,0))="x",'ETAPA OBRA'!S$1&", ","")& IF(INDEX('ETAPA OBRA'!T:T,MATCH($B47,'ETAPA OBRA'!$B:$B,0))="x",'ETAPA OBRA'!T$1&", ","")& IF(INDEX('ETAPA OBRA'!U:U,MATCH($B47,'ETAPA OBRA'!$B:$B,0))="x",'ETAPA OBRA'!U$1&", ",""),LEN( IF(INDEX('ETAPA OBRA'!C:C,MATCH($B47,'ETAPA OBRA'!$B:$B,0))="x",'ETAPA OBRA'!C$1&", ","")& IF(INDEX('ETAPA OBRA'!D:D,MATCH($B47,'ETAPA OBRA'!$B:$B,0))="x",'ETAPA OBRA'!D$1&", ","")& IF(INDEX('ETAPA OBRA'!F:F,MATCH($B47,'ETAPA OBRA'!$B:$B,0))="x",'ETAPA OBRA'!F$1&", ","")& IF(INDEX('ETAPA OBRA'!G:G,MATCH($B47,'ETAPA OBRA'!$B:$B,0))="x",'ETAPA OBRA'!G$1&", ","")& IF(INDEX('ETAPA OBRA'!H:H,MATCH($B47,'ETAPA OBRA'!$B:$B,0))="x",'ETAPA OBRA'!H$1&", ","")& IF(INDEX('ETAPA OBRA'!I:I,MATCH($B47,'ETAPA OBRA'!$B:$B,0))="x",'ETAPA OBRA'!I$1&", ","")& IF(INDEX('ETAPA OBRA'!J:J,MATCH($B47,'ETAPA OBRA'!$B:$B,0))="x",'ETAPA OBRA'!J$1&", ","")& IF(INDEX('ETAPA OBRA'!K:K,MATCH($B47,'ETAPA OBRA'!$B:$B,0))="x",'ETAPA OBRA'!K$1&", ","")& IF(INDEX('ETAPA OBRA'!L:L,MATCH($B47,'ETAPA OBRA'!$B:$B,0))="x",'ETAPA OBRA'!L$1&", ","")& IF(INDEX('ETAPA OBRA'!M:M,MATCH($B47,'ETAPA OBRA'!$B:$B,0))="x",'ETAPA OBRA'!M$1&", ","")& IF(INDEX('ETAPA OBRA'!N:N,MATCH($B47,'ETAPA OBRA'!$B:$B,0))="x",'ETAPA OBRA'!N$1&", ","")& IF(INDEX('ETAPA OBRA'!O:O,MATCH($B47,'ETAPA OBRA'!$B:$B,0))="x",'ETAPA OBRA'!O$1&", ","")& IF(INDEX('ETAPA OBRA'!P:P,MATCH($B47,'ETAPA OBRA'!$B:$B,0))="x",'ETAPA OBRA'!P$1&", ","")& IF(INDEX('ETAPA OBRA'!Q:Q,MATCH($B47,'ETAPA OBRA'!$B:$B,0))="x",'ETAPA OBRA'!Q$1&", ","")& IF(INDEX('ETAPA OBRA'!R:R,MATCH($B47,'ETAPA OBRA'!$B:$B,0))="x",'ETAPA OBRA'!R$1&", ","")& IF(INDEX('ETAPA OBRA'!S:S,MATCH($B47,'ETAPA OBRA'!$B:$B,0))="x",'ETAPA OBRA'!S$1&", ","")& IF(INDEX('ETAPA OBRA'!T:T,MATCH($B47,'ETAPA OBRA'!$B:$B,0))="x",'ETAPA OBRA'!T$1&", ","")& IF(INDEX('ETAPA OBRA'!U:U,MATCH($B47,'ETAPA OBRA'!$B:$B,0))="x",'ETAPA OBRA'!U$1&", ","") )-2),"") -> Finalizado | N47: =IF(M47="","Não iniciada", IF(ISNUMBER(FIND("Cancelada",M47)),"Cancelada", IF(ISNUMBER(FIND("Paralisada",M47)),"Paralisada", IF(ISNUMBER(FIND("Finalizado",M47)),"Finalizado", "Em andamento")))) -> Finalizado | O47: 11928.07 | P47: =SUM($J47:$L47) -> 2352.42 | Q47: =O47-P47 -> 9575.65 | R47: =IF(O47=0,0,Q47/O47) -> 0.80278285 | S47: =IF(R47>=0.2,"✅ OK - Fechar Parceiro","⚠️ Ajustar Custos (<20%)") -> ✅ OK - Fechar Parceiro | T47: =Cronograma[[#This Row],[STATUS]] -> ✅ CONCLUÍDO
A48: BR72119-A | B48: =IF(A48<>"","contel-"&TEXT(COUNTA($A$2:A48),"00"),"") -> contel-47 | C48: SBA | D48: ITUIUTUBA | E48: MG | F48: https://maps.app.goo.gl/Sin5JLSmbvkHjBk27 | G48: 1755 | H48: 16211 | I48: DANILO | J48: =SUM(EQUIPE!C48,EQUIPE!E48,EQUIPE!G48,EQUIPE!I48,EQUIPE!K48,EQUIPE!M48,EQUIPE!O48) -> 11750 | K48: 21701.26 | L48: 271.46 | M48: =IFERROR(LEFT( IF(INDEX('ETAPA OBRA'!C:C,MATCH($B48,'ETAPA OBRA'!$B:$B,0))="x",'ETAPA OBRA'!C$1&", ","")& IF(INDEX('ETAPA OBRA'!D:D,MATCH($B48,'ETAPA OBRA'!$B:$B,0))="x",'ETAPA OBRA'!D$1&", ","")& IF(INDEX('ETAPA OBRA'!F:F,MATCH($B48,'ETAPA OBRA'!$B:$B,0))="x",'ETAPA OBRA'!F$1&", ","")& IF(INDEX('ETAPA OBRA'!G:G,MATCH($B48,'ETAPA OBRA'!$B:$B,0))="x",'ETAPA OBRA'!G$1&", ","")& IF(INDEX('ETAPA OBRA'!H:H,MATCH($B48,'ETAPA OBRA'!$B:$B,0))="x",'ETAPA OBRA'!H$1&", ","")& IF(INDEX('ETAPA OBRA'!I:I,MATCH($B48,'ETAPA OBRA'!$B:$B,0))="x",'ETAPA OBRA'!I$1&", ","")& IF(INDEX('ETAPA OBRA'!J:J,MATCH($B48,'ETAPA OBRA'!$B:$B,0))="x",'ETAPA OBRA'!J$1&", ","")& IF(INDEX('ETAPA OBRA'!K:K,MATCH($B48,'ETAPA OBRA'!$B:$B,0))="x",'ETAPA OBRA'!K$1&", ","")& IF(INDEX('ETAPA OBRA'!L:L,MATCH($B48,'ETAPA OBRA'!$B:$B,0))="x",'ETAPA OBRA'!L$1&", ","")& IF(INDEX('ETAPA OBRA'!M:M,MATCH($B48,'ETAPA OBRA'!$B:$B,0))="x",'ETAPA OBRA'!M$1&", ","")& IF(INDEX('ETAPA OBRA'!N:N,MATCH($B48,'ETAPA OBRA'!$B:$B,0))="x",'ETAPA OBRA'!N$1&", ","")& IF(INDEX('ETAPA OBRA'!O:O,MATCH($B48,'ETAPA OBRA'!$B:$B,0))="x",'ETAPA OBRA'!O$1&", ","")& IF(INDEX('ETAPA OBRA'!P:P,MATCH($B48,'ETAPA OBRA'!$B:$B,0))="x",'ETAPA OBRA'!P$1&", ","")& IF(INDEX('ETAPA OBRA'!Q:Q,MATCH($B48,'ETAPA OBRA'!$B:$B,0))="x",'ETAPA OBRA'!Q$1&", ","")& IF(INDEX('ETAPA OBRA'!R:R,MATCH($B48,'ETAPA OBRA'!$B:$B,0))="x",'ETAPA OBRA'!R$1&", ","")& IF(INDEX('ETAPA OBRA'!S:S,MATCH($B48,'ETAPA OBRA'!$B:$B,0))="x",'ETAPA OBRA'!S$1&", ","")& IF(INDEX('ETAPA OBRA'!T:T,MATCH($B48,'ETAPA OBRA'!$B:$B,0))="x",'ETAPA OBRA'!T$1&", ","")& IF(INDEX('ETAPA OBRA'!U:U,MATCH($B48,'ETAPA OBRA'!$B:$B,0))="x",'ETAPA OBRA'!U$1&", ",""),LEN( IF(INDEX('ETAPA OBRA'!C:C,MATCH($B48,'ETAPA OBRA'!$B:$B,0))="x",'ETAPA OBRA'!C$1&", ","")& IF(INDEX('ETAPA OBRA'!D:D,MATCH($B48,'ETAPA OBRA'!$B:$B,0))="x",'ETAPA OBRA'!D$1&", ","")& IF(INDEX('ETAPA OBRA'!F:F,MATCH($B48,'ETAPA OBRA'!$B:$B,0))="x",'ETAPA OBRA'!F$1&", ","")& IF(INDEX('ETAPA OBRA'!G:G,MATCH($B48,'ETAPA OBRA'!$B:$B,0))="x",'ETAPA OBRA'!G$1&", ","")& IF(INDEX('ETAPA OBRA'!H:H,MATCH($B48,'ETAPA OBRA'!$B:$B,0))="x",'ETAPA OBRA'!H$1&", ","")& IF(INDEX('ETAPA OBRA'!I:I,MATCH($B48,'ETAPA OBRA'!$B:$B,0))="x",'ETAPA OBRA'!I$1&", ","")& IF(INDEX('ETAPA OBRA'!J:J,MATCH($B48,'ETAPA OBRA'!$B:$B,0))="x",'ETAPA OBRA'!J$1&", ","")& IF(INDEX('ETAPA OBRA'!K:K,MATCH($B48,'ETAPA OBRA'!$B:$B,0))="x",'ETAPA OBRA'!K$1&", ","")& IF(INDEX('ETAPA OBRA'!L:L,MATCH($B48,'ETAPA OBRA'!$B:$B,0))="x",'ETAPA OBRA'!L$1&", ","")& IF(INDEX('ETAPA OBRA'!M:M,MATCH($B48,'ETAPA OBRA'!$B:$B,0))="x",'ETAPA OBRA'!M$1&", ","")& IF(INDEX('ETAPA OBRA'!N:N,MATCH($B48,'ETAPA OBRA'!$B:$B,0))="x",'ETAPA OBRA'!N$1&", ","")& IF(INDEX('ETAPA OBRA'!O:O,MATCH($B48,'ETAPA OBRA'!$B:$B,0))="x",'ETAPA OBRA'!O$1&", ","")& IF(INDEX('ETAPA OBRA'!P:P,MATCH($B48,'ETAPA OBRA'!$B:$B,0))="x",'ETAPA OBRA'!P$1&", ","")& IF(INDEX('ETAPA OBRA'!Q:Q,MATCH($B48,'ETAPA OBRA'!$B:$B,0))="x",'ETAPA OBRA'!Q$1&", ","")& IF(INDEX('ETAPA OBRA'!R:R,MATCH($B48,'ETAPA OBRA'!$B:$B,0))="x",'ETAPA OBRA'!R$1&", ","")& IF(INDEX('ETAPA OBRA'!S:S,MATCH($B48,'ETAPA OBRA'!$B:$B,0))="x",'ETAPA OBRA'!S$1&", ","")& IF(INDEX('ETAPA OBRA'!T:T,MATCH($B48,'ETAPA OBRA'!$B:$B,0))="x",'ETAPA OBRA'!T$1&", ","")& IF(INDEX('ETAPA OBRA'!U:U,MATCH($B48,'ETAPA OBRA'!$B:$B,0))="x",'ETAPA OBRA'!U$1&", ","") )-2),"") -> Finalizado | N48: =IF(M48="","Não iniciada", IF(ISNUMBER(FIND("Cancelada",M48)),"Cancelada", IF(ISNUMBER(FIND("Paralisada",M48)),"Paralisada", IF(ISNUMBER(FIND("Finalizado",M48)),"Finalizado", "Em andamento")))) -> Finalizado | O48: 42000 | P48: =SUM($J48:$L48) -> 33722.72 | Q48: =O48-P48 -> 8277.28 | R48: =IF(O48=0,0,Q48/O48) -> 0.1970781 | S48: =IF(R48>=0.2,"✅ OK - Fechar Parceiro","⚠️ Ajustar Custos (<20%)") -> ⚠️ Ajustar Custos (<20%) | T48: =Cronograma[[#This Row],[STATUS]] -> ✅ CONCLUÍDO
... A54: BR63121-A | B54: =IF(A54<>"","contel-"&TEXT(COUNTA($A$2:A54),"00"),"") -> contel-53 | C54: SBA | D54: CAAPIRANGA | E54: AM | F54: https://maps.app.goo.gl/LXQceEw8mfhTQUKn9 | G54: 1794 | H54: 16545 | I54: DANILO | J54: =SUM(EQUIPE!C54,EQUIPE!E54,EQUIPE!G54,EQUIPE!I54,EQUIPE!K54,EQUIPE!M54,EQUIPE!O54) -> 13500 | K54: 6254.86 | L54: 2935.59 | M54: =IFERROR(LEFT( IF(INDEX('ETAPA OBRA'!C:C,MATCH($B54,'ETAPA OBRA'!$B:$B,0))="x",'ETAPA OBRA'!C$1&", ","")& IF(INDEX('ETAPA OBRA'!D:D,MATCH($B54,'ETAPA OBRA'!$B:$B,0))="x",'ETAPA OBRA'!D$1&", ","")& IF(INDEX('ETAPA OBRA'!F:F,MATCH($B54,'ETAPA OBRA'!$B:$B,0))="x",'ETAPA OBRA'!F$1&", ","")& IF(INDEX('ETAPA OBRA'!G:G,MATCH($B54,'ETAPA OBRA'!$B:$B,0))="x",'ETAPA OBRA'!G$1&", ","")& IF(INDEX('ETAPA OBRA'!H:H,MATCH($B54,'ETAPA OBRA'!$B:$B,0))="x",'ETAPA OBRA'!H$1&", ","")& IF(INDEX('ETAPA OBRA'!I:I,MATCH($B54,'ETAPA OBRA'!$B:$B,0))="x",'ETAPA OBRA'!I$1&", ","")& IF(INDEX('ETAPA OBRA'!J:J,MATCH($B54,'ETAPA OBRA'!$B:$B,0))="x",'ETAPA OBRA'!J$1&", ","")& IF(INDEX('ETAPA OBRA'!K:K,MATCH($B54,'ETAPA OBRA'!$B:$B,0))="x",'ETAPA OBRA'!K$1&", ","")& IF(INDEX('ETAPA OBRA'!L:L,MATCH($B54,'ETAPA OBRA'!$B:$B,0))="x",'ETAPA OBRA'!L$1&", ","")& IF(INDEX('ETAPA OBRA'!M:M,MATCH($B54,'ETAPA OBRA'!$B:$B,0))="x",'ETAPA OBRA'!M$1&", ","")& IF(INDEX('ETAPA OBRA'!N:N,MATCH($B54,'ETAPA OBRA'!$B:$B,0))="x",'ETAPA OBRA'!N$1&", ","")& IF(INDEX('ETAPA OBRA'!O:O,MATCH($B54,'ETAPA OBRA'!$B:$B,0))="x",'ETAPA OBRA'!O$1&", ","")& IF(INDEX('ETAPA OBRA'!P:P,MATCH($B54,'ETAPA OBRA'!$B:$B,0))="x",'ETAPA OBRA'!P$1&", ","")& IF(INDEX('ETAPA OBRA'!Q:Q,MATCH($B54,'ETAPA OBRA'!$B:$B,0))="x",'ETAPA OBRA'!Q$1&", ","")& IF(INDEX('ETAPA OBRA'!R:R,MATCH($B54,'ETAPA OBRA'!$B:$B,0))="x",'ETAPA OBRA'!R$1&", ","")& IF(INDEX('ETAPA OBRA'!S:S,MATCH($B54,'ETAPA OBRA'!$B:$B,0))="x",'ETAPA OBRA'!S$1&", ","")& IF(INDEX('ETAPA OBRA'!T:T,MATCH($B54,'ETAPA OBRA'!$B:$B,0))="x",'ETAPA OBRA'!T$1&", ","")& IF(INDEX('ETAPA OBRA'!U:U,MATCH($B54,'ETAPA OBRA'!$B:$B,0))="x",'ETAPA OBRA'!U$1&", ",""),LEN( IF(INDEX('ETAPA OBRA'!C:C,MATCH($B54,'ETAPA OBRA'!$B:$B,0))="x",'ETAPA OBRA'!C$1&", ","")& IF(INDEX('ETAPA OBRA'!D:D,MATCH($B54,'ETAPA OBRA'!$B:$B,0))="x",'ETAPA OBRA'!D$1&", ","")& IF(INDEX('ETAPA OBRA'!F:F,MATCH($B54,'ETAPA OBRA'!$B:$B,0))="x",'ETAPA OBRA'!F$1&", ","")& IF(INDEX('ETAPA OBRA'!G:G,MATCH($B54,'ETAPA OBRA'!$B:$B,0))="x",'ETAPA OBRA'!G$1&", ","")& IF(INDEX('ETAPA OBRA'!H:H,MATCH($B54,'ETAPA OBRA'!$B:$B,0))="x",'ETAPA OBRA'!H$1&", ","")& IF(INDEX('ETAPA OBRA'!I:I,MATCH($B54,'ETAPA OBRA'!$B:$B,0))="x",'ETAPA OBRA'!I$1&", ","")& IF(INDEX('ETAPA OBRA'!J:J,MATCH($B54,'ETAPA OBRA'!$B:$B,0))="x",'ETAPA OBRA'!J$1&", ","")& IF(INDEX('ETAPA OBRA'!K:K,MATCH($B54,'ETAPA OBRA'!$B:$B,0))="x",'ETAPA OBRA'!K$1&", ","")& IF(INDEX('ETAPA OBRA'!L:L,MATCH($B54,'ETAPA OBRA'!$B:$B,0))="x",'ETAPA OBRA'!L$1&", ","")& IF(INDEX('ETAPA OBRA'!M:M,MATCH($B54,'ETAPA OBRA'!$B:$B,0))="x",'ETAPA OBRA'!M$1&", ","")& IF(INDEX('ETAPA OBRA'!N:N,MATCH($B54,'ETAPA OBRA'!$B:$B,0))="x",'ETAPA OBRA'!N$1&", ","")& IF(INDEX('ETAPA OBRA'!O:O,MATCH($B54,'ETAPA OBRA'!$B:$B,0))="x",'ETAPA OBRA'!O$1&", ","")& IF(INDEX('ETAPA OBRA'!P:P,MATCH($B54,'ETAPA OBRA'!$B:$B,0))="x",'ETAPA OBRA'!P$1&", ","")& IF(INDEX('ETAPA OBRA'!Q:Q,MATCH($B54,'ETAPA OBRA'!$B:$B,0))="x",'ETAPA OBRA'!Q$1&", ","")& IF(INDEX('ETAPA OBRA'!R:R,MATCH($B54,'ETAPA OBRA'!$B:$B,0))="x",'ETAPA OBRA'!R$1&", ","")& IF(INDEX('ETAPA OBRA'!S:S,MATCH($B54,'ETAPA OBRA'!$B:$B,0))="x",'ETAPA OBRA'!S$1&", ","")& IF(INDEX('ETAPA OBRA'!T:T,MATCH($B54,'ETAPA OBRA'!$B:$B,0))="x",'ETAPA OBRA'!T$1&", ","")& IF(INDEX('ETAPA OBRA'!U:U,MATCH($B54,'ETAPA OBRA'!$B:$B,0))="x",'ETAPA OBRA'!U$1&", ","") )-2),"") -> Execução | N54: =IF(M54="","Não iniciada", IF(ISNUMBER(FIND("Cancelada",M54)),"Cancelada", IF(ISNUMBER(FIND("Paralisada",M54)),"Paralisada", IF(ISNUMBER(FIND("Finalizado",M54)),"Finalizado", "Em andamento")))) -> Em andamento | O54: 49865.72 | P54: =SUM($J54:$L54) -> 22690.45 | Q54: =O54-P54 -> 27175.27 | R54: =IF(O54=0,0,Q54/O54) -> 0.54496897 | S54: =IF(R54>=0.2,"✅ OK - Fechar Parceiro","⚠️ Ajustar Custos (<20%)") -> ✅ OK - Fechar Parceiro | T54: =Cronograma[[#This Row],[STATUS]] -> ⏰ ATRASADO
A55: 38010003 | B55: =IF(A55<>"","contel-"&TEXT(COUNTA($A$2:A55),"00"),"") -> contel-54 | C55: IHS | D55: MONTES CLAROS | E55: MG | F55: https://maps.app.goo.gl/5oZ66QsoUhn4549a8 | G55: 1796 | H55: 16581 | I55: DANILO | J55: =SUM(EQUIPE!C55,EQUIPE!E55,EQUIPE!G55,EQUIPE!I55,EQUIPE!K55,EQUIPE!M55,EQUIPE!O55) -> 51000 | K55: 0 | L55: 5230.92 | M55: =IFERROR(LEFT( IF(INDEX('ETAPA OBRA'!C:C,MATCH($B55,'ETAPA OBRA'!$B:$B,0))="x",'ETAPA OBRA'!C$1&", ","")& IF(INDEX('ETAPA OBRA'!D:D,MATCH($B55,'ETAPA OBRA'!$B:$B,0))="x",'ETAPA OBRA'!D$1&", ","")& IF(INDEX('ETAPA OBRA'!F:F,MATCH($B55,'ETAPA OBRA'!$B:$B,0))="x",'ETAPA OBRA'!F$1&", ","")& IF(INDEX('ETAPA OBRA'!G:G,MATCH($B55,'ETAPA OBRA'!$B:$B,0))="x",'ETAPA OBRA'!G$1&", ","")& IF(INDEX('ETAPA OBRA'!H:H,MATCH($B55,'ETAPA OBRA'!$B:$B,0))="x",'ETAPA OBRA'!H$1&", ","")& IF(INDEX('ETAPA OBRA'!I:I,MATCH($B55,'ETAPA OBRA'!$B:$B,0))="x",'ETAPA OBRA'!I$1&", ","")& IF(INDEX('ETAPA OBRA'!J:J,MATCH($B55,'ETAPA OBRA'!$B:$B,0))="x",'ETAPA OBRA'!J$1&", ","")& IF(INDEX('ETAPA OBRA'!K:K,MATCH($B55,'ETAPA OBRA'!$B:$B,0))="x",'ETAPA OBRA'!K$1&", ","")& IF(INDEX('ETAPA OBRA'!L:L,MATCH($B55,'ETAPA OBRA'!$B:$B,0))="x",'ETAPA OBRA'!L$1&", ","")& IF(INDEX('ETAPA OBRA'!M:M,MATCH($B55,'ETAPA OBRA'!$B:$B,0))="x",'ETAPA OBRA'!M$1&", ","")& IF(INDEX('ETAPA OBRA'!N:N,MATCH($B55,'ETAPA OBRA'!$B:$B,0))="x",'ETAPA OBRA'!N$1&", ","")& IF(INDEX('ETAPA OBRA'!O:O,MATCH($B55,'ETAPA OBRA'!$B:$B,0))="x",'ETAPA OBRA'!O$1&", ","")& IF(INDEX('ETAPA OBRA'!P:P,MATCH($B55,'ETAPA OBRA'!$B:$B,0))="x",'ETAPA OBRA'!P$1&", ","")& IF(INDEX('ETAPA OBRA'!Q:Q,MATCH($B55,'ETAPA OBRA'!$B:$B,0))="x",'ETAPA OBRA'!Q$1&", ","")& IF(INDEX('ETAPA OBRA'!R:R,MATCH($B55,'ETAPA OBRA'!$B:$B,0))="x",'ETAPA OBRA'!R$1&", ","")& IF(INDEX('ETAPA OBRA'!S:S,MATCH($B55,'ETAPA OBRA'!$B:$B,0))="x",'ETAPA OBRA'!S$1&", ","")& IF(INDEX('ETAPA OBRA'!T:T,MATCH($B55,'ETAPA OBRA'!$B:$B,0))="x",'ETAPA OBRA'!T$1&", ","")& IF(INDEX('ETAPA OBRA'!U:U,MATCH($B55,'ETAPA OBRA'!$B:$B,0))="x",'ETAPA OBRA'!U$1&", ",""),LEN( IF(INDEX('ETAPA OBRA'!C:C,MATCH($B55,'ETAPA OBRA'!$B:$B,0))="x",'ETAPA OBRA'!C$1&", ","")& IF(INDEX('ETAPA OBRA'!D:D,MATCH($B55,'ETAPA OBRA'!$B:$B,0))="x",'ETAPA OBRA'!D$1&", ","")& IF(INDEX('ETAPA OBRA'!F:F,MATCH($B55,'ETAPA OBRA'!$B:$B,0))="x",'ETAPA OBRA'!F$1&", ","")& IF(INDEX('ETAPA OBRA'!G:G,MATCH($B55,'ETAPA OBRA'!$B:$B,0))="x",'ETAPA OBRA'!G$1&", ","")& IF(INDEX('ETAPA OBRA'!H:H,MATCH($B55,'ETAPA OBRA'!$B:$B,0))="x",'ETAPA OBRA'!H$1&", ","")& IF(INDEX('ETAPA OBRA'!I:I,MATCH($B55,'ETAPA OBRA'!$B:$B,0))="x",'ETAPA OBRA'!I$1&", ","")& IF(INDEX('ETAPA OBRA'!J:J,MATCH($B55,'ETAPA OBRA'!$B:$B,0))="x",'ETAPA OBRA'!J$1&", ","")& IF(INDEX('ETAPA OBRA'!K:K,MATCH($B55,'ETAPA OBRA'!$B:$B,0))="x",'ETAPA OBRA'!K$1&", ","")& IF(INDEX('ETAPA OBRA'!L:L,MATCH($B55,'ETAPA OBRA'!$B:$B,0))="x",'ETAPA OBRA'!L$1&", ","")& IF(INDEX('ETAPA OBRA'!M:M,MATCH($B55,'ETAPA OBRA'!$B:$B,0))="x",'ETAPA OBRA'!M$1&", ","")& IF(INDEX('ETAPA OBRA'!N:N,MATCH($B55,'ETAPA OBRA'!$B:$B,0))="x",'ETAPA OBRA'!N$1&", ","")& IF(INDEX('ETAPA OBRA'!O:O,MATCH($B55,'ETAPA OBRA'!$B:$B,0))="x",'ETAPA OBRA'!O$1&", ","")& IF(INDEX('ETAPA OBRA'!P:P,MATCH($B55,'ETAPA OBRA'!$B:$B,0))="x",'ETAPA OBRA'!P$1&", ","")& IF(INDEX('ETAPA OBRA'!Q:Q,MATCH($B55,'ETAPA OBRA'!$B:$B,0))="x",'ETAPA OBRA'!Q$1&", ","")& IF(INDEX('ETAPA OBRA'!R:R,MATCH($B55,'ETAPA OBRA'!$B:$B,0))="x",'ETAPA OBRA'!R$1&", ","")& IF(INDEX('ETAPA OBRA'!S:S,MATCH($B55,'ETAPA OBRA'!$B:$B,0))="x",'ETAPA OBRA'!S$1&", ","")& IF(INDEX('ETAPA OBRA'!T:T,MATCH($B55,'ETAPA OBRA'!$B:$B,0))="x",'ETAPA OBRA'!T$1&", ","")& IF(INDEX('ETAPA OBRA'!U:U,MATCH($B55,'ETAPA OBRA'!$B:$B,0))="x",'ETAPA OBRA'!U$1&", ","") )-2),"") -> Execução | N55: =IF(M55="","Não iniciada", IF(ISNUMBER(FIND("Cancelada",M55)),"Cancelada", IF(ISNUMBER(FIND("Paralisada",M55)),"Paralisada", IF(ISNUMBER(FIND("Finalizado",M55)),"Finalizado", "Em andamento")))) -> Em andamento | O55: 120000 | P55: =SUM($J55:$L55) -> 56230.92 | Q55: =O55-P55 -> 63769.08 | R55: =IF(O55=0,0,Q55/O55) -> 0.531409 | S55: =IF(R55>=0.2,"✅ OK - Fechar Parceiro","⚠️ Ajustar Custos (<20%)") -> ✅ OK - Fechar Parceiro | T55: =Cronograma[[#This Row],[STATUS]] -> ⏰ ATRASADO
A56: TORRE RECORD | B56: =IF(A56<>"","contel-"&TEXT(COUNTA($A$2:A56),"00"),"") -> contel-55 | C56: RECORD | D56: CAMPO GRANDE | E56: MS | F56: https://maps.app.goo.gl/tNwDZEiEZkeZ1tw97 | G56: 1799 | H56: 16612 | I56: PEDRO | J56: =SUM(EQUIPE!C56,EQUIPE!E56,EQUIPE!G56,EQUIPE!I56,EQUIPE!K56,EQUIPE!M56,EQUIPE!O56) -> 1900 | K56: 0 | L56: 0 | M56: =IFERROR(LEFT( IF(INDEX('ETAPA OBRA'!C:C,MATCH($B56,'ETAPA OBRA'!$B:$B,0))="x",'ETAPA OBRA'!C$1&", ","")& IF(INDEX('ETAPA OBRA'!D:D,MATCH($B56,'ETAPA OBRA'!$B:$B,0))="x",'ETAPA OBRA'!D$1&", ","")& IF(INDEX('ETAPA OBRA'!F:F,MATCH($B56,'ETAPA OBRA'!$B:$B,0))="x",'ETAPA OBRA'!F$1&", ","")& IF(INDEX('ETAPA OBRA'!G:G,MATCH($B56,'ETAPA OBRA'!$B:$B,0))="x",'ETAPA OBRA'!G$1&", ","")& IF(INDEX('ETAPA OBRA'!H:H,MATCH($B56,'ETAPA OBRA'!$B:$B,0))="x",'ETAPA OBRA'!H$1&", ","")& IF(INDEX('ETAPA OBRA'!I:I,MATCH($B56,'ETAPA OBRA'!$B:$B,0))="x",'ETAPA OBRA'!I$1&", ","")& IF(INDEX('ETAPA OBRA'!J:J,MATCH($B56,'ETAPA OBRA'!$B:$B,0))="x",'ETAPA OBRA'!J$1&", ","")& IF(INDEX('ETAPA OBRA'!K:K,MATCH($B56,'ETAPA OBRA'!$B:$B,0))="x",'ETAPA OBRA'!K$1&", ","")& IF(INDEX('ETAPA OBRA'!L:L,MATCH($B56,'ETAPA OBRA'!$B:$B,0))="x",'ETAPA OBRA'!L$1&", ","")& IF(INDEX('ETAPA OBRA'!M:M,MATCH($B56,'ETAPA OBRA'!$B:$B,0))="x",'ETAPA OBRA'!M$1&", ","")& IF(INDEX('ETAPA OBRA'!N:N,MATCH($B56,'ETAPA OBRA'!$B:$B,0))="x",'ETAPA OBRA'!N$1&", ","")& IF(INDEX('ETAPA OBRA'!O:O,MATCH($B56,'ETAPA OBRA'!$B:$B,0))="x",'ETAPA OBRA'!O$1&", ","")& IF(INDEX('ETAPA OBRA'!P:P,MATCH($B56,'ETAPA OBRA'!$B:$B,0))="x",'ETAPA OBRA'!P$1&", ","")& IF(INDEX('ETAPA OBRA'!Q:Q,MATCH($B56,'ETAPA OBRA'!$B:$B,0))="x",'ETAPA OBRA'!Q$1&", ","")& IF(INDEX('ETAPA OBRA'!R:R,MATCH($B56,'ETAPA OBRA'!$B:$B,0))="x",'ETAPA OBRA'!R$1&", ","")& IF(INDEX('ETAPA OBRA'!S:S,MATCH($B56,'ETAPA OBRA'!$B:$B,0))="x",'ETAPA OBRA'!S$1&", ","")& IF(INDEX('ETAPA OBRA'!T:T,MATCH($B56,'ETAPA OBRA'!$B:$B,0))="x",'ETAPA OBRA'!T$1&", ","")& IF(INDEX('ETAPA OBRA'!U:U,MATCH($B56,'ETAPA OBRA'!$B:$B,0))="x",'ETAPA OBRA'!U$1&", ",""),LEN( IF(INDEX('ETAPA OBRA'!C:C,MATCH($B56,'ETAPA OBRA'!$B:$B,0))="x",'ETAPA OBRA'!C$1&", ","")& IF(INDEX('ETAPA OBRA'!D:D,MATCH($B56,'ETAPA OBRA'!$B:$B,0))="x",'ETAPA OBRA'!D$1&", ","")& IF(INDEX('ETAPA OBRA'!F:F,MATCH($B56,'ETAPA OBRA'!$B:$B,0))="x",'ETAPA OBRA'!F$1&", ","")& IF(INDEX('ETAPA OBRA'!G:G,MATCH($B56,'ETAPA OBRA'!$B:$B,0))="x",'ETAPA OBRA'!G$1&", ","")& IF(INDEX('ETAPA OBRA'!H:H,MATCH($B56,'ETAPA OBRA'!$B:$B,0))="x",'ETAPA OBRA'!H$1&", ","")& IF(INDEX('ETAPA OBRA'!I:I,MATCH($B56,'ETAPA OBRA'!$B:$B,0))="x",'ETAPA OBRA'!I$1&", ","")& IF(INDEX('ETAPA OBRA'!J:J,MATCH($B56,'ETAPA OBRA'!$B:$B,0))="x",'ETAPA OBRA'!J$1&", ","")& IF(INDEX('ETAPA OBRA'!K:K,MATCH($B56,'ETAPA OBRA'!$B:$B,0))="x",'ETAPA OBRA'!K$1&", ","")& IF(INDEX('ETAPA OBRA'!L:L,MATCH($B56,'ETAPA OBRA'!$B:$B,0))="x",'ETAPA OBRA'!L$1&", ","")& IF(INDEX('ETAPA OBRA'!M:M,MATCH($B56,'ETAPA OBRA'!$B:$B,0))="x",'ETAPA OBRA'!M$1&", ","")& IF(INDEX('ETAPA OBRA'!N:N,MATCH($B56,'ETAPA OBRA'!$B:$B,0))="x",'ETAPA OBRA'!N$1&", ","")& IF(INDEX('ETAPA OBRA'!O:O,MATCH($B56,'ETAPA OBRA'!$B:$B,0))="x",'ETAPA OBRA'!O$1&", ","")& IF(INDEX('ETAPA OBRA'!P:P,MATCH($B56,'ETAPA OBRA'!$B:$B,0))="x",'ETAPA OBRA'!P$1&", ","")& IF(INDEX('ETAPA OBRA'!Q:Q,MATCH($B56,'ETAPA OBRA'!$B:$B,0))="x",'ETAPA OBRA'!Q$1&", ","")& IF(INDEX('ETAPA OBRA'!R:R,MATCH($B56,'ETAPA OBRA'!$B:$B,0))="x",'ETAPA OBRA'!R$1&", ","")& IF(INDEX('ETAPA OBRA'!S:S,MATCH($B56,'ETAPA OBRA'!$B:$B,0))="x",'ETAPA OBRA'!S$1&", ","")& IF(INDEX('ETAPA OBRA'!T:T,MATCH($B56,'ETAPA OBRA'!$B:$B,0))="x",'ETAPA OBRA'!T$1&", ","")& IF(INDEX('ETAPA OBRA'!U:U,MATCH($B56,'ETAPA OBRA'!$B:$B,0))="x",'ETAPA OBRA'!U$1&", ","") )-2),"") -> Finalizado | N56: =IF(M56="","Não iniciada", IF(ISNUMBER(FIND("Cancelada",M56)),"Cancelada", IF(ISNUMBER(FIND("Paralisada",M56)),"Paralisada", IF(ISNUMBER(FIND("Finalizado",M56)),"Finalizado", "Em andamento")))) -> Finalizado | O56: 8000 | P56: =SUM($J56:$L56) -> 1900 | Q56: =O56-P56 -> 6100 | R56: =IF(O56=0,0,Q56/O56) -> 0.7625 | S56: =IF(R56>=0.2,"✅ OK - Fechar Parceiro","⚠️ Ajustar Custos (<20%)") -> ✅ OK - Fechar Parceiro | T56: =Cronograma[[#This Row],[STATUS]] -> ✅ CONCLUÍDO
A57: MABCY001 | B57: =IF(A57<>"","contel-"&TEXT(COUNTA($A$2:A57),"00"),"") -> contel-56 | C57: HLB | D57: BACURITUBA | E57: MA | F57: https://maps.app.goo.gl/LSnUkKvUxFXntyix6 | G57: 1803 | H57: 16615 | I57: PEDRO | J57: =SUM(EQUIPE!C57,EQUIPE!E57,EQUIPE!G57,EQUIPE!I57,EQUIPE!K57,EQUIPE!M57,EQUIPE!O57) -> 5260 | K57: 0 | L57: 285.59 | M57: =IFERROR(LEFT( IF(INDEX('ETAPA OBRA'!C:C,MATCH($B57,'ETAPA OBRA'!$B:$B,0))="x",'ETAPA OBRA'!C$1&", ","")& IF(INDEX('ETAPA OBRA'!D:D,MATCH($B57,'ETAPA OBRA'!$B:$B,0))="x",'ETAPA OBRA'!D$1&", ","")& IF(INDEX('ETAPA OBRA'!F:F,MATCH($B57,'ETAPA OBRA'!$B:$B,0))="x",'ETAPA OBRA'!F$1&", ","")& IF(INDEX('ETAPA OBRA'!G:G,MATCH($B57,'ETAPA OBRA'!$B:$B,0))="x",'ETAPA OBRA'!G$1&", ","")& IF(INDEX('ETAPA OBRA'!H:H,MATCH($B57,'ETAPA OBRA'!$B:$B,0))="x",'ETAPA OBRA'!H$1&", ","")& IF(INDEX('ETAPA OBRA'!I:I,MATCH($B57,'ETAPA OBRA'!$B:$B,0))="x",'ETAPA OBRA'!I$1&", ","")& IF(INDEX('ETAPA OBRA'!J:J,MATCH($B57,'ETAPA OBRA'!$B:$B,0))="x",'ETAPA OBRA'!J$1&", ","")& IF(INDEX('ETAPA OBRA'!K:K,MATCH($B57,'ETAPA OBRA'!$B:$B,0))="x",'ETAPA OBRA'!K$1&", ","")& IF(INDEX('ETAPA OBRA'!L:L,MATCH($B57,'ETAPA OBRA'!$B:$B,0))="x",'ETAPA OBRA'!L$1&", ","")& IF(INDEX('ETAPA OBRA'!M:M,MATCH($B57,'ETAPA OBRA'!$B:$B,0))="x",'ETAPA OBRA'!M$1&", ","")& IF(INDEX('ETAPA OBRA'!N:N,MATCH($B57,'ETAPA OBRA'!$B:$B,0))="x",'ETAPA OBRA'!N$1&", ","")& IF(INDEX('ETAPA OBRA'!O:O,MATCH($B57,'ETAPA OBRA'!$B:$B,0))="x",'ETAPA OBRA'!O$1&", ","")& IF(INDEX('ETAPA OBRA'!P:P,MATCH($B57,'ETAPA OBRA'!$B:$B,0))="x",'ETAPA OBRA'!P$1&", ","")& IF(INDEX('ETAPA OBRA'!Q:Q,MATCH($B57,'ETAPA OBRA'!$B:$B,0))="x",'ETAPA OBRA'!Q$1&", ","")& IF(INDEX('ETAPA OBRA'!R:R,MATCH($B57,'ETAPA OBRA'!$B:$B,0))="x",'ETAPA OBRA'!R$1&", ","")& IF(INDEX('ETAPA OBRA'!S:S,MATCH($B57,'ETAPA OBRA'!$B:$B,0))="x",'ETAPA OBRA'!S$1&", ","")& IF(INDEX('ETAPA OBRA'!T:T,MATCH($B57,'ETAPA OBRA'!$B:$B,0))="x",'ETAPA OBRA'!T$1&", ","")& IF(INDEX('ETAPA OBRA'!U:U,MATCH($B57,'ETAPA OBRA'!$B:$B,0))="x",'ETAPA OBRA'!U$1&", ",""),LEN( IF(INDEX('ETAPA OBRA'!C:C,MATCH($B57,'ETAPA OBRA'!$B:$B,0))="x",'ETAPA OBRA'!C$1&", ","")& IF(INDEX('ETAPA OBRA'!D:D,MATCH($B57,'ETAPA OBRA'!$B:$B,0))="x",'ETAPA OBRA'!D$1&", ","")& IF(INDEX('ETAPA OBRA'!F:F,MATCH($B57,'ETAPA OBRA'!$B:$B,0))="x",'ETAPA OBRA'!F$1&", ","")& IF(INDEX('ETAPA OBRA'!G:G,MATCH($B57,'ETAPA OBRA'!$B:$B,0))="x",'ETAPA OBRA'!G$1&", ","")& IF(INDEX('ETAPA OBRA'!H:H,MATCH($B57,'ETAPA OBRA'!$B:$B,0))="x",'ETAPA OBRA'!H$1&", ","")& IF(INDEX('ETAPA OBRA'!I:I,MATCH($B57,'ETAPA OBRA'!$B:$B,0))="x",'ETAPA OBRA'!I$1&", ","")& IF(INDEX('ETAPA OBRA'!J:J,MATCH($B57,'ETAPA OBRA'!$B:$B,0))="x",'ETAPA OBRA'!J$1&", ","")& IF(INDEX('ETAPA OBRA'!K:K,MATCH($B57,'ETAPA OBRA'!$B:$B,0))="x",'ETAPA OBRA'!K$1&", ","")& IF(INDEX('ETAPA OBRA'!L:L,MATCH($B57,'ETAPA OBRA'!$B:$B,0))="x",'ETAPA OBRA'!L$1&", ","")& IF(INDEX('ETAPA OBRA'!M:M,MATCH($B57,'ETAPA OBRA'!$B:$B,0))="x",'ETAPA OBRA'!M$1&", ","")& IF(INDEX('ETAPA OBRA'!N:N,MATCH($B57,'ETAPA OBRA'!$B:$B,0))="x",'ETAPA OBRA'!N$1&", ","")& IF(INDEX('ETAPA OBRA'!O:O,MATCH($B57,'ETAPA OBRA'!$B:$B,0))="x",'ETAPA OBRA'!O$1&", ","")& IF(INDEX('ETAPA OBRA'!P:P,MATCH($B57,'ETAPA OBRA'!$B:$B,0))="x",'ETAPA OBRA'!P$1&", ","")& IF(INDEX('ETAPA OBRA'!Q:Q,MATCH($B57,'ETAPA OBRA'!$B:$B,0))="x",'ETAPA OBRA'!Q$1&", ","")& IF(INDEX('ETAPA OBRA'!R:R,MATCH($B57,'ETAPA OBRA'!$B:$B,0))="x",'ETAPA OBRA'!R$1&", ","")& IF(INDEX('ETAPA OBRA'!S:S,MATCH($B57,'ETAPA OBRA'!$B:$B,0))="x",'ETAPA OBRA'!S$1&", ","")& IF(INDEX('ETAPA OBRA'!T:T,MATCH($B57,'ETAPA OBRA'!$B:$B,0))="x",'ETAPA OBRA'!T$1&", ","")& IF(INDEX('ETAPA OBRA'!U:U,MATCH($B57,'ETAPA OBRA'!$B:$B,0))="x",'ETAPA OBRA'!U$1&", ","") )-2),"") -> Finalizado | N57: =IF(M57="","Não iniciada", IF(ISNUMBER(FIND("Cancelada",M57)),"Cancelada", IF(ISNUMBER(FIND("Paralisada",M57)),"Paralisada", IF(ISNUMBER(FIND("Finalizado",M57)),"Finalizado", "Em andamento")))) -> Finalizado | O57: 17050 | P57: =SUM($J57:$L57) -> 5545.59 | Q57: =O57-P57 -> 11504.41 | R57: =IF(O57=0,0,Q57/O57) -> 0.67474545 | S57: =IF(R57>=0.2,"✅ OK - Fechar Parceiro","⚠️ Ajustar Custos (<20%)") -> ✅ OK - Fechar Parceiro | T57: =Cronograma[[#This Row],[STATUS]] -> ✅ CONCLUÍDO
A58: PARMX006 | B58: =IF(A58<>"","contel-"&TEXT(COUNTA($A$2:A58),"00"),"") -> contel-57 | C58: HLB | D58: SANTAREM | E58: PA | F58: https://maps.app.goo.gl/s2G195KrffKjBL5D8 | G58: 1804 | H58: 16616 | I58: PEDRO | J58: =SUM(EQUIPE!C58,EQUIPE!E58,EQUIPE!G58,EQUIPE!I58,EQUIPE!K58,EQUIPE!M58,EQUIPE!O58) -> 6060 | K58: 2500 | L58: 285.59 | M58: =IFERROR(LEFT( IF(INDEX('ETAPA OBRA'!C:C,MATCH($B58,'ETAPA OBRA'!$B:$B,0))="x",'ETAPA OBRA'!C$1&", ","")& IF(INDEX('ETAPA OBRA'!D:D,MATCH($B58,'ETAPA OBRA'!$B:$B,0))="x",'ETAPA OBRA'!D$1&", ","")& IF(INDEX('ETAPA OBRA'!F:F,MATCH($B58,'ETAPA OBRA'!$B:$B,0))="x",'ETAPA OBRA'!F$1&", ","")& IF(INDEX('ETAPA OBRA'!G:G,MATCH($B58,'ETAPA OBRA'!$B:$B,0))="x",'ETAPA OBRA'!G$1&", ","")& IF(INDEX('ETAPA OBRA'!H:H,MATCH($B58,'ETAPA OBRA'!$B:$B,0))="x",'ETAPA OBRA'!H$1&", ","")& IF(INDEX('ETAPA OBRA'!I:I,MATCH($B58,'ETAPA OBRA'!$B:$B,0))="x",'ETAPA OBRA'!I$1&", ","")& IF(INDEX('ETAPA OBRA'!J:J,MATCH($B58,'ETAPA OBRA'!$B:$B,0))="x",'ETAPA OBRA'!J$1&", ","")& IF(INDEX('ETAPA OBRA'!K:K,MATCH($B58,'ETAPA OBRA'!$B:$B,0))="x",'ETAPA OBRA'!K$1&", ","")& IF(INDEX('ETAPA OBRA'!L:L,MATCH($B58,'ETAPA OBRA'!$B:$B,0))="x",'ETAPA OBRA'!L$1&", ","")& IF(INDEX('ETAPA OBRA'!M:M,MATCH($B58,'ETAPA OBRA'!$B:$B,0))="x",'ETAPA OBRA'!M$1&", ","")& IF(INDEX('ETAPA OBRA'!N:N,MATCH($B58,'ETAPA OBRA'!$B:$B,0))="x",'ETAPA OBRA'!N$1&", ","")& IF(INDEX('ETAPA OBRA'!O:O,MATCH($B58,'ETAPA OBRA'!$B:$B,0))="x",'ETAPA OBRA'!O$1&", ","")& IF(INDEX('ETAPA OBRA'!P:P,MATCH($B58,'ETAPA OBRA'!$B:$B,0))="x",'ETAPA OBRA'!P$1&", ","")& IF(INDEX('ETAPA OBRA'!Q:Q,MATCH($B58,'ETAPA OBRA'!$B:$B,0))="x",'ETAPA OBRA'!Q$1&", ","")& IF(INDEX('ETAPA OBRA'!R:R,MATCH($B58,'ETAPA OBRA'!$B:$B,0))="x",'ETAPA OBRA'!R$1&", ","")& IF(INDEX('ETAPA OBRA'!S:S,MATCH($B58,'ETAPA OBRA'!$B:$B,0))="x",'ETAPA OBRA'!S$1&", ","")& IF(INDEX('ETAPA OBRA'!T:T,MATCH($B58,'ETAPA OBRA'!$B:$B,0))="x",'ETAPA OBRA'!T$1&", ","")& IF(INDEX('ETAPA OBRA'!U:U,MATCH($B58,'ETAPA OBRA'!$B:$B,0))="x",'ETAPA OBRA'!U$1&", ",""),LEN( IF(INDEX('ETAPA OBRA'!C:C,MATCH($B58,'ETAPA OBRA'!$B:$B,0))="x",'ETAPA OBRA'!C$1&", ","")& IF(INDEX('ETAPA OBRA'!D:D,MATCH($B58,'ETAPA OBRA'!$B:$B,0))="x",'ETAPA OBRA'!D$1&", ","")& IF(INDEX('ETAPA OBRA'!F:F,MATCH($B58,'ETAPA OBRA'!$B:$B,0))="x",'ETAPA OBRA'!F$1&", ","")& IF(INDEX('ETAPA OBRA'!G:G,MATCH($B58,'ETAPA OBRA'!$B:$B,0))="x",'ETAPA OBRA'!G$1&", ","")& IF(INDEX('ETAPA OBRA'!H:H,MATCH($B58,'ETAPA OBRA'!$B:$B,0))="x",'ETAPA OBRA'!H$1&", ","")& IF(INDEX('ETAPA OBRA'!I:I,MATCH($B58,'ETAPA OBRA'!$B:$B,0))="x",'ETAPA OBRA'!I$1&", ","")& IF(INDEX('ETAPA OBRA'!J:J,MATCH($B58,'ETAPA OBRA'!$B:$B,0))="x",'ETAPA OBRA'!J$1&", ","")& IF(INDEX('ETAPA OBRA'!K:K,MATCH($B58,'ETAPA OBRA'!$B:$B,0))="x",'ETAPA OBRA'!K$1&", ","")& IF(INDEX('ETAPA OBRA'!L:L,MATCH($B58,'ETAPA OBRA'!$B:$B,0))="x",'ETAPA OBRA'!L$1&", ","")& IF(INDEX('ETAPA OBRA'!M:M,MATCH($B58,'ETAPA OBRA'!$B:$B,0))="x",'ETAPA OBRA'!M$1&", ","")& IF(INDEX('ETAPA OBRA'!N:N,MATCH($B58,'ETAPA OBRA'!$B:$B,0))="x",'ETAPA OBRA'!N$1&", ","")& IF(INDEX('ETAPA OBRA'!O:O,MATCH($B58,'ETAPA OBRA'!$B:$B,0))="x",'ETAPA OBRA'!O$1&", ","")& IF(INDEX('ETAPA OBRA'!P:P,MATCH($B58,'ETAPA OBRA'!$B:$B,0))="x",'ETAPA OBRA'!P$1&", ","")& IF(INDEX('ETAPA OBRA'!Q:Q,MATCH($B58,'ETAPA OBRA'!$B:$B,0))="x",'ETAPA OBRA'!Q$1&", ","")& IF(INDEX('ETAPA OBRA'!R:R,MATCH($B58,'ETAPA OBRA'!$B:$B,0))="x",'ETAPA OBRA'!R$1&", ","")& IF(INDEX('ETAPA OBRA'!S:S,MATCH($B58,'ETAPA OBRA'!$B:$B,0))="x",'ETAPA OBRA'!S$1&", ","")& IF(INDEX('ETAPA OBRA'!T:T,MATCH($B58,'ETAPA OBRA'!$B:$B,0))="x",'ETAPA OBRA'!T$1&", ","")& IF(INDEX('ETAPA OBRA'!U:U,MATCH($B58,'ETAPA OBRA'!$B:$B,0))="x",'ETAPA OBRA'!U$1&", ","") )-2),"") -> Projeto | N58: =IF(M58="","Não iniciada", IF(ISNUMBER(FIND("Cancelada",M58)),"Cancelada", IF(ISNUMBER(FIND("Paralisada",M58)),"Paralisada", IF(ISNUMBER(FIND("Finalizado",M58)),"Finalizado", "Em andamento")))) -> Em andamento | O58: 21010 | P58: =SUM($J58:$L58) -> 8845.59 | Q58: =O58-P58 -> 12164.41 | R58: =IF(O58=0,0,Q58/O58) -> 0.57898191 | S58: =IF(R58>=0.2,"✅ OK - Fechar Parceiro","⚠️ Ajustar Custos (<20%)") -> ✅ OK - Fechar Parceiro | T58: =Cronograma[[#This Row],[STATUS]] -> ⏰ ATRASADO
A59: MAVNX001 | B59: =IF(A59<>"","contel-"&TEXT(COUNTA($A$2:A59),"00"),"") -> contel-58 | C59: HLB | D59: VIANA | E59: MA | F59: https://maps.app.goo.gl/b436xVT5jq5BGn767 | G59: 1802 | H59: 16617 | I59: PEDRO | J59: =SUM(EQUIPE!C59,EQUIPE!E59,EQUIPE!G59,EQUIPE!I59,EQUIPE!K59,EQUIPE!M59,EQUIPE!O59) -> 5760 | K59: 4500 | L59: 285.59 | M59: =IFERROR(LEFT( IF(INDEX('ETAPA OBRA'!C:C,MATCH($B59,'ETAPA OBRA'!$B:$B,0))="x",'ETAPA OBRA'!C$1&", ","")& IF(INDEX('ETAPA OBRA'!D:D,MATCH($B59,'ETAPA OBRA'!$B:$B,0))="x",'ETAPA OBRA'!D$1&", ","")& IF(INDEX('ETAPA OBRA'!F:F,MATCH($B59,'ETAPA OBRA'!$B:$B,0))="x",'ETAPA OBRA'!F$1&", ","")& IF(INDEX('ETAPA OBRA'!G:G,MATCH($B59,'ETAPA OBRA'!$B:$B,0))="x",'ETAPA OBRA'!G$1&", ","")& IF(INDEX('ETAPA OBRA'!H:H,MATCH($B59,'ETAPA OBRA'!$B:$B,0))="x",'ETAPA OBRA'!H$1&", ","")& IF(INDEX('ETAPA OBRA'!I:I,MATCH($B59,'ETAPA OBRA'!$B:$B,0))="x",'ETAPA OBRA'!I$1&", ","")& IF(INDEX('ETAPA OBRA'!J:J,MATCH($B59,'ETAPA OBRA'!$B:$B,0))="x",'ETAPA OBRA'!J$1&", ","")& IF(INDEX('ETAPA OBRA'!K:K,MATCH($B59,'ETAPA OBRA'!$B:$B,0))="x",'ETAPA OBRA'!K$1&", ","")& IF(INDEX('ETAPA OBRA'!L:L,MATCH($B59,'ETAPA OBRA'!$B:$B,0))="x",'ETAPA OBRA'!L$1&", ","")& IF(INDEX('ETAPA OBRA'!M:M,MATCH($B59,'ETAPA OBRA'!$B:$B,0))="x",'ETAPA OBRA'!M$1&", ","")& IF(INDEX('ETAPA OBRA'!N:N,MATCH($B59,'ETAPA OBRA'!$B:$B,0))="x",'ETAPA OBRA'!N$1&", ","")& IF(INDEX('ETAPA OBRA'!O:O,MATCH($B59,'ETAPA OBRA'!$B:$B,0))="x",'ETAPA OBRA'!O$1&", ","")& IF(INDEX('ETAPA OBRA'!P:P,MATCH($B59,'ETAPA OBRA'!$B:$B,0))="x",'ETAPA OBRA'!P$1&", ","")& IF(INDEX('ETAPA OBRA'!Q:Q,MATCH($B59,'ETAPA OBRA'!$B:$B,0))="x",'ETAPA OBRA'!Q$1&", ","")& IF(INDEX('ETAPA OBRA'!R:R,MATCH($B59,'ETAPA OBRA'!$B:$B,0))="x",'ETAPA OBRA'!R$1&", ","")& IF(INDEX('ETAPA OBRA'!S:S,MATCH($B59,'ETAPA OBRA'!$B:$B,0))="x",'ETAPA OBRA'!S$1&", ","")& IF(INDEX('ETAPA OBRA'!T:T,MATCH($B59,'ETAPA OBRA'!$B:$B,0))="x",'ETAPA OBRA'!T$1&", ","")& IF(INDEX('ETAPA OBRA'!U:U,MATCH($B59,'ETAPA OBRA'!$B:$B,0))="x",'ETAPA OBRA'!U$1&", ",""),LEN( IF(INDEX('ETAPA OBRA'!C:C,MATCH($B59,'ETAPA OBRA'!$B:$B,0))="x",'ETAPA OBRA'!C$1&", ","")& IF(INDEX('ETAPA OBRA'!D:D,MATCH($B59,'ETAPA OBRA'!$B:$B,0))="x",'ETAPA OBRA'!D$1&", ","")& IF(INDEX('ETAPA OBRA'!F:F,MATCH($B59,'ETAPA OBRA'!$B:$B,0))="x",'ETAPA OBRA'!F$1&", ","")& IF(INDEX('ETAPA OBRA'!G:G,MATCH($B59,'ETAPA OBRA'!$B:$B,0))="x",'ETAPA OBRA'!G$1&", ","")& IF(INDEX('ETAPA OBRA'!H:H,MATCH($B59,'ETAPA OBRA'!$B:$B,0))="x",'ETAPA OBRA'!H$1&", ","")& IF(INDEX('ETAPA OBRA'!I:I,MATCH($B59,'ETAPA OBRA'!$B:$B,0))="x",'ETAPA OBRA'!I$1&", ","")& IF(INDEX('ETAPA OBRA'!J:J,MATCH($B59,'ETAPA OBRA'!$B:$B,0))="x",'ETAPA OBRA'!J$1&", ","")& IF(INDEX('ETAPA OBRA'!K:K,MATCH($B59,'ETAPA OBRA'!$B:$B,0))="x",'ETAPA OBRA'!K$1&", ","")& IF(INDEX('ETAPA OBRA'!L:L,MATCH($B59,'ETAPA OBRA'!$B:$B,0))="x",'ETAPA OBRA'!L$1&", ","")& IF(INDEX('ETAPA OBRA'!M:M,MATCH($B59,'ETAPA OBRA'!$B:$B,0))="x",'ETAPA OBRA'!M$1&", ","")& IF(INDEX('ETAPA OBRA'!N:N,MATCH($B59,'ETAPA OBRA'!$B:$B,0))="x",'ETAPA OBRA'!N$1&", ","")& IF(INDEX('ETAPA OBRA'!O:O,MATCH($B59,'ETAPA OBRA'!$B:$B,0))="x",'ETAPA OBRA'!O$1&", ","")& IF(INDEX('ETAPA OBRA'!P:P,MATCH($B59,'ETAPA OBRA'!$B:$B,0))="x",'ETAPA OBRA'!P$1&", ","")& IF(INDEX('ETAPA OBRA'!Q:Q,MATCH($B59,'ETAPA OBRA'!$B:$B,0))="x",'ETAPA OBRA'!Q$1&", ","")& IF(INDEX('ETAPA OBRA'!R:R,MATCH($B59,'ETAPA OBRA'!$B:$B,0))="x",'ETAPA OBRA'!R$1&", ","")& IF(INDEX('ETAPA OBRA'!S:S,MATCH($B59,'ETAPA OBRA'!$B:$B,0))="x",'ETAPA OBRA'!S$1&", ","")& IF(INDEX('ETAPA OBRA'!T:T,MATCH($B59,'ETAPA OBRA'!$B:$B,0))="x",'ETAPA OBRA'!T$1&", ","")& IF(INDEX('ETAPA OBRA'!U:U,MATCH($B59,'ETAPA OBRA'!$B:$B,0))="x",'ETAPA OBRA'!U$1&", ","") )-2),"") -> Finalizado | N59: =IF(M59="","Não iniciada", IF(ISNUMBER(FIND("Cancelada",M59)),"Cancelada", IF(ISNUMBER(FIND("Paralisada",M59)),"Paralisada", IF(ISNUMBER(FIND("Finalizado",M59)),"Finalizado", "Em andamento")))) -> Finalizado | O59: 21010 | P59: =SUM($J59:$L59) -> 10545.59 | Q59: =O59-P59 -> 10464.41 | R59: =IF(O59=0,0,Q59/O59) -> 0.49806806 | S59: =IF(R59>=0.2,"✅ OK - Fechar Parceiro","⚠️ Ajustar Custos (<20%)") -> ✅ OK - Fechar Parceiro | T59: =Cronograma[[#This Row],[STATUS]] -> ✅ CONCLUÍDO
A60: TNSMOSA002 | B60: =IF(A60<>"","contel-"&TEXT(COUNTA($A$2:A60),"00"),"") -> contel-59 | C60: TBSA | D60: OSASCO | E60: SP | F60: https://maps.app.goo.gl/WaGrFBd7bzCFcKf59 | G60: 1801 | H60: 16620 | I60: DANILO | J60: =SUM(EQUIPE!C60,EQUIPE!E60,EQUIPE!G60,EQUIPE!I60,EQUIPE!K60,EQUIPE!M60,EQUIPE!O60) -> 24500 | K60: 0 | L60: 285.59 | M60: =IFERROR(LEFT( IF(INDEX('ETAPA OBRA'!C:C,MATCH($B60,'ETAPA OBRA'!$B:$B,0))="x",'ETAPA OBRA'!C$1&", ","")& IF(INDEX('ETAPA OBRA'!D:D,MATCH($B60,'ETAPA OBRA'!$B:$B,0))="x",'ETAPA OBRA'!D$1&", ","")& IF(INDEX('ETAPA OBRA'!F:F,MATCH($B60,'ETAPA OBRA'!$B:$B,0))="x",'ETAPA OBRA'!F$1&", ","")& IF(INDEX('ETAPA OBRA'!G:G,MATCH($B60,'ETAPA OBRA'!$B:$B,0))="x",'ETAPA OBRA'!G$1&", ","")& IF(INDEX('ETAPA OBRA'!H:H,MATCH($B60,'ETAPA OBRA'!$B:$B,0))="x",'ETAPA OBRA'!H$1&", ","")& IF(INDEX('ETAPA OBRA'!I:I,MATCH($B60,'ETAPA OBRA'!$B:$B,0))="x",'ETAPA OBRA'!I$1&", ","")& IF(INDEX('ETAPA OBRA'!J:J,MATCH($B60,'ETAPA OBRA'!$B:$B,0))="x",'ETAPA OBRA'!J$1&", ","")& IF(INDEX('ETAPA OBRA'!K:K,MATCH($B60,'ETAPA OBRA'!$B:$B,0))="x",'ETAPA OBRA'!K$1&", ","")& IF(INDEX('ETAPA OBRA'!L:L,MATCH($B60,'ETAPA OBRA'!$B:$B,0))="x",'ETAPA OBRA'!L$1&", ","")& IF(INDEX('ETAPA OBRA'!M:M,MATCH($B60,'ETAPA OBRA'!$B:$B,0))="x",'ETAPA OBRA'!M$1&", ","")& IF(INDEX('ETAPA OBRA'!N:N,MATCH($B60,'ETAPA OBRA'!$B:$B,0))="x",'ETAPA OBRA'!N$1&", ","")& IF(INDEX('ETAPA OBRA'!O:O,MATCH($B60,'ETAPA OBRA'!$B:$B,0))="x",'ETAPA OBRA'!O$1&", ","")& IF(INDEX('ETAPA OBRA'!P:P,MATCH($B60,'ETAPA OBRA'!$B:$B,0))="x",'ETAPA OBRA'!P$1&", ","")& IF(INDEX('ETAPA OBRA'!Q:Q,MATCH($B60,'ETAPA OBRA'!$B:$B,0))="x",'ETAPA OBRA'!Q$1&", ","")& IF(INDEX('ETAPA OBRA'!R:R,MATCH($B60,'ETAPA OBRA'!$B:$B,0))="x",'ETAPA OBRA'!R$1&", ","")& IF(INDEX('ETAPA OBRA'!S:S,MATCH($B60,'ETAPA OBRA'!$B:$B,0))="x",'ETAPA OBRA'!S$1&", ","")& IF(INDEX('ETAPA OBRA'!T:T,MATCH($B60,'ETAPA OBRA'!$B:$B,0))="x",'ETAPA OBRA'!T$1&", ","")& IF(INDEX('ETAPA OBRA'!U:U,MATCH($B60,'ETAPA OBRA'!$B:$B,0))="x",'ETAPA OBRA'!U$1&", ",""),LEN( IF(INDEX('ETAPA OBRA'!C:C,MATCH($B60,'ETAPA OBRA'!$B:$B,0))="x",'ETAPA OBRA'!C$1&", ","")& IF(INDEX('ETAPA OBRA'!D:D,MATCH($B60,'ETAPA OBRA'!$B:$B,0))="x",'ETAPA OBRA'!D$1&", ","")& IF(INDEX('ETAPA OBRA'!F:F,MATCH($B60,'ETAPA OBRA'!$B:$B,0))="x",'ETAPA OBRA'!F$1&", ","")& IF(INDEX('ETAPA OBRA'!G:G,MATCH($B60,'ETAPA OBRA'!$B:$B,0))="x",'ETAPA OBRA'!G$1&", ","")& IF(INDEX('ETAPA OBRA'!H:H,MATCH($B60,'ETAPA OBRA'!$B:$B,0))="x",'ETAPA OBRA'!H$1&", ","")& IF(INDEX('ETAPA OBRA'!I:I,MATCH($B60,'ETAPA OBRA'!$B:$B,0))="x",'ETAPA OBRA'!I$1&", ","")& IF(INDEX('ETAPA OBRA'!J:J,MATCH($B60,'ETAPA OBRA'!$B:$B,0))="x",'ETAPA OBRA'!J$1&", ","")& IF(INDEX('ETAPA OBRA'!K:K,MATCH($B60,'ETAPA OBRA'!$B:$B,0))="x",'ETAPA OBRA'!K$1&", ","")& IF(INDEX('ETAPA OBRA'!L:L,MATCH($B60,'ETAPA OBRA'!$B:$B,0))="x",'ETAPA OBRA'!L$1&", ","")& IF(INDEX('ETAPA OBRA'!M:M,MATCH($B60,'ETAPA OBRA'!$B:$B,0))="x",'ETAPA OBRA'!M$1&", ","")& IF(INDEX('ETAPA OBRA'!N:N,MATCH($B60,'ETAPA OBRA'!$B:$B,0))="x",'ETAPA OBRA'!N$1&", ","")& IF(INDEX('ETAPA OBRA'!O:O,MATCH($B60,'ETAPA OBRA'!$B:$B,0))="x",'ETAPA OBRA'!O$1&", ","")& IF(INDEX('ETAPA OBRA'!P:P,MATCH($B60,'ETAPA OBRA'!$B:$B,0))="x",'ETAPA OBRA'!P$1&", ","")& IF(INDEX('ETAPA OBRA'!Q:Q,MATCH($B60,'ETAPA OBRA'!$B:$B,0))="x",'ETAPA OBRA'!Q$1&", ","")& IF(INDEX('ETAPA OBRA'!R:R,MATCH($B60,'ETAPA OBRA'!$B:$B,0))="x",'ETAPA OBRA'!R$1&", ","")& IF(INDEX('ETAPA OBRA'!S:S,MATCH($B60,'ETAPA OBRA'!$B:$B,0))="x",'ETAPA OBRA'!S$1&", ","")& IF(INDEX('ETAPA OBRA'!T:T,MATCH($B60,'ETAPA OBRA'!$B:$B,0))="x",'ETAPA OBRA'!T$1&", ","")& IF(INDEX('ETAPA OBRA'!U:U,MATCH($B60,'ETAPA OBRA'!$B:$B,0))="x",'ETAPA OBRA'!U$1&", ","") )-2),"") -> Finalizado | N60: =IF(M60="","Não iniciada", IF(ISNUMBER(FIND("Cancelada",M60)),"Cancelada", IF(ISNUMBER(FIND("Paralisada",M60)),"Paralisada", IF(ISNUMBER(FIND("Finalizado",M60)),"Finalizado", "Em andamento")))) -> Finalizado | O60: 62994.5 | P60: =SUM($J60:$L60) -> 24785.59 | Q60: =O60-P60 -> 38208.91 | R60: =IF(O60=0,0,Q60/O60) -> 0.60654359 | S60: =IF(R60>=0.2,"✅ OK - Fechar Parceiro","⚠️ Ajustar Custos (<20%)") -> ✅ OK - Fechar Parceiro | T60: =Cronograma[[#This Row],[STATUS]] -> ✅ CONCLUÍDO
A61: 65010027 | B61: =IF(A61<>"","contel-"&TEXT(COUNTA($A$2:A61),"00"),"") -> contel-60 | C61: IHS | D61: CUIABÁ | E61: MT | F61: https://maps.app.goo.gl/2A2y88uHnsUmC5j8A | G61: 1714 | H61: 16625 | I61: DANILO | J61: =SUM(EQUIPE!C61,EQUIPE!E61,EQUIPE!G61,EQUIPE!I61,EQUIPE!K61,EQUIPE!M61,EQUIPE!O61) -> 3000 | K61: 1190.5 | L61: 2721.47 | M61: =IFERROR(LEFT( IF(INDEX('ETAPA OBRA'!C:C,MATCH($B61,'ETAPA OBRA'!$B:$B,0))="x",'ETAPA OBRA'!C$1&", ","")& IF(INDEX('ETAPA OBRA'!D:D,MATCH($B61,'ETAPA OBRA'!$B:$B,0))="x",'ETAPA OBRA'!D$1&", ","")& IF(INDEX('ETAPA OBRA'!F:F,MATCH($B61,'ETAPA OBRA'!$B:$B,0))="x",'ETAPA OBRA'!F$1&", ","")& IF(INDEX('ETAPA OBRA'!G:G,MATCH($B61,'ETAPA OBRA'!$B:$B,0))="x",'ETAPA OBRA'!G$1&", ","")& IF(INDEX('ETAPA OBRA'!H:H,MATCH($B61,'ETAPA OBRA'!$B:$B,0))="x",'ETAPA OBRA'!H$1&", ","")& IF(INDEX('ETAPA OBRA'!I:I,MATCH($B61,'ETAPA OBRA'!$B:$B,0))="x",'ETAPA OBRA'!I$1&", ","")& IF(INDEX('ETAPA OBRA'!J:J,MATCH($B61,'ETAPA OBRA'!$B:$B,0))="x",'ETAPA OBRA'!J$1&", ","")& IF(INDEX('ETAPA OBRA'!K:K,MATCH($B61,'ETAPA OBRA'!$B:$B,0))="x",'ETAPA OBRA'!K$1&", ","")& IF(INDEX('ETAPA OBRA'!L:L,MATCH($B61,'ETAPA OBRA'!$B:$B,0))="x",'ETAPA OBRA'!L$1&", ","")& IF(INDEX('ETAPA OBRA'!M:M,MATCH($B61,'ETAPA OBRA'!$B:$B,0))="x",'ETAPA OBRA'!M$1&", ","")& IF(INDEX('ETAPA OBRA'!N:N,MATCH($B61,'ETAPA OBRA'!$B:$B,0))="x",'ETAPA OBRA'!N$1&", ","")& IF(INDEX('ETAPA OBRA'!O:O,MATCH($B61,'ETAPA OBRA'!$B:$B,0))="x",'ETAPA OBRA'!O$1&", ","")& IF(INDEX('ETAPA OBRA'!P:P,MATCH($B61,'ETAPA OBRA'!$B:$B,0))="x",'ETAPA OBRA'!P$1&", ","")& IF(INDEX('ETAPA OBRA'!Q:Q,MATCH($B61,'ETAPA OBRA'!$B:$B,0))="x",'ETAPA OBRA'!Q$1&", ","")& IF(INDEX('ETAPA OBRA'!R:R,MATCH($B61,'ETAPA OBRA'!$B:$B,0))="x",'ETAPA OBRA'!R$1&", ","")& IF(INDEX('ETAPA OBRA'!S:S,MATCH($B61,'ETAPA OBRA'!$B:$B,0))="x",'ETAPA OBRA'!S$1&", ","")& IF(INDEX('ETAPA OBRA'!T:T,MATCH($B61,'ETAPA OBRA'!$B:$B,0))="x",'ETAPA OBRA'!T$1&", ","")& IF(INDEX('ETAPA OBRA'!U:U,MATCH($B61,'ETAPA OBRA'!$B:$B,0))="x",'ETAPA OBRA'!U$1&", ",""),LEN( IF(INDEX('ETAPA OBRA'!C:C,MATCH($B61,'ETAPA OBRA'!$B:$B,0))="x",'ETAPA OBRA'!C$1&", ","")& IF(INDEX('ETAPA OBRA'!D:D,MATCH($B61,'ETAPA OBRA'!$B:$B,0))="x",'ETAPA OBRA'!D$1&", ","")& IF(INDEX('ETAPA OBRA'!F:F,MATCH($B61,'ETAPA OBRA'!$B:$B,0))="x",'ETAPA OBRA'!F$1&", ","")& IF(INDEX('ETAPA OBRA'!G:G,MATCH($B61,'ETAPA OBRA'!$B:$B,0))="x",'ETAPA OBRA'!G$1&", ","")& IF(INDEX('ETAPA OBRA'!H:H,MATCH($B61,'ETAPA OBRA'!$B:$B,0))="x",'ETAPA OBRA'!H$1&", ","")& IF(INDEX('ETAPA OBRA'!I:I,MATCH($B61,'ETAPA OBRA'!$B:$B,0))="x",'ETAPA OBRA'!I$1&", ","")& IF(INDEX('ETAPA OBRA'!J:J,MATCH($B61,'ETAPA OBRA'!$B:$B,0))="x",'ETAPA OBRA'!J$1&", ","")& IF(INDEX('ETAPA OBRA'!K:K,MATCH($B61,'ETAPA OBRA'!$B:$B,0))="x",'ETAPA OBRA'!K$1&", ","")& IF(INDEX('ETAPA OBRA'!L:L,MATCH($B61,'ETAPA OBRA'!$B:$B,0))="x",'ETAPA OBRA'!L$1&", ","")& IF(INDEX('ETAPA OBRA'!M:M,MATCH($B61,'ETAPA OBRA'!$B:$B,0))="x",'ETAPA OBRA'!M$1&", ","")& IF(INDEX('ETAPA OBRA'!N:N,MATCH($B61,'ETAPA OBRA'!$B:$B,0))="x",'ETAPA OBRA'!N$1&", ","")& IF(INDEX('ETAPA OBRA'!O:O,MATCH($B61,'ETAPA OBRA'!$B:$B,0))="x",'ETAPA OBRA'!O$1&", ","")& IF(INDEX('ETAPA OBRA'!P:P,MATCH($B61,'ETAPA OBRA'!$B:$B,0))="x",'ETAPA OBRA'!P$1&", ","")& IF(INDEX('ETAPA OBRA'!Q:Q,MATCH($B61,'ETAPA OBRA'!$B:$B,0))="x",'ETAPA OBRA'!Q$1&", ","")& IF(INDEX('ETAPA OBRA'!R:R,MATCH($B61,'ETAPA OBRA'!$B:$B,0))="x",'ETAPA OBRA'!R$1&", ","")& IF(INDEX('ETAPA OBRA'!S:S,MATCH($B61,'ETAPA OBRA'!$B:$B,0))="x",'ETAPA OBRA'!S$1&", ","")& IF(INDEX('ETAPA OBRA'!T:T,MATCH($B61,'ETAPA OBRA'!$B:$B,0))="x",'ETAPA OBRA'!T$1&", ","")& IF(INDEX('ETAPA OBRA'!U:U,MATCH($B61,'ETAPA OBRA'!$B:$B,0))="x",'ETAPA OBRA'!U$1&", ","") )-2),"") -> Finalizado | N61: =IF(M61="","Não iniciada", IF(ISNUMBER(FIND("Cancelada",M61)),"Cancelada", IF(ISNUMBER(FIND("Paralisada",M61)),"Paralisada", IF(ISNUMBER(FIND("Finalizado",M61)),"Finalizado", "Em andamento")))) -> Finalizado | O61: 28395.24 | P61: =SUM($J61:$L61) -> 6911.97 | Q61: =O61-P61 -> 21483.27 | R61: =IF(O61=0,0,Q61/O61) -> 0.75657998 | S61: =IF(R61>=0.2,"✅ OK - Fechar Parceiro","⚠️ Ajustar Custos (<20%)") -> ✅ OK - Fechar Parceiro | T61: =Cronograma[[#This Row],[STATUS]] -> ✅ CONCLUÍDO
A62: BR88606-A | B62: =IF(A62<>"","contel-"&TEXT(COUNTA($A$2:A62),"00"),"") -> contel-61 | C62: SBA | D62: MANAUS | E62: AM | F62: https://maps.app.goo.gl/rdzBb461qeisgEP99 | G62: 1805 | H62: 16632 | I62: DANILO | J62: =SUM(EQUIPE!C62,EQUIPE!E62,EQUIPE!G62,EQUIPE!I62,EQUIPE!K62,EQUIPE!M62,EQUIPE!O62) -> 12000 | K62: 4163 | L62: 0 | M62: =IFERROR(LEFT( IF(INDEX('ETAPA OBRA'!C:C,MATCH($B62,'ETAPA OBRA'!$B:$B,0))="x",'ETAPA OBRA'!C$1&", ","")& IF(INDEX('ETAPA OBRA'!D:D,MATCH($B62,'ETAPA OBRA'!$B:$B,0))="x",'ETAPA OBRA'!D$1&", ","")& IF(INDEX('ETAPA OBRA'!F:F,MATCH($B62,'ETAPA OBRA'!$B:$B,0))="x",'ETAPA OBRA'!F$1&", ","")& IF(INDEX('ETAPA OBRA'!G:G,MATCH($B62,'ETAPA OBRA'!$B:$B,0))="x",'ETAPA OBRA'!G$1&", ","")& IF(INDEX('ETAPA OBRA'!H:H,MATCH($B62,'ETAPA OBRA'!$B:$B,0))="x",'ETAPA OBRA'!H$1&", ","")& IF(INDEX('ETAPA OBRA'!I:I,MATCH($B62,'ETAPA OBRA'!$B:$B,0))="x",'ETAPA OBRA'!I$1&", ","")& IF(INDEX('ETAPA OBRA'!J:J,MATCH($B62,'ETAPA OBRA'!$B:$B,0))="x",'ETAPA OBRA'!J$1&", ","")& IF(INDEX('ETAPA OBRA'!K:K,MATCH($B62,'ETAPA OBRA'!$B:$B,0))="x",'ETAPA OBRA'!K$1&", ","")& IF(INDEX('ETAPA OBRA'!L:L,MATCH($B62,'ETAPA OBRA'!$B:$B,0))="x",'ETAPA OBRA'!L$1&", ","")& IF(INDEX('ETAPA OBRA'!M:M,MATCH($B62,'ETAPA OBRA'!$B:$B,0))="x",'ETAPA OBRA'!M$1&", ","")& IF(INDEX('ETAPA OBRA'!N:N,MATCH($B62,'ETAPA OBRA'!$B:$B,0))="x",'ETAPA OBRA'!N$1&", ","")& IF(INDEX('ETAPA OBRA'!O:O,MATCH($B62,'ETAPA OBRA'!$B:$B,0))="x",'ETAPA OBRA'!O$1&", ","")& IF(INDEX('ETAPA OBRA'!P:P,MATCH($B62,'ETAPA OBRA'!$B:$B,0))="x",'ETAPA OBRA'!P$1&", ","")& IF(INDEX('ETAPA OBRA'!Q:Q,MATCH($B62,'ETAPA OBRA'!$B:$B,0))="x",'ETAPA OBRA'!Q$1&", ","")& IF(INDEX('ETAPA OBRA'!R:R,MATCH($B62,'ETAPA OBRA'!$B:$B,0))="x",'ETAPA OBRA'!R$1&", ","")& IF(INDEX('ETAPA OBRA'!S:S,MATCH($B62,'ETAPA OBRA'!$B:$B,0))="x",'ETAPA OBRA'!S$1&", ","")& IF(INDEX('ETAPA OBRA'!T:T,MATCH($B62,'ETAPA OBRA'!$B:$B,0))="x",'ETAPA OBRA'!T$1&", ","")& IF(INDEX('ETAPA OBRA'!U:U,MATCH($B62,'ETAPA OBRA'!$B:$B,0))="x",'ETAPA OBRA'!U$1&", ",""),LEN( IF(INDEX('ETAPA OBRA'!C:C,MATCH($B62,'ETAPA OBRA'!$B:$B,0))="x",'ETAPA OBRA'!C$1&", ","")& IF(INDEX('ETAPA OBRA'!D:D,MATCH($B62,'ETAPA OBRA'!$B:$B,0))="x",'ETAPA OBRA'!D$1&", ","")& IF(INDEX('ETAPA OBRA'!F:F,MATCH($B62,'ETAPA OBRA'!$B:$B,0))="x",'ETAPA OBRA'!F$1&", ","")& IF(INDEX('ETAPA OBRA'!G:G,MATCH($B62,'ETAPA OBRA'!$B:$B,0))="x",'ETAPA OBRA'!G$1&", ","")& IF(INDEX('ETAPA OBRA'!H:H,MATCH($B62,'ETAPA OBRA'!$B:$B,0))="x",'ETAPA OBRA'!H$1&", ","")& IF(INDEX('ETAPA OBRA'!I:I,MATCH($B62,'ETAPA OBRA'!$B:$B,0))="x",'ETAPA OBRA'!I$1&", ","")& IF(INDEX('ETAPA OBRA'!J:J,MATCH($B62,'ETAPA OBRA'!$B:$B,0))="x",'ETAPA OBRA'!J$1&", ","")& IF(INDEX('ETAPA OBRA'!K:K,MATCH($B62,'ETAPA OBRA'!$B:$B,0))="x",'ETAPA OBRA'!K$1&", ","")& IF(INDEX('ETAPA OBRA'!L:L,MATCH($B62,'ETAPA OBRA'!$B:$B,0))="x",'ETAPA OBRA'!L$1&", ","")& IF(INDEX('ETAPA OBRA'!M:M,MATCH($B62,'ETAPA OBRA'!$B:$B,0))="x",'ETAPA OBRA'!M$1&", ","")& IF(INDEX('ETAPA OBRA'!N:N,MATCH($B62,'ETAPA OBRA'!$B:$B,0))="x",'ETAPA OBRA'!N$1&", ","")& IF(INDEX('ETAPA OBRA'!O:O,MATCH($B62,'ETAPA OBRA'!$B:$B,0))="x",'ETAPA OBRA'!O$1&", ","")& IF(INDEX('ETAPA OBRA'!P:P,MATCH($B62,'ETAPA OBRA'!$B:$B,0))="x",'ETAPA OBRA'!P$1&", ","")& IF(INDEX('ETAPA OBRA'!Q:Q,MATCH($B62,'ETAPA OBRA'!$B:$B,0))="x",'ETAPA OBRA'!Q$1&", ","")& IF(INDEX('ETAPA OBRA'!R:R,MATCH($B62,'ETAPA OBRA'!$B:$B,0))="x",'ETAPA OBRA'!R$1&", ","")& IF(INDEX('ETAPA OBRA'!S:S,MATCH($B62,'ETAPA OBRA'!$B:$B,0))="x",'ETAPA OBRA'!S$1&", ","")& IF(INDEX('ETAPA OBRA'!T:T,MATCH($B62,'ETAPA OBRA'!$B:$B,0))="x",'ETAPA OBRA'!T$1&", ","")& IF(INDEX('ETAPA OBRA'!U:U,MATCH($B62,'ETAPA OBRA'!$B:$B,0))="x",'ETAPA OBRA'!U$1&", ","") )-2),"") -> Execução | N62: =IF(M62="","Não iniciada", IF(ISNUMBER(FIND("Cancelada",M62)),"Cancelada", IF(ISNUMBER(FIND("Paralisada",M62)),"Paralisada", IF(ISNUMBER(FIND("Finalizado",M62)),"Finalizado", "Em andamento")))) -> Em andamento | O62: 43936.3 | P62: =SUM($J62:$L62) -> 16163 | Q62: =O62-P62 -> 27773.3 | R62: =IF(O62=0,0,Q62/O62) -> 0.63212651 | S62: =IF(R62>=0.2,"✅ OK - Fechar Parceiro","⚠️ Ajustar Custos (<20%)") -> ✅ OK - Fechar Parceiro | T62: =Cronograma[[#This Row],[STATUS]] -> ⏰ ATRASADO
